Workbook

Sheet TABLE
A1: =(CONCATENATE("PG_CI_",(MID(B4,4,LEN(B4)-4)))) -> PG_CI_CUSTOMER
A3: PK | B3: Nombre Campo | C3: Tipo Dato
A4: X | B4: [K_CUSTOMER] | C4: [INT]
B5: [D_CUSTOMER] | C5: [VARCHAR](500)
B6: [C_CUSTOMER] | C6: [VARCHAR](500)
B7: [S_CUSTOMER] | C7: [VARCHAR](10)
B8: [K_COUNTRY] | C8: [INT]
B9: [K_STATE_GEO] | C9: [INT]
B10: [CUSTOMER_CITY] | C10: [VARCHAR](100)
B11: [D_CUSTOMER_ADDRESS_01] | C11: [VARCHAR](500)
B12: [D_CUSTOMER_ADDRESS_02] | C12: [VARCHAR](500)
B13: [CUSTOMER_POSTAL_CODE] | C13: [INT]
B14: [F_CUSTOMER_DATE] | C14: [DATE]
B15: [O_CUSTOMER] | C15: [INT]
B16: [L_CUSTOMER] | C16: [INT]
C24: [SLSPSN_NO] | D24: [CUST_TYPE_CD] | E24: [COLLECTOR] | F24: [CURR_CD] | G24: [CMT_2] | H24: [CMT_1] | I24: [HOLD_FG]

Sheet CI_
A1: ??? | B1: L_DEBUG | C1: K_SISTEMA_EXE | D1: K_USUARIO_ACCION | E1: [K_CUSTOMER] | F1: [D_CUSTOMER] | G1: [C_CUSTOMER] | H1: [S_CUSTOMER] | I1: [K_CONTINENTE] | J1: [K_COUNTRY] | K1: [K_STATE_GEO] | L1: [CUSTOMER_CITY] | M1: [D_CUSTOMER_ADDRESS_01] | N1: [D_CUSTOMER_ADDRESS_02] | O1: [CUSTOMER_POSTAL_CODE] | P1: [F_CUSTOMER_DATE] | Q1: [O_CUSTOMER] | R1: [L_CUSTOMER] | S1: [EMAIL] | T1: [SLSPSN_NO] | U1: [CUST_TYPE_CD] | V1: [COLLECTOR] | W1: [CURR_CD] | X1: [CMT_2] | Y1: [CMT_1] | Z1: [HOLD_FG] | AB1: EXECUTE [dbo].[ | AC1: PG_CI_ARCUSFIL_SQL | AD1: ] | AE1: =CONCATENATE($AB$1,$AC$1,$AD$1,B3, ", ", C3, ", ", D3, ", ", ) -> EXECUTE [dbo].[PG_CI_ARCUSFIL_SQL] 0, 0, 0,
B2: 0 | C2: 0 | D2: 0 | E2: 1 | F2: CNI INC | G2: CNI INC | H2: CNII01 | I2: 200 | J2: 221 | K2: 54 | L2: TROY | M2: 1148 ROCHESTER ROAD | O2: 48083 | P2: 1998-05-22 | Q2: =E2 -> 1 | R2: 1 | T2: 2 | U2: MCUEX | W2: USD | X2: FOB ACUNA | Y2: N/A | Z2: N | AB2: =CONCATENATE(CI_!$AE$1,E2,", '",F2,"', '",G2,"' , '",H2,"' , ",I2,",",J2," , ",K2,", '",L2,"', '",M2,"' ,'",N2,"' , '",O2,"' , '",P2,"' , '",Q2,"' , '",R2,"','",S2,"','",T2,"','",U2,"','",V2,"','",W2,"','",X2,"','",Y2,"','",Z2,"'") -> EXECUTE [dbo].[PG_CI_ARCUSFIL_SQL] 0, 0, 0, 1, 'CNI INC', 'CNI INC' , 'CNII01' , 200,221 , 54, 'TROY', '1148 ROCHESTER ROAD' ,'' , '48083' , '1998-05-22' , '1' , '1','','2','MCUEX','','USD','FOB ACUNA','N/A','N'
B3: 0 | C3: 0 | D3: 0 | E3: 2 | F3: EBINGER BROTHERS LEATHER COMPANY | G3: EBINGER BROTHERS LEATHER COMPANY | H3: EBIN01 | I3: 200 | J3: 221 | K3: 53 | L3: MASSACHUSETTS | M3: 44 MITCHELL ROAD | N3: IPSWICH | O3: 1938 | P3: 2001-02-12 | Q3: =E3 -> 2 | R3: 1 | T3: 2 | U3: MSUEX | W3: USD | Y3: N/A | Z3: N | AB3: =CONCATENATE(CI_!$AE$1,E3,", '",F3,"', '",G3,"' , '",H3,"' , ",I3,",",J3," , ",K3,", '",L3,"', '",M3,"' ,'",N3,"' , '",O3,"' , '",P3,"' , '",Q3,"' , '",R3,"','",S3,"','",T3,"','",U3,"','",V3,"','",W3,"','",X3,"','",Y3,"','",Z3,"'") -> EXECUTE [dbo].[PG_CI_ARCUSFIL_SQL] 0, 0, 0, 2, 'EBINGER BROTHERS LEATHER COMPANY', 'EBINGER BROTHERS LEATHER COMPANY' , 'EBIN01' , 200,221 , 53, 'MASSACHUSETTS', '44 MITCHELL ROAD' ,'IPSWICH' , '1938' , '2001-02-12' , '2' , '1','','2','MSUEX','','USD','','N/A','N'
B4: 0 | C4: 0 | D4: 0 | E4: 3 | F4: ENSAMBLE DE INTERIORES AUTOMOTRICES | G4: ENSAMBLE DE INTERIORES AUTOMOTRICES | H4: ENSA01 | I4: 200 | J4: 260 | K4: 8 | L4: CD JUAREZ, CHIH. | M4: BLVD. OSCAR FLORES 4250 | O4: 32650 | P4: 2001-06-07 | Q4: =E4 -> 3 | R4: 1 | T4: 2 | U4: MISC | W4: USD | Y4: N/A | Z4: N | AB4: =CONCATENATE(CI_!$AE$1,E4,", '",F4,"', '",G4,"' , '",H4,"' , ",I4,",",J4," , ",K4,", '",L4,"', '",M4,"' ,'",N4,"' , '",O4,"' , '",P4,"' , '",Q4,"' , '",R4,"','",S4,"','",T4,"','",U4,"','",V4,"','",W4,"','",X4,"','",Y4,"','",Z4,"'") -> EXECUTE [dbo].[PG_CI_ARCUSFIL_SQL] 0, 0, 0, 3, 'ENSAMBLE DE INTERIORES AUTOMOTRICES', 'ENSAMBLE DE INTERIORES AUTOMOTRICES' , 'ENSA01' , 200,260 , 8, 'CD JUAREZ, CHIH.', 'BLVD. OSCAR FLORES 4250' ,'' , '32650' , '2001-06-07' , '3' , '1','','2','MISC ','','USD','','N/A','N'
B5: 0 | C5: 0 | D5: 0 | E5: 4 | F5: FINDLAY INDUSTRIES********* | G5: FINDLAY INDUSTRIES************* | H5: FIND01 | I5: 200 | J5: 221 | K5: 67 | L5: OHIO | M5: 4000 FOSTORIA ROAD | N5: FINDLAY 0410 45840 | O5: 45840 | P5: 1998-05-22 | Q5: =E5 -> 4 | R5: 1 | T5: 2 | U5: MCUEX | W5: USD | X5: NETT CIF | Y5: N/A | Z5: N | AB5: =CONCATENATE(CI_!$AE$1,E5,", '",F5,"', '",G5,"' , '",H5,"' , ",I5,",",J5," , ",K5,", '",L5,"', '",M5,"' ,'",N5,"' , '",O5,"' , '",P5,"' , '",Q5,"' , '",R5,"','",S5,"','",T5,"','",U5,"','",V5,"','",W5,"','",X5,"','",Y5,"','",Z5,"'") -> EXECUTE [dbo].[PG_CI_ARCUSFIL_SQL] 0, 0, 0, 4, 'FINDLAY INDUSTRIES*********', 'FINDLAY INDUSTRIES*************' , 'FIND01' , 200,221 , 67, 'OHIO', '4000 FOSTORIA ROAD' ,'FINDLAY 0410 45840' , '45840' , '1998-05-22' , '4' , '1','','2','MCUEX','','USD','NETT CIF','N/A','N'
B6: 0 | C6: 0 | D6: 0 | E6: 5 | F6: FINDLAY INDUSTRIES (FLORIDA)*********** | G6: FINDLAY INDUSTRIES (FLORIDA)************ | H6: FIND02 | I6: 200 | J6: 221 | K6: 41 | L6: FLORIDA | M6: PO BOX 1350 | N6: LAKE WALES | O6: 33853 | P6: 1999-09-02 | Q6: =E6 -> 5 | R6: 1 | T6: 2 | U6: MCUEX | W6: USD | X6: NETT CIF | Y6: N/A | Z6: N | AB6: =CONCATENATE(CI_!$AE$1,E6,", '",F6,"', '",G6,"' , '",H6,"' , ",I6,",",J6," , ",K6,", '",L6,"', '",M6,"' ,'",N6,"' , '",O6,"' , '",P6,"' , '",Q6,"' , '",R6,"','",S6,"','",T6,"','",U6,"','",V6,"','",W6,"','",X6,"','",Y6,"','",Z6,"'") -> EXECUTE [dbo].[PG_CI_ARCUSFIL_SQL] 0, 0, 0, 5, 'FINDLAY INDUSTRIES (FLORIDA)***********', 'FINDLAY INDUSTRIES (FLORIDA)************' , 'FIND02' , 200,221 , 41, 'FLORIDA', 'PO BOX 1350' ,'LAKE WALES' , '33853' , '1999-09-02' , '5' , '1','','2','MCUEX','','USD','NETT CIF','N/A','N'
B7: 0 | C7: 0 | D7: 0 | E7: 6 | F7: GLOBALTEX 2000 LTD | G7: GLOBALTEX 2000 LTD | H7: GLOB01 | I7: 200 | J7: 213 | K7: 0 | M7: UNIT C/735 PRINCE ROAD | N7: WINDSOR | O7: N9C2Z2 | P7: 2000-03-23 | Q7: =E7 -> 6 | R7: 1 | T7: 2 | U7: MCUEX | W7: USD | Y7: N/A | Z7: N | AB7: =CONCATENATE(CI_!$AE$1,E7,", '",F7,"', '",G7,"' , '",H7,"' , ",I7,",",J7," , ",K7,", '",L7,"', '",M7,"' ,'",N7,"' , '",O7,"' , '",P7,"' , '",Q7,"' , '",R7,"','",S7,"','",T7,"','",U7,"','",V7,"','",W7,"','",X7,"','",Y7,"','",Z7,"'") -> EXECUTE [dbo].[PG_CI_ARCUSFIL_SQL] 0, 0, 0, 6, 'GLOBALTEX 2000 LTD', 'GLOBALTEX 2000 LTD' , 'GLOB01' , 200,213 , 0, '', 'UNIT C/735 PRINCE ROAD' ,'WINDSOR' , 'N9C2Z2' , '2000-03-23' , '6' , '1','','2','MCUEX','','USD','','N/A','N'
B8: 0 | C8: 0 | D8: 0 | E8: 7 | F8: IRVIN AUTOMOTIVE PRODUCTS -PONTIAC | G8: IRVIN AUTOMOTIVE | H8: IRVI02 | I8: 200 | J8: 221 | K8: 54 | L8: PONTIAC | M8: 2600 CENTER POINT PARKWAY | O8: 48341 | P8: 2001-07-25 | Q8: =E8 -> 7 | R8: 1 | T8: 2 | U8: MFUEX | W8: USD | Y8: N/A | Z8: N | AB8: =CONCATENATE(CI_!$AE$1,E8,", '",F8,"', '",G8,"' , '",H8,"' , ",I8,",",J8," , ",K8,", '",L8,"', '",M8,"' ,'",N8,"' , '",O8,"' , '",P8,"' , '",Q8,"' , '",R8,"','",S8,"','",T8,"','",U8,"','",V8,"','",W8,"','",X8,"','",Y8,"','",Z8,"'") -> EXECUTE [dbo].[PG_CI_ARCUSFIL_SQL] 0, 0, 0, 7, 'IRVIN AUTOMOTIVE PRODUCTS -PONTIAC', 'IRVIN AUTOMOTIVE' , 'IRVI02' , 200,221 , 54, 'PONTIAC', '2600 CENTER POINT PARKWAY' ,'' , '48341' , '2001-07-25' , '7' , '1','','2','MFUEX','','USD','','N/A','N'
B9: 0 | C9: 0 | D9: 0 | E9: 8 | F9: AUTOSEAT S.A. DE C.V. | G9: AUTOSEAT S.A. DE C.V. | H9: JITC01 | I9: 200 | J9: 260 | K9: 15 | L9: NAUCALPA | M9: PLANT#18232 | N9: CALLE NEGRA MODELO #6A FRACC ALCE BLANCO | O9: 53370 | P9: 1999-11-11 | Q9: =E9 -> 8 | R9: 1 | T9: 2 | U9: MCUEX | W9: USD | Y9: N/A | Z9: N | AB9: =CONCATENATE(CI_!$AE$1,E9,", '",F9,"', '",G9,"' , '",H9,"' , ",I9,",",J9," , ",K9,", '",L9,"', '",M9,"' ,'",N9,"' , '",O9,"' , '",P9,"' , '",Q9,"' , '",R9,"','",S9,"','",T9,"','",U9,"','",V9,"','",W9,"','",X9,"','",Y9,"','",Z9,"'") -> EXECUTE [dbo].[PG_CI_ARCUSFIL_SQL] 0, 0, 0, 8, 'AUTOSEAT S.A. DE C.V.', 'AUTOSEAT S.A. DE C.V.' , 'JITC01' , 200,260 , 15, 'NAUCALPA', 'PLANT#18232' ,'CALLE NEGRA MODELO #6A FRACC ALCE BLANCO' , '53370' , '1999-11-11' , '8' , '1','','2','MCUEX','','USD','','N/A','N'
B10: 0 | C10: 0 | D10: 0 | E10: 9 | F10: Johnson Control Interiors LLC | G10: JOHNSON CONTROL INTERIORS LLC | H10: JOHN02 | I10: 200 | J10: 221 | K10: 75 | L10: El Paso | M10: 1320 Goodyear Dr | O10: 79936 | P10: 2001-03-04 | Q10: =E10 -> 9 | R10: 1 | T10: 2 | U10: MCUEX | W10: USD | Y10: N/A | Z10: N | AB10: =CONCATENATE(CI_!$AE$1,E10,", '",F10,"', '",G10,"' , '",H10,"' , ",I10,",",J10," , ",K10,", '",L10,"', '",M10,"' ,'",N10,"' , '",O10,"' , '",P10,"' , '",Q10,"' , '",R10,"','",S10,"','",T10,"','",U10,"','",V10,"','",W10,"','",X10,"','",Y10,"','",Z10,"'") -> EXECUTE [dbo].[PG_CI_ARCUSFIL_SQL] 0, 0, 0, 9, 'Johnson Control Interiors LLC', 'JOHNSON CONTROL INTERIORS LLC' , 'JOHN02' , 200,221 , 75, 'El Paso', '1320 Goodyear Dr' ,'' , '79936' , '2001-03-04' , '9' , '1','','2','MCUEX','','USD','','N/A','N'
B11: 0 | C11: 0 | D11: 0 | E11: 10 | F11: KRAFT AUTOMOTIVE GROUP, INC | G11: KRAFT AUTOMOTIVE GROUP, INC | H11: KRAF01 | I11: 200 | J11: 221 | K11: 54 | L11: HOWELL | M11: 955 GRAND OAKS DRIVE | O11: 48843 | P11: 2001-04-26 | Q11: =E11 -> 10 | R11: 1 | T11: 8 | U11: MFUEX | W11: USD | Y11: N/A | Z11: N | AB11: =CONCATENATE(CI_!$AE$1,E11,", '",F11,"', '",G11,"' , '",H11,"' , ",I11,",",J11," , ",K11,", '",L11,"', '",M11,"' ,'",N11,"' , '",O11,"' , '",P11,"' , '",Q11,"' , '",R11,"','",S11,"','",T11,"','",U11,"','",V11,"','",W11,"','",X11,"','",Y11,"','",Z11,"'") -> EXECUTE [dbo].[PG_CI_ARCUSFIL_SQL] 0, 0, 0, 10, 'KRAFT AUTOMOTIVE GROUP, INC', 'KRAFT AUTOMOTIVE GROUP, INC' , 'KRAF01' , 200,221 , 54, 'HOWELL', '955 GRAND OAKS DRIVE' ,'' , '48843' , '2001-04-26' , '10' , '1','','8','MFUEX','','USD','','N/A','N'
B12: 0 | C12: 0 | D12: 0 | E12: 11 | F12: LEAR NAB CORPORATION (FAVESA) | G12: LEAR NAB CORPORATION (FAVESA) | H12: LEAR05 | I12: 200 | J12: 221 | K12: 75 | L12: EL PASO | M12: 1440 DON HASKINS | O12: 79936 | P12: 1998-05-25 | Q12: =E12 -> 11 | R12: 1 | T12: 2 | U12: MCUEX | W12: USD | Y12: N/A | Z12: N | AB12: =CONCATENATE(CI_!$AE$1,E12,", '",F12,"', '",G12,"' , '",H12,"' , ",I12,",",J12," , ",K12,", '",L12,"', '",M12,"' ,'",N12,"' , '",O12,"' , '",P12,"' , '",Q12,"' , '",R12,"','",S12,"','",T12,"','",U12,"','",V12,"','",W12,"','",X12,"','",Y12,"','",Z12,"'") -> EXECUTE [dbo].[PG_CI_ARCUSFIL_SQL] 0, 0, 0, 11, 'LEAR NAB CORPORATION (FAVESA)', 'LEAR NAB CORPORATION (FAVESA)' , 'LEAR05' , 200,221 , 75, 'EL PASO', '1440 DON HASKINS' ,'' , '79936' , '1998-05-25' , '11' , '1','','2','MCUEX','','USD','','N/A','N'
B13: 0 | C13: 0 | D13: 0 | E13: 12 | F13: LEAR TECHNOLOGIES, LLC | G13: LEAR TECHNOLOGIES, LLC | H13: LEAT01 | I13: 200 | J13: 221 | K13: 79 | M13: PO BOX 4178 | N13: SOUTHFIELD | O13: 48086-4178 | P13: 2000-03-09 | Q13: =E13 -> 12 | R13: 1 | T13: 2 | U13: MFUEX | W13: USD | Y13: N/A | Z13: N | AB13: =CONCATENATE(CI_!$AE$1,E13,", '",F13,"', '",G13,"' , '",H13,"' , ",I13,",",J13," , ",K13,", '",L13,"', '",M13,"' ,'",N13,"' , '",O13,"' , '",P13,"' , '",Q13,"' , '",R13,"','",S13,"','",T13,"','",U13,"','",V13,"','",W13,"','",X13,"','",Y13,"','",Z13,"'") -> EXECUTE [dbo].[PG_CI_ARCUSFIL_SQL] 0, 0, 0, 12, 'LEAR TECHNOLOGIES, LLC', 'LEAR TECHNOLOGIES, LLC' , 'LEAT01' , 200,221 , 79, '', 'PO BOX 4178' ,'SOUTHFIELD' , '48086-4178' , '2000-03-09' , '12' , '1','','2','MFUEX','','USD','','N/A','N'
B14: 0 | C14: 0 | D14: 0 | E14: 13 | F14: LEAR MEXICAN SEATING CORP | G14: LEAR RIO BRAVO | H14: LEAV01 | I14: 200 | J14: 221 | K14: 75 | L14: EL PASO | M14: 9500 PLAZA CIRCLE | N14: P.O. BOX 17709 | O14: 79917-7709 | P14: 1999-02-25 | Q14: =E14 -> 13 | R14: 1 | T14: 2 | U14: MFUEX | W14: USD | Y14: N/A | Z14: N | AB14: =CONCATENATE(CI_!$AE$1,E14,", '",F14,"', '",G14,"' , '",H14,"' , ",I14,",",J14," , ",K14,", '",L14,"', '",M14,"' ,'",N14,"' , '",O14,"' , '",P14,"' , '",Q14,"' , '",R14,"','",S14,"','",T14,"','",U14,"','",V14,"','",W14,"','",X14,"','",Y14,"','",Z14,"'") -> EXECUTE [dbo].[PG_CI_ARCUSFIL_SQL] 0, 0, 0, 13, 'LEAR MEXICAN SEATING CORP', 'LEAR RIO BRAVO' , 'LEAV01' , 200,221 , 75, 'EL PASO', '9500 PLAZA CIRCLE' ,'P.O. BOX 17709' , '79917-7709' , '1999-02-25' , '13' , '1','','2','MFUEX','','USD','','N/A','N'
B15: 0 | C15: 0 | D15: 0 | E15: 14 | F15: Leatherworks LLC | G15: LEATHERWORKS LLC | H15: LEAW01 | I15: 200 | J15: 221 | K15: 54 | L15: ALLEN PARK | M15: ATTN Accounts Payable | N15: 16630 Southfield Road, Suite 3100 | O15: 48101 | P15: 2001-08-22 | Q15: =E15 -> 14 | R15: 1 | T15: 2 | U15: MFUEX | W15: USD | Y15: Duty Paid | Z15: N | AB15: =CONCATENATE(CI_!$AE$1,E15,", '",F15,"', '",G15,"' , '",H15,"' , ",I15,",",J15," , ",K15,", '",L15,"', '",M15,"' ,'",N15,"' , '",O15,"' , '",P15,"' , '",Q15,"' , '",R15,"','",S15,"','",T15,"','",U15,"','",V15,"','",W15,"','",X15,"','",Y15,"','",Z15,"'") -> EXECUTE [dbo].[PG_CI_ARCUSFIL_SQL] 0, 0, 0, 14, 'Leatherworks LLC', 'LEATHERWORKS LLC' , 'LEAW01' , 200,221 , 54, 'ALLEN PARK', 'ATTN Accounts Payable' ,'16630 Southfield Road, Suite 3100' , '48101' , '2001-08-22' , '14' , '1','','2','MFUEX','','USD','','Duty Paid','N'
B16: 0 | C16: 0 | D16: 0 | E16: 15 | F16: LEAR CORPORATION - GM DIVISION | G16: LEAR CORPORATION - GM DIVISION | H16: LEGM01 | I16: 200 | J16: 221 | K16: 54 | L16: WARREN | M16: 5800 ENTERPRISE DRIVE | O16: 48092 | P16: 1999-11-19 | Q16: =E16 -> 15 | R16: 1 | T16: 2 | U16: MFUEX | W16: USD | Y16: N/A | Z16: N | AB16: =CONCATENATE(CI_!$AE$1,E16,", '",F16,"', '",G16,"' , '",H16,"' , ",I16,",",J16," , ",K16,", '",L16,"', '",M16,"' ,'",N16,"' , '",O16,"' , '",P16,"' , '",Q16,"' , '",R16,"','",S16,"','",T16,"','",U16,"','",V16,"','",W16,"','",X16,"','",Y16,"','",Z16,"'") -> EXECUTE [dbo].[PG_CI_ARCUSFIL_SQL] 0, 0, 0, 15, 'LEAR CORPORATION - GM DIVISION', 'LEAR CORPORATION - GM DIVISION' , 'LEGM01' , 200,221 , 54, 'WARREN', '5800 ENTERPRISE DRIVE' ,'' , '48092' , '1999-11-19' , '15' , '1','','2','MFUEX','','USD','','N/A','N'
B17: 0 | C17: 0 | D17: 0 | E17: 16 | F17: LEAR CORP FORD DIVISION | G17: LEAR CORP FORD DIVISION | H17: LFOR01 | I17: 200 | J17: 221 | K17: 54 | L17: DEARBORN | M17: 5250 AUTO CLUB DRIVE ANNEX | O17: 48126 | P17: 1999-04-30 | Q17: =E17 -> 16 | R17: 1 | T17: 2 | U17: MFUEX | W17: USD | Y17: N/A | Z17: N | AB17: =CONCATENATE(CI_!$AE$1,E17,", '",F17,"', '",G17,"' , '",H17,"' , ",I17,",",J17," , ",K17,", '",L17,"', '",M17,"' ,'",N17,"' , '",O17,"' , '",P17,"' , '",Q17,"' , '",R17,"','",S17,"','",T17,"','",U17,"','",V17,"','",W17,"','",X17,"','",Y17,"','",Z17,"'") -> EXECUTE [dbo].[PG_CI_ARCUSFIL_SQL] 0, 0, 0, 16, 'LEAR CORP FORD DIVISION', 'LEAR CORP FORD DIVISION' , 'LFOR01' , 200,221 , 54, 'DEARBORN', '5250 AUTO CLUB DRIVE ANNEX' ,'' , '48126' , '1999-04-30' , '16' , '1','','2','MFUEX','','USD','','N/A','N'
B18: 0 | C18: 0 | D18: 0 | E18: 17 | F18: SEATING SYSTEMS OF SABINAS | G18: SEATING SYSTEMS OF SABINAS | H18: MAGN01 | I18: 200 | J18: 221 | K18: 75 | L18: EAGLE PASS | M18: A DIV OF Magna Seating of America, Inc. | N18: 540 SOUTH BIBB PMB #1 | O18: 78852 | P18: 1999-11-12 | Q18: =E18 -> 17 | R18: 1 | T18: 2 | U18: MCUEX | W18: USD | Y18: N/A | Z18: N | AB18: =CONCATENATE(CI_!$AE$1,E18,", '",F18,"', '",G18,"' , '",H18,"' , ",I18,",",J18," , ",K18,", '",L18,"', '",M18,"' ,'",N18,"' , '",O18,"' , '",P18,"' , '",Q18,"' , '",R18,"','",S18,"','",T18,"','",U18,"','",V18,"','",W18,"','",X18,"','",Y18,"','",Z18,"'") -> EXECUTE [dbo].[PG_CI_ARCUSFIL_SQL] 0, 0, 0, 17, 'SEATING SYSTEMS OF SABINAS', 'SEATING SYSTEMS OF SABINAS' , 'MAGN01' , 200,221 , 75, 'EAGLE PASS', 'A DIV OF Magna Seating of America, Inc.' ,'540 SOUTH BIBB PMB #1' , '78852' , '1999-11-12' , '17' , '1','','2','MCUEX','','USD','','N/A','N'
B19: 0 | C19: 0 | D19: 0 | E19: 18 | F19: MAGNA SEATING OF AMERICA INC (ACUÑA) | G19: MAGNA SEATING OF AMERICA | H19: MAGN02 | I19: 200 | J19: 221 | K19: 75 | L19: DEL RIO | M19: 2199 SPUR 239 | N19: MAILING TO: P.O BOX 420699 | O19: 78840 | P19: 2000-02-01 | Q19: =E19 -> 18 | R19: 1 | T19: 2 | U19: MCUEX | W19: USD | Y19: N/A | Z19: N | AB19: =CONCATENATE(CI_!$AE$1,E19,", '",F19,"', '",G19,"' , '",H19,"' , ",I19,",",J19," , ",K19,", '",L19,"', '",M19,"' ,'",N19,"' , '",O19,"' , '",P19,"' , '",Q19,"' , '",R19,"','",S19,"','",T19,"','",U19,"','",V19,"','",W19,"','",X19,"','",Y19,"','",Z19,"'") -> EXECUTE [dbo].[PG_CI_ARCUSFIL_SQL] 0, 0, 0, 18, 'MAGNA SEATING OF AMERICA INC (ACUÑA)', 'MAGNA SEATING OF AMERICA' , 'MAGN02' , 200,221 , 75, 'DEL RIO', '2199 SPUR 239' ,'MAILING TO: P.O BOX 420699' , '78840' , '2000-02-01' , '18' , '1','','2','MCUEX','','USD','','N/A','N'
B20: 0 | C20: 0 | D20: 0 | E20: 19 | F20: SEATING SYS.OF ACUNA DIV INTIER AUTO | G20: MAGNA SEATING SYSTEMS OF ACUNA | H20: MAGN03 | I20: 200 | J20: 221 | K20: 75 | L20: DEL RIO | M20: 2199 SPUR 239 | N20: P.O. BOX 420699 | O20: 78840 | P20: 2000-07-28 | Q20: =E20 -> 19 | R20: 1 | T20: 2 | U20: MCUEX | W20: USD | Y20: N/A | Z20: N | AB20: =CONCATENATE(CI_!$AE$1,E20,", '",F20,"', '",G20,"' , '",H20,"' , ",I20,",",J20," , ",K20,", '",L20,"', '",M20,"' ,'",N20,"' , '",O20,"' , '",P20,"' , '",Q20,"' , '",R20,"','",S20,"','",T20,"','",U20,"','",V20,"','",W20,"','",X20,"','",Y20,"','",Z20,"'") -> EXECUTE [dbo].[PG_CI_ARCUSFIL_SQL] 0, 0, 0, 19, 'SEATING SYS.OF ACUNA DIV INTIER AUTO', 'MAGNA SEATING SYSTEMS OF ACUNA' , 'MAGN03' , 200,221 , 75, 'DEL RIO', '2199 SPUR 239' ,'P.O. BOX 420699' , '78840' , '2000-07-28' , '19' , '1','','2','MCUEX','','USD','','N/A','N'
B21: 0 | C21: 0 | D21: 0 | E21: 20 | F21: MAZDA CANADA INC | G21: MAZDA CANADA INC | H21: MAZC01 | I21: 200 | J21: 213 | K21: 83 | L21: SCARBOROUGH | M21: 305 MILNER AVENUE, | N21: SUITE 400 | O21: MIB 3V4 | P21: 2000-03-22 | Q21: =E21 -> 20 | R21: 1 | T21: 2 | U21: MFUEX | W21: USD | Y21: N/A | Z21: N | AB21: =CONCATENATE(CI_!$AE$1,E21,", '",F21,"', '",G21,"' , '",H21,"' , ",I21,",",J21," , ",K21,", '",L21,"', '",M21,"' ,'",N21,"' , '",O21,"' , '",P21,"' , '",Q21,"' , '",R21,"','",S21,"','",T21,"','",U21,"','",V21,"','",W21,"','",X21,"','",Y21,"','",Z21,"'") -> EXECUTE [dbo].[PG_CI_ARCUSFIL_SQL] 0, 0, 0, 20, 'MAZDA CANADA INC', 'MAZDA CANADA INC' , 'MAZC01' , 200,213 , 83, 'SCARBOROUGH', '305 MILNER AVENUE,' ,'SUITE 400' , 'MIB 3V4' , '2000-03-22' , '20' , '1','','2','MFUEX','','USD','','N/A','N'
B22: 0 | C22: 0 | D22: 0 | E22: 21 | F22: MAZDA NORTH AMERICAN OPERATION | G22: MAZDA NORTH AMERICAN OPERATION | H22: MAZN01 | I22: 200 | J22: 221 | K22: 37 | L22: IRVINE | M22: 7755 IRVINE CENTRE DRIVE | O22: 92618-2922 | P22: 2000-03-22 | Q22: =E22 -> 21 | R22: 1 | T22: 2 | U22: MFUEX | W22: USD | Y22: N/A | Z22: N | AB22: =CONCATENATE(CI_!$AE$1,E22,", '",F22,"', '",G22,"' , '",H22,"' , ",I22,",",J22," , ",K22,", '",L22,"', '",M22,"' ,'",N22,"' , '",O22,"' , '",P22,"' , '",Q22,"' , '",R22,"','",S22,"','",T22,"','",U22,"','",V22,"','",W22,"','",X22,"','",Y22,"','",Z22,"'") -> EXECUTE [dbo].[PG_CI_ARCUSFIL_SQL] 0, 0, 0, 21, 'MAZDA NORTH AMERICAN OPERATION', 'MAZDA NORTH AMERICAN OPERATION' , 'MAZN01' , 200,221 , 37, 'IRVINE', '7755 IRVINE CENTRE DRIVE' ,'' , '92618-2922' , '2000-03-22' , '21' , '1','','2','MFUEX','','USD','','N/A','N'
B23: 0 | C23: 0 | D23: 0 | E23: 22 | F23: MCDONALD EXP-DO NOT USE | G23: MCDONALD EXPORTS -DO NOT USE | H23: MCDO01 | I23: 500 | J23: 501 | K23: 105 | L23: SOUTHPORT | M23: SUITE 1 SOUTHPORT CHASE | N23: 19 EXPO COURT | O23: 4215 | P23: 2001-08-03 | Q23: =E23 -> 22 | R23: 1 | T23: 2 | U23: MISC | W23: USD | Y23: ABN | Z23: N | AB23: =CONCATENATE(CI_!$AE$1,E23,", '",F23,"', '",G23,"' , '",H23,"' , ",I23,",",J23," , ",K23,", '",L23,"', '",M23,"' ,'",N23,"' , '",O23,"' , '",P23,"' , '",Q23,"' , '",R23,"','",S23,"','",T23,"','",U23,"','",V23,"','",W23,"','",X23,"','",Y23,"','",Z23,"'") -> EXECUTE [dbo].[PG_CI_ARCUSFIL_SQL] 0, 0, 0, 22, 'MCDONALD EXP-DO NOT USE', 'MCDONALD EXPORTS -DO NOT USE' , 'MCDO01' , 500,501 , 105, 'SOUTHPORT', 'SUITE 1 SOUTHPORT CHASE' ,'19 EXPO COURT' , '4215' , '2001-08-03' , '22' , '1','','2','MISC ','','USD','','ABN','N'
B24: 0 | C24: 0 | D24: 0 | E24: 23 | F24: MCDONALD EXPORTS (AUST) P/L | G24: MCDONALD EXPORTS (AUST) P/L | H24: MCDO02 | I24: 500 | J24: 501 | K24: 105 | L24: SOUTHPORT | M24: SUITE 1 SOUTHPORT CHASE | N24: 19 EXPO COURT | O24: 4215 | P24: 2001-08-03 | Q24: =E24 -> 23 | R24: 1 | T24: 2 | U24: MISC | W24: USD | Y24: ABN | Z24: N | AB24: =CONCATENATE(CI_!$AE$1,E24,", '",F24,"', '",G24,"' , '",H24,"' , ",I24,",",J24," , ",K24,", '",L24,"', '",M24,"' ,'",N24,"' , '",O24,"' , '",P24,"' , '",Q24,"' , '",R24,"','",S24,"','",T24,"','",U24,"','",V24,"','",W24,"','",X24,"','",Y24,"','",Z24,"'") -> EXECUTE [dbo].[PG_CI_ARCUSFIL_SQL] 0, 0, 0, 23, 'MCDONALD EXPORTS (AUST) P/L', 'MCDONALD EXPORTS (AUST) P/L' , 'MCDO02' , 500,501 , 105, 'SOUTHPORT', 'SUITE 1 SOUTHPORT CHASE' ,'19 EXPO COURT' , '4215' , '2001-08-03' , '23' , '1','','2','MISC ','','USD','','ABN','N'
B25: 0 | C25: 0 | D25: 0 | E25: 24 | F25: MEXICAN INDUSTRIES**DO NOT USE** | G25: MEXICAN INDUSTRIES**DO NOT USE** | H25: MEXI02 | I25: 200 | J25: 221 | K25: 54 | L25: DETROIT | M25: ATT : PATTY ODELL | N25: 1801 HOWARD STREET | O25: 48216 | P25: 1998-11-30 | Q25: =E25 -> 24 | R25: 1 | T25: 2 | U25: MCUEX | W25: USD | Y25: N/A | Z25: Y | AB25: =CONCATENATE(CI_!$AE$1,E25,", '",F25,"', '",G25,"' , '",H25,"' , ",I25,",",J25," , ",K25,", '",L25,"', '",M25,"' ,'",N25,"' , '",O25,"' , '",P25,"' , '",Q25,"' , '",R25,"','",S25,"','",T25,"','",U25,"','",V25,"','",W25,"','",X25,"','",Y25,"','",Z25,"'") -> EXECUTE [dbo].[PG_CI_ARCUSFIL_SQL] 0, 0, 0, 24, 'MEXICAN INDUSTRIES**DO NOT USE**', 'MEXICAN INDUSTRIES**DO NOT USE**' , 'MEXI02' , 200,221 , 54, 'DETROIT', 'ATT : PATTY ODELL' ,'1801 HOWARD STREET' , '48216' , '1998-11-30' , '24' , '1','','2','MCUEX','','USD','','N/A','Y'
B26: 0 | C26: 0 | D26: 0 | E26: 25 | F26: MORIDEN AMERICA, INC. | G26: MORIDEN | H26: MORI01 | I26: 200 | J26: 221 | K26: 46 | L26: INDIANAPOLIS | M26: 915 WESTERN DRIVE | O26: 46241 | P26: 1998-07-01 | Q26: =E26 -> 25 | R26: 1 | T26: 2 | U26: MCUEX | W26: USD | Y26: N/A | Z26: N | AB26: =CONCATENATE(CI_!$AE$1,E26,", '",F26,"', '",G26,"' , '",H26,"' , ",I26,",",J26," , ",K26,", '",L26,"', '",M26,"' ,'",N26,"' , '",O26,"' , '",P26,"' , '",Q26,"' , '",R26,"','",S26,"','",T26,"','",U26,"','",V26,"','",W26,"','",X26,"','",Y26,"','",Z26,"'") -> EXECUTE [dbo].[PG_CI_ARCUSFIL_SQL] 0, 0, 0, 25, 'MORIDEN AMERICA, INC.', 'MORIDEN' , 'MORI01' , 200,221 , 46, 'INDIANAPOLIS', '915 WESTERN DRIVE' ,'' , '46241' , '1998-07-01' , '25' , '1','','2','MCUEX','','USD','','N/A','N'
B27: 0 | C27: 0 | D27: 0 | E27: 26 | F27: 1004274 ONTARIO LTD | G27: ONTARIO LTD | H27: ONTA01 | I27: 200 | J27: 213 | K27: 83 | L27: ONTARIO | M27: 993 BUCKSKIN WAY | N27: ORLEANS | O27: 2Y7 | P27: 2000-06-22 | Q27: =E27 -> 26 | R27: 1 | T27: 8 | U27: MSUEX | W27: USD | X27: L/C | Y27: N/A | Z27: N | AB27: =CONCATENATE(CI_!$AE$1,E27,", '",F27,"', '",G27,"' , '",H27,"' , ",I27,",",J27," , ",K27,", '",L27,"', '",M27,"' ,'",N27,"' , '",O27,"' , '",P27,"' , '",Q27,"' , '",R27,"','",S27,"','",T27,"','",U27,"','",V27,"','",W27,"','",X27,"','",Y27,"','",Z27,"'") -> EXECUTE [dbo].[PG_CI_ARCUSFIL_SQL] 0, 0, 0, 26, '1004274 ONTARIO LTD', 'ONTARIO LTD' , 'ONTA01' , 200,213 , 83, 'ONTARIO', '993 BUCKSKIN WAY' ,'ORLEANS' , '2Y7' , '2000-06-22' , '26' , '1','','8','MSUEX','','USD','L/C','N/A','N'
B28: 0 | C28: 0 | D28: 0 | E28: 27 | F28: TECHNOTRIM | G28: TECHNOTRIM | H28: TECH01 | I28: 200 | J28: 221 | K28: 54 | L28: CANTON | M28: 42015 FORD ROAD BOX 358 | O28: 48187-3669 | P28: 2000-01-31 | Q28: =E28 -> 27 | R28: 1 | T28: 2 | U28: MCUEX | W28: USD | Y28: N/A | Z28: N | AB28: =CONCATENATE(CI_!$AE$1,E28,", '",F28,"', '",G28,"' , '",H28,"' , ",I28,",",J28," , ",K28,", '",L28,"', '",M28,"' ,'",N28,"' , '",O28,"' , '",P28,"' , '",Q28,"' , '",R28,"','",S28,"','",T28,"','",U28,"','",V28,"','",W28,"','",X28,"','",Y28,"','",Z28,"'") -> EXECUTE [dbo].[PG_CI_ARCUSFIL_SQL] 0, 0, 0, 27, 'TECHNOTRIM', 'TECHNOTRIM' , 'TECH01' , 200,221 , 54, 'CANTON', '42015 FORD ROAD BOX 358' ,'' , '48187-3669' , '2000-01-31' , '27' , '1','','2','MCUEX','','USD','','N/A','N'
B29: 0 | C29: 0 | D29: 0 | E29: 28 | F29: UNIVERSAL TRIM INC | G29: UNIVERSAL TRIM INC | H29: UNIV01 | I29: 200 | J29: 221 | K29: 54 | L29: MADISON HEIGHTS | M29: PO BOX 71541 | O29: 48071-0541 | P29: 2000-01-25 | Q29: =E29 -> 28 | R29: 1 | T29: 2 | U29: MCUEX | W29: USD | Y29: N/A | Z29: N | AB29: =CONCATENATE(CI_!$AE$1,E29,", '",F29,"', '",G29,"' , '",H29,"' , ",I29,",",J29," , ",K29,", '",L29,"', '",M29,"' ,'",N29,"' , '",O29,"' , '",P29,"' , '",Q29,"' , '",R29,"','",S29,"','",T29,"','",U29,"','",V29,"','",W29,"','",X29,"','",Y29,"','",Z29,"'") -> EXECUTE [dbo].[PG_CI_ARCUSFIL_SQL] 0, 0, 0, 28, 'UNIVERSAL TRIM INC', 'UNIVERSAL TRIM INC' , 'UNIV01' , 200,221 , 54, 'MADISON HEIGHTS', 'PO BOX 71541' ,'' , '48071-0541' , '2000-01-25' , '28' , '1','','2','MCUEX','','USD','','N/A','N'
B30: 0 | C30: 0 | D30: 0 | E30: 29 | F30: BAILEY MANAGEMENT CONSULTING SERVICES | G30: BAILEY MANAGEMENT CONSULTING SERVICES | H30: BMCS01 | I30: 200 | J30: 213 | K30: 83 | L30: ONTARIO | M30: 163 HERITAGE ROAD | N30: KINGSVILLE | O30: N9Y 2C7 | P30: 2001-10-08 | Q30: =E30 -> 29 | R30: 1 | T30: 2 | U30: MCUEX | W30: USD | Y30: N/A | Z30: N | AB30: =CONCATENATE(CI_!$AE$1,E30,", '",F30,"', '",G30,"' , '",H30,"' , ",I30,",",J30," , ",K30,", '",L30,"', '",M30,"' ,'",N30,"' , '",O30,"' , '",P30,"' , '",Q30,"' , '",R30,"','",S30,"','",T30,"','",U30,"','",V30,"','",W30,"','",X30,"','",Y30,"','",Z30,"'") -> EXECUTE [dbo].[PG_CI_ARCUSFIL_SQL] 0, 0, 0, 29, 'BAILEY MANAGEMENT CONSULTING SERVICES', 'BAILEY MANAGEMENT CONSULTING SERVICES' , 'BMCS01' , 200,213 , 83, 'ONTARIO', '163 HERITAGE ROAD' ,'KINGSVILLE' , 'N9Y 2C7' , '2001-10-08' , '29' , '1','','2','MCUEX','','USD','','N/A','N'
B31: 0 | C31: 0 | D31: 0 | E31: 30 | F31: LEAR HERMOSILLO | G31: LEAR HERMOSILLO | H31: LEAR07 | I31: 200 | J31: 260 | K31: 26 | L31: NOGALES | M31: LEAR CORPORATION MEXICO SA DE CV | N31: PO BOX 6323 | O31: 85621 | P31: 2001-10-18 | Q31: =E31 -> 30 | R31: 1 | T31: 2 | U31: MCUEX | W31: USD | Y31: ABN | Z31: N | AB31: =CONCATENATE(CI_!$AE$1,E31,", '",F31,"', '",G31,"' , '",H31,"' , ",I31,",",J31," , ",K31,", '",L31,"', '",M31,"' ,'",N31,"' , '",O31,"' , '",P31,"' , '",Q31,"' , '",R31,"','",S31,"','",T31,"','",U31,"','",V31,"','",W31,"','",X31,"','",Y31,"','",Z31,"'") -> EXECUTE [dbo].[PG_CI_ARCUSFIL_SQL] 0, 0, 0, 30, 'LEAR HERMOSILLO', 'LEAR HERMOSILLO' , 'LEAR07' , 200,260 , 26, 'NOGALES', 'LEAR CORPORATION MEXICO SA DE CV' ,'PO BOX 6323' , '85621' , '2001-10-18' , '30' , '1','','2','MCUEX','','USD','','ABN','N'
B32: 0 | C32: 0 | D32: 0 | E32: 31 | F32: VISUAL SERVICES | G32: VISUAL SERVICES | H32: VISU01 | I32: 200 | J32: 221 | K32: 54 | L32: BLOOMFIELD HILLS | M32: 41000 WOODWARD AVENUE | O32: 48304-2263 | P32: 2001-11-18 | Q32: =E32 -> 31 | R32: 1 | T32: 2 | U32: MFUEX | W32: USD | Y32: N/A | Z32: N | AB32: =CONCATENATE(CI_!$AE$1,E32,", '",F32,"', '",G32,"' , '",H32,"' , ",I32,",",J32," , ",K32,", '",L32,"', '",M32,"' ,'",N32,"' , '",O32,"' , '",P32,"' , '",Q32,"' , '",R32,"','",S32,"','",T32,"','",U32,"','",V32,"','",W32,"','",X32,"','",Y32,"','",Z32,"'") -> EXECUTE [dbo].[PG_CI_ARCUSFIL_SQL] 0, 0, 0, 31, 'VISUAL SERVICES', 'VISUAL SERVICES' , 'VISU01' , 200,221 , 54, 'BLOOMFIELD HILLS', '41000 WOODWARD AVENUE' ,'' , '48304-2263' , '2001-11-18' , '31' , '1','','2','MFUEX','','USD','','N/A','N'
B33: 0 | C33: 0 | D33: 0 | E33: 32 | F33: JCIM MEXICO PROPERTIES,S.de R.L. | G33: JOHNSON CONTROLS MEXICO | H33: JOHN01 | I33: 200 | J33: 260 | K33: 8 | L33: JUAREZ | M33: EPSILON 6525 | N33: PARQUE INDUSTRIAL OMEGA | O33: 32320 | P33: 2002-01-22 | Q33: =E33 -> 32 | R33: 1 | T33: 2 | U33: MFUEX | W33: USD | X33: RICARDO.PEREZ@JCI.COM | Y33: N/A | Z33: N | AB33: =CONCATENATE(CI_!$AE$1,E33,", '",F33,"', '",G33,"' , '",H33,"' , ",I33,",",J33," , ",K33,", '",L33,"', '",M33,"' ,'",N33,"' , '",O33,"' , '",P33,"' , '",Q33,"' , '",R33,"','",S33,"','",T33,"','",U33,"','",V33,"','",W33,"','",X33,"','",Y33,"','",Z33,"'") -> EXECUTE [dbo].[PG_CI_ARCUSFIL_SQL] 0, 0, 0, 32, 'JCIM MEXICO PROPERTIES,S.de R.L.', 'JOHNSON CONTROLS MEXICO' , 'JOHN01' , 200,260 , 8, 'JUAREZ', 'EPSILON 6525' ,'PARQUE INDUSTRIAL OMEGA' , '32320' , '2002-01-22' , '32' , '1','','2','MFUEX','','USD','RICARDO.PEREZ@JCI.COM','N/A','N'
B34: 0 | C34: 0 | D34: 0 | E34: 33 | F34: CASH SALES MEXICO | G34: CASH SALES MEXICO | H34: CASH01 | I34: 0 | J34: 0 | K34: 0 | O34: 0 | P34: 2002-01-28 | Q34: =E34 -> 33 | R34: 1 | T34: 2 | U34: MISC | W34: USD | Z34: N | AB34: =CONCATENATE(CI_!$AE$1,E34,", '",F34,"', '",G34,"' , '",H34,"' , ",I34,",",J34," , ",K34,", '",L34,"', '",M34,"' ,'",N34,"' , '",O34,"' , '",P34,"' , '",Q34,"' , '",R34,"','",S34,"','",T34,"','",U34,"','",V34,"','",W34,"','",X34,"','",Y34,"','",Z34,"'") -> EXECUTE [dbo].[PG_CI_ARCUSFIL_SQL] 0, 0, 0, 33, 'CASH SALES MEXICO', 'CASH SALES MEXICO' , 'CASH01' , 0,0 , 0, '', '' ,'' , '0' , '2002-01-28' , '33' , '1','','2','MISC ','','USD','','','N'
B35: 0 | C35: 0 | D35: 0 | E35: 34 | F35: IRVIN AUTOMOTIVE | G35: JAROPAMEX ACUNA, PLANT1 | H35: IRVI03 | I35: 200 | J35: 221 | K35: 75 | L35: DEL RIO | M35: 2A FAWCETT DRIVE | O35: 78840 | P35: 2003-11-06 | Q35: =E35 -> 34 | R35: 1 | T35: 2 | U35: MFUEX | W35: USD | X35: FOB SHIP POINT | Y35: N/A | Z35: N | AB35: =CONCATENATE(CI_!$AE$1,E35,", '",F35,"', '",G35,"' , '",H35,"' , ",I35,",",J35," , ",K35,", '",L35,"', '",M35,"' ,'",N35,"' , '",O35,"' , '",P35,"' , '",Q35,"' , '",R35,"','",S35,"','",T35,"','",U35,"','",V35,"','",W35,"','",X35,"','",Y35,"','",Z35,"'") -> EXECUTE [dbo].[PG_CI_ARCUSFIL_SQL] 0, 0, 0, 34, 'IRVIN AUTOMOTIVE', 'JAROPAMEX ACUNA, PLANT1' , 'IRVI03' , 200,221 , 75, 'DEL RIO', '2A FAWCETT DRIVE' ,'' , '78840' , '2003-11-06' , '34' , '1','','2','MFUEX','','USD','FOB SHIP POINT','N/A','N'
B36: 0 | C36: 0 | D36: 0 | E36: 35 | F36: TENNMEX INC | G36: TENNMEX INC | H36: TENN01 | I36: 200 | J36: 221 | K36: 75 | M36: 2262 SAN JUAN DRIVE | N36: EAGLE PASS | O36: 78852 | P36: 2005-08-15 | Q36: =E36 -> 35 | R36: 1 | T36: 2 | U36: MCUEX | W36: USD | Y36: N/A | Z36: N | AB36: =CONCATENATE(CI_!$AE$1,E36,", '",F36,"', '",G36,"' , '",H36,"' , ",I36,",",J36," , ",K36,", '",L36,"', '",M36,"' ,'",N36,"' , '",O36,"' , '",P36,"' , '",Q36,"' , '",R36,"','",S36,"','",T36,"','",U36,"','",V36,"','",W36,"','",X36,"','",Y36,"','",Z36,"'") -> EXECUTE [dbo].[PG_CI_ARCUSFIL_SQL] 0, 0, 0, 35, 'TENNMEX INC', 'TENNMEX INC' , 'TENN01' , 200,221 , 75, '', '2262 SAN JUAN DRIVE' ,'EAGLE PASS' , '78852' , '2005-08-15' , '35' , '1','','2','MCUEX','','USD','','N/A','N'
B37: 0 | C37: 0 | D37: 0 | E37: 36 | F37: WOODBRIDGE FOAM CORPORATION | G37: WOODBRIDGE FOAM CORPORATION | H37: WOOD01 | I37: 200 | J37: 260 | K37: 5 | L37: RAMOS ARIZPE | M37: SALTILLO MONTERREY KM1150 | N37: PARQUE INDUSTRIAL RAMOS ARIZPE | O37: 25900 | P37: 2006-01-30 | Q37: =E37 -> 36 | R37: 1 | T37: 2 | U37: MFUEX | W37: USD | Y37: N/A | Z37: N | AB37: =CONCATENATE(CI_!$AE$1,E37,", '",F37,"', '",G37,"' , '",H37,"' , ",I37,",",J37," , ",K37,", '",L37,"', '",M37,"' ,'",N37,"' , '",O37,"' , '",P37,"' , '",Q37,"' , '",R37,"','",S37,"','",T37,"','",U37,"','",V37,"','",W37,"','",X37,"','",Y37,"','",Z37,"'") -> EXECUTE [dbo].[PG_CI_ARCUSFIL_SQL] 0, 0, 0, 36, 'WOODBRIDGE FOAM CORPORATION', 'WOODBRIDGE FOAM CORPORATION' , 'WOOD01' , 200,260 , 5, 'RAMOS ARIZPE', 'SALTILLO MONTERREY KM1150' ,'PARQUE INDUSTRIAL RAMOS ARIZPE' , '25900' , '2006-01-30' , '36' , '1','','2','MFUEX','','USD','','N/A','N'
B38: 0 | C38: 0 | D38: 0 | E38: 37 | F38: JOHNSON CONTROLS-EDIASA 3 | G38: JOHNSON CONTROLS-EDIASA 3 | H38: JOHN03 | I38: 200 | J38: 221 | K38: 75 | L38: EL PASO | M38: JOHNSON CONTROLS INC | N38: SSC ACCOUNTS PAYABLE | O38: 981700 | P38: 2006-12-20 | Q38: =E38 -> 37 | R38: 1 | T38: 2 | U38: MCUEX | W38: USD | Y38: N/A | Z38: N | AB38: =CONCATENATE(CI_!$AE$1,E38,", '",F38,"', '",G38,"' , '",H38,"' , ",I38,",",J38," , ",K38,", '",L38,"', '",M38,"' ,'",N38,"' , '",O38,"' , '",P38,"' , '",Q38,"' , '",R38,"','",S38,"','",T38,"','",U38,"','",V38,"','",W38,"','",X38,"','",Y38,"','",Z38,"'") -> EXECUTE [dbo].[PG_CI_ARCUSFIL_SQL] 0, 0, 0, 37, 'JOHNSON CONTROLS-EDIASA 3', 'JOHNSON CONTROLS-EDIASA 3' , 'JOHN03' , 200,221 , 75, 'EL PASO', 'JOHNSON CONTROLS INC' ,'SSC ACCOUNTS PAYABLE' , '981700' , '2006-12-20' , '37' , '1','','2','MCUEX','','USD','','N/A','N'
B39: 0 | C39: 0 | D39: 0 | E39: 38 | F39: JOHNSON CONTROL SHANGAI | G39: JOHNSON CONTROL SHANGAI | H39: JOHN04 | I39: 200 | J39: 221 | K39: 75 | L39: EL PASO | M39: SSC ACCOUNTS PAYABLE -18438 | N39: PO BOX 981700 | O39: 79998 | P39: 2007-01-18 | Q39: =E39 -> 38 | R39: 1 | T39: 11 | U39: MCUEX | W39: USD | Z39: N | AB39: =CONCATENATE(CI_!$AE$1,E39,", '",F39,"', '",G39,"' , '",H39,"' , ",I39,",",J39," , ",K39,", '",L39,"', '",M39,"' ,'",N39,"' , '",O39,"' , '",P39,"' , '",Q39,"' , '",R39,"','",S39,"','",T39,"','",U39,"','",V39,"','",W39,"','",X39,"','",Y39,"','",Z39,"'") -> EXECUTE [dbo].[PG_CI_ARCUSFIL_SQL] 0, 0, 0, 38, 'JOHNSON CONTROL SHANGAI', 'JOHNSON CONTROL SHANGAI' , 'JOHN04' , 200,221 , 75, 'EL PASO', 'SSC ACCOUNTS PAYABLE -18438' ,'PO BOX 981700' , '79998' , '2007-01-18' , '38' , '1','','11','MCUEX','','USD','','','N'
B40: 0 | C40: 0 | D40: 0 | E40: 39 | F40: KONGSBERG AUTOMOTIVE | G40: KONGSBERG AUTOMOTIVE | H40: KONG01 | I40: 200 | J40: 221 | K40: 75 | L40: PHARR | M40: LAREDO FREIGHT - KONGSBERG AUTOMOTIVE | N40: 9208 SOUTH CAGE BLVD | O40: 78577 | P40: 2008-01-29 | Q40: =E40 -> 39 | R40: 1 | T40: 2 | U40: MCUEX | W40: USD | X40: EXW | Y40: N/A | Z40: N | AB40: =CONCATENATE(CI_!$AE$1,E40,", '",F40,"', '",G40,"' , '",H40,"' , ",I40,",",J40," , ",K40,", '",L40,"', '",M40,"' ,'",N40,"' , '",O40,"' , '",P40,"' , '",Q40,"' , '",R40,"','",S40,"','",T40,"','",U40,"','",V40,"','",W40,"','",X40,"','",Y40,"','",Z40,"'") -> EXECUTE [dbo].[PG_CI_ARCUSFIL_SQL] 0, 0, 0, 39, 'KONGSBERG AUTOMOTIVE', 'KONGSBERG AUTOMOTIVE' , 'KONG01' , 200,221 , 75, 'PHARR', 'LAREDO FREIGHT - KONGSBERG AUTOMOTIVE' ,'9208 SOUTH CAGE BLVD' , '78577' , '2008-01-29' , '39' , '1','','2','MCUEX','','USD','EXW','N/A','N'
B41: 0 | C41: 0 | D41: 0 | E41: 40 | F41: GRAMMER AUTOMOTIVE PUEBLA | G41: GRAMMER AUTOMOTIVE PUEBLA | H41: GRAM01 | I41: 200 | J41: 260 | K41: 29 | L41: TETLA | M41: BOULEVARD TETLA NO 107 | N41: Cd. Industrial Xicohtencatl | O41: 90434 | P41: 2008-02-06 | Q41: =E41 -> 40 | R41: 1 | T41: 2 | U41: MCUEX | W41: USD | X41: FOB Juarez | Y41: N/A | Z41: N | AB41: =CONCATENATE(CI_!$AE$1,E41,", '",F41,"', '",G41,"' , '",H41,"' , ",I41,",",J41," , ",K41,", '",L41,"', '",M41,"' ,'",N41,"' , '",O41,"' , '",P41,"' , '",Q41,"' , '",R41,"','",S41,"','",T41,"','",U41,"','",V41,"','",W41,"','",X41,"','",Y41,"','",Z41,"'") -> EXECUTE [dbo].[PG_CI_ARCUSFIL_SQL] 0, 0, 0, 40, 'GRAMMER AUTOMOTIVE PUEBLA', 'GRAMMER AUTOMOTIVE PUEBLA' , 'GRAM01' , 200,260 , 29, 'TETLA', 'BOULEVARD TETLA NO 107' ,'Cd. Industrial Xicohtencatl' , '90434' , '2008-02-06' , '40' , '1','','2','MCUEX','','USD','FOB Juarez','N/A','N'
B42: 0 | C42: 0 | D42: 0 | E42: 41 | F42: MAY & SCOFIELD | G42: MAY & SCOFIELD | H42: MAYS01 | I42: 200 | J42: 221 | K42: 54 | L42: FOWLERVILLE | M42: 445 E. VAN RIPER | O42: 48836 | P42: 2008-03-05 | Q42: =E42 -> 41 | R42: 1 | T42: 2 | U42: MCUEX | W42: USD | Z42: N | AB42: =CONCATENATE(CI_!$AE$1,E42,", '",F42,"', '",G42,"' , '",H42,"' , ",I42,",",J42," , ",K42,", '",L42,"', '",M42,"' ,'",N42,"' , '",O42,"' , '",P42,"' , '",Q42,"' , '",R42,"','",S42,"','",T42,"','",U42,"','",V42,"','",W42,"','",X42,"','",Y42,"','",Z42,"'") -> EXECUTE [dbo].[PG_CI_ARCUSFIL_SQL] 0, 0, 0, 41, 'MAY & SCOFIELD', 'MAY & SCOFIELD' , 'MAYS01' , 200,221 , 54, 'FOWLERVILLE', '445 E. VAN RIPER' ,'' , '48836' , '2008-03-05' , '41' , '1','','2','MCUEX','','USD','','','N'
B43: 0 | C43: 0 | D43: 0 | E43: 42 | F43: RECICLADOS ECOLOGICOS DIVERSOS | G43: RECICLADOS ECOLOGICOS DIVERSOS | H43: CASH02 | I43: 200 | J43: 260 | K43: 8 | L43: JUAREZ | M43: CALLE PASCUAL OROZCO 591 | N43: COL. SANTA MARIA | O43: 32676 | P43: 2013-01-15 | Q43: =E43 -> 42 | R43: 1 | T43: 2 | U43: MISC | W43: USD | Z43: N | AB43: =CONCATENATE(CI_!$AE$1,E43,", '",F43,"', '",G43,"' , '",H43,"' , ",I43,",",J43," , ",K43,", '",L43,"', '",M43,"' ,'",N43,"' , '",O43,"' , '",P43,"' , '",Q43,"' , '",R43,"','",S43,"','",T43,"','",U43,"','",V43,"','",W43,"','",X43,"','",Y43,"','",Z43,"'") -> EXECUTE [dbo].[PG_CI_ARCUSFIL_SQL] 0, 0, 0, 42, 'RECICLADOS ECOLOGICOS DIVERSOS', 'RECICLADOS ECOLOGICOS DIVERSOS' , 'CASH02' , 200,260 , 8, 'JUAREZ', 'CALLE PASCUAL OROZCO 591' ,'COL. SANTA MARIA' , '32676' , '2013-01-15' , '42' , '1','','2','MISC ','','USD','','','N'
B44: 0 | C44: 0 | D44: 0 | E44: 43 | F44: PEARL LEATHER GROUP LLC | G44: PEARL LEATHER GROUP LLC | H44: PEARL01 | I44: 200 | J44: 221 | K44: 64 | L44: MANHASSET | M44: 390 PLANDOME ROAD | O44: 11030 | P44: 2013-01-24 | Q44: =E44 -> 43 | R44: 1 | T44: 2 | U44: MISC | W44: USD | Z44: N | AB44: =CONCATENATE(CI_!$AE$1,E44,", '",F44,"', '",G44,"' , '",H44,"' , ",I44,",",J44," , ",K44,", '",L44,"', '",M44,"' ,'",N44,"' , '",O44,"' , '",P44,"' , '",Q44,"' , '",R44,"','",S44,"','",T44,"','",U44,"','",V44,"','",W44,"','",X44,"','",Y44,"','",Z44,"'") -> EXECUTE [dbo].[PG_CI_ARCUSFIL_SQL] 0, 0, 0, 43, 'PEARL LEATHER GROUP LLC', 'PEARL LEATHER GROUP LLC' , 'PEARL01' , 200,221 , 64, 'MANHASSET', '390 PLANDOME ROAD' ,'' , '11030' , '2013-01-24' , '43' , '1','','2','MISC ','','USD','','','N'
B45: 0 | C45: 0 | D45: 0 | E45: 44 | F45: PEARL LEATHER SALES | G45: PEARL LEATHER SALES | H45: PSALES | I45: 200 | J45: 221 | K45: 54 | L45: BIRMINGHAM | M45: 523 ARGYLE | O45: 48009 | P45: 2015-08-31 | Q45: =E45 -> 44 | R45: 1 | T45: 2 | U45: MCUEX | W45: USD | Z45: N | AB45: =CONCATENATE(CI_!$AE$1,E45,", '",F45,"', '",G45,"' , '",H45,"' , ",I45,",",J45," , ",K45,", '",L45,"', '",M45,"' ,'",N45,"' , '",O45,"' , '",P45,"' , '",Q45,"' , '",R45,"','",S45,"','",T45,"','",U45,"','",V45,"','",W45,"','",X45,"','",Y45,"','",Z45,"'") -> EXECUTE [dbo].[PG_CI_ARCUSFIL_SQL] 0, 0, 0, 44, 'PEARL LEATHER SALES', 'PEARL LEATHER SALES' , 'PSALES' , 200,221 , 54, 'BIRMINGHAM', '523 ARGYLE' ,'' , '48009' , '2015-08-31' , '44' , '1','','2','MCUEX','','USD','','','N'
B46: 0 | C46: 0 | D46: 0 | E46: 45 | F46: PEARL LEATHER FINISHERS | G46: PEARL LEATHER FINISHERS | H46: PLFNY1 | I46: 200 | J46: 221 | K46: 64 | L46: JOHNSTOWN | M46: 11-21 INDUSTRIAL PARK | O46: 12095 | P46: 2015-08-31 | Q46: =E46 -> 45 | R46: 1 | T46: 2 | U46: MCUEX | W46: USD | Z46: N | AB46: =CONCATENATE(CI_!$AE$1,E46,", '",F46,"', '",G46,"' , '",H46,"' , ",I46,",",J46," , ",K46,", '",L46,"', '",M46,"' ,'",N46,"' , '",O46,"' , '",P46,"' , '",Q46,"' , '",R46,"','",S46,"','",T46,"','",U46,"','",V46,"','",W46,"','",X46,"','",Y46,"','",Z46,"'") -> EXECUTE [dbo].[PG_CI_ARCUSFIL_SQL] 0, 0, 0, 45, 'PEARL LEATHER FINISHERS', 'PEARL LEATHER FINISHERS' , 'PLFNY1' , 200,221 , 64, 'JOHNSTOWN', '11-21 INDUSTRIAL PARK' ,'' , '12095' , '2015-08-31' , '45' , '1','','2','MCUEX','','USD','','','N'
B47: 0 | C47: 0 | D47: 0 | E47: 46 | F47: AUTOMOTIVE LEATHER GROUP | G47: AUTOMOTIVE LEATHER GROUP | H47: ALGRP1 | I47: 200 | J47: 221 | K47: 64 | L47: GREAT NECK STATES | M47: 17 BARSTOWN ROAD | O47: 11021 | P47: 2015-08-31 | Q47: =E47 -> 46 | R47: 1 | S47: BKAMALI@KAMALIGROUP.COM | T47: 2 | U47: MCUEX | W47: USD | Z47: N | AB47: =CONCATENATE(CI_!$AE$1,E47,", '",F47,"', '",G47,"' , '",H47,"' , ",I47,",",J47," , ",K47,", '",L47,"', '",M47,"' ,'",N47,"' , '",O47,"' , '",P47,"' , '",Q47,"' , '",R47,"','",S47,"','",T47,"','",U47,"','",V47,"','",W47,"','",X47,"','",Y47,"','",Z47,"'") -> EXECUTE [dbo].[PG_CI_ARCUSFIL_SQL] 0, 0, 0, 46, 'AUTOMOTIVE LEATHER GROUP', 'AUTOMOTIVE LEATHER GROUP' , 'ALGRP1' , 200,221 , 64, 'GREAT NECK STATES', '17 BARSTOWN ROAD' ,'' , '11021' , '2015-08-31' , '46' , '1','BKAMALI@KAMALIGROUP.COM','2','MCUEX','','USD','','','N'
B48: 0 | C48: 0 | D48: 0 | E48: 47 | F48: MAGNA SEATING | G48: MAGNA SEATING OF AMERICA INC | H48: MAGN04 | I48: 200 | J48: 221 | K48: 75 | L48: DEL RIO | M48: 2199 SPUR 239 | N48: MAILING TO: P.O BOX 420699 | O48: 78840 | P48: 2015-08-31 | Q48: =E48 -> 47 | R48: 1 | T48: 2 | U48: MCUEX | W48: USD | Z48: N | AB48: =CONCATENATE(CI_!$AE$1,E48,", '",F48,"', '",G48,"' , '",H48,"' , ",I48,",",J48," , ",K48,", '",L48,"', '",M48,"' ,'",N48,"' , '",O48,"' , '",P48,"' , '",Q48,"' , '",R48,"','",S48,"','",T48,"','",U48,"','",V48,"','",W48,"','",X48,"','",Y48,"','",Z48,"'") -> EXECUTE [dbo].[PG_CI_ARCUSFIL_SQL] 0, 0, 0, 47, 'MAGNA SEATING', 'MAGNA SEATING OF AMERICA INC' , 'MAGN04' , 200,221 , 75, 'DEL RIO', '2199 SPUR 239' ,'MAILING TO: P.O BOX 420699' , '78840' , '2015-08-31' , '47' , '1','','2','MCUEX','','USD','','','N'
B49: 0 | C49: 0 | D49: 0 | E49: 48 | F49: KAMALI GROUP INCORPORATED | G49: KAMALI GROUP INCORPORATED | H49: KAMA01 | I49: 200 | J49: 221 | K49: 64 | L49: GREAT NECK | M49: 17 BARSTOW ROAD | O49: 11021 | P49: 2015-12-07 | Q49: =E49 -> 48 | R49: 1 | T49: 2 | U49: MISC | W49: USD | Z49: N | AB49: =CONCATENATE(CI_!$AE$1,E49,", '",F49,"', '",G49,"' , '",H49,"' , ",I49,",",J49," , ",K49,", '",L49,"', '",M49,"' ,'",N49,"' , '",O49,"' , '",P49,"' , '",Q49,"' , '",R49,"','",S49,"','",T49,"','",U49,"','",V49,"','",W49,"','",X49,"','",Y49,"','",Z49,"'") -> EXECUTE [dbo].[PG_CI_ARCUSFIL_SQL] 0, 0, 0, 48, 'KAMALI GROUP INCORPORATED', 'KAMALI GROUP INCORPORATED' , 'KAMA01' , 200,221 , 64, 'GREAT NECK', '17 BARSTOW ROAD' ,'' , '11021' , '2015-12-07' , '48' , '1','','2','MISC ','','USD','','','N'
B50: 0 | C50: 0 | D50: 0 | E50: 49 | F50: BILTMORE CORPORATION | G50: BILTMORE CORPORATION | H50: BILT01 | I50: 200 | J50: 221 | K50: 64 | L50: GREAT NECK | M50: 17 BARSTOW RD. | N50: SUITE 206 | O50: 11021 | P50: 2016-12-08 | Q50: =E50 -> 49 | R50: 1 | T50: 2 | U50: MISC | W50: AUD | Z50: N | AB50: =CONCATENATE(CI_!$AE$1,E50,", '",F50,"', '",G50,"' , '",H50,"' , ",I50,",",J50," , ",K50,", '",L50,"', '",M50,"' ,'",N50,"' , '",O50,"' , '",P50,"' , '",Q50,"' , '",R50,"','",S50,"','",T50,"','",U50,"','",V50,"','",W50,"','",X50,"','",Y50,"','",Z50,"'") -> EXECUTE [dbo].[PG_CI_ARCUSFIL_SQL] 0, 0, 0, 49, 'BILTMORE CORPORATION', 'BILTMORE CORPORATION' , 'BILT01' , 200,221 , 64, 'GREAT NECK', '17 BARSTOW RD.' ,'SUITE 206' , '11021' , '2016-12-08' , '49' , '1','','2','MISC ','','AUD','','','N'
B51: 0 | C51: 0 | D51: 0 | E51: 50 | F51: RICARDO VALTIERRA HERNANDEZ | G51: RICARDO VALTIERRA HERNANDEZ | H51: VALT01 | I51: 200 | J51: 260 | K51: 8 | L51: JUAREZ | M51: FRAY GARCIA DE SAN FRANCISCO NO. 880 | N51: COL. BELLAVISTA | O51: 32000 | P51: 2019-03-19 | Q51: =E51 -> 50 | R51: 1 | T51: 2 | U51: MFUEX | W51: USD | Z51: N | AB51: =CONCATENATE(CI_!$AE$1,E51,", '",F51,"', '",G51,"' , '",H51,"' , ",I51,",",J51," , ",K51,", '",L51,"', '",M51,"' ,'",N51,"' , '",O51,"' , '",P51,"' , '",Q51,"' , '",R51,"','",S51,"','",T51,"','",U51,"','",V51,"','",W51,"','",X51,"','",Y51,"','",Z51,"'") -> EXECUTE [dbo].[PG_CI_ARCUSFIL_SQL] 0, 0, 0, 50, 'RICARDO VALTIERRA HERNANDEZ', 'RICARDO VALTIERRA HERNANDEZ' , 'VALT01' , 200,260 , 8, 'JUAREZ', 'FRAY GARCIA DE SAN FRANCISCO NO. 880' ,'COL. BELLAVISTA' , '32000' , '2019-03-19' , '50' , '1','','2','MFUEX','','USD','','','N'
B52: 0 | C52: 0 | D52: 0 | E52: 51 | F52: FAURECIA AUTOMOTIVE SEATING INC. | G52: FAURECIA AUTOMOTIVE SEATING INC. | H52: FAUR01 | I52: 200 | J52: 221 | K52: 54 | L52: AUBURN HILLS | M52: TROY_1402 | O52: 48321 | P52: 2019-11-11 | Q52: =E52 -> 51 | R52: 1 | T52: 2 | U52: MCUEX | W52: USD | Z52: N | AB52: =CONCATENATE(CI_!$AE$1,E52,", '",F52,"', '",G52,"' , '",H52,"' , ",I52,",",J52," , ",K52,", '",L52,"', '",M52,"' ,'",N52,"' , '",O52,"' , '",P52,"' , '",Q52,"' , '",R52,"','",S52,"','",T52,"','",U52,"','",V52,"','",W52,"','",X52,"','",Y52,"','",Z52,"'") -> EXECUTE [dbo].[PG_CI_ARCUSFIL_SQL] 0, 0, 0, 51, 'FAURECIA AUTOMOTIVE SEATING INC.', 'FAURECIA AUTOMOTIVE SEATING INC.' , 'FAUR01' , 200,221 , 54, 'AUBURN HILLS', 'TROY_1402' ,'' , '48321' , '2019-11-11' , '51' , '1','','2','MCUEX','','USD','','','N'
B53: 0 | C53: 0 | D53: 0 | E53: 52 | F53: (NO-Customer) | G53: ( N/C ) | H53: XXXX00 | I53: 0 | J53: 0 | K53: 0 | L53: (NO-Customer) | M53: (NO-Customer) | N53: (NO-Customer) | O53: 0 | P53: 36526 | Q53: =E53 -> 52 | R53: 1 | T53: 2 | U53: MCUEX | W53: USD | Z53: N | AB53: =CONCATENATE(CI_!$AE$1,E53,", '",F53,"', '",G53,"' , '",H53,"' , ",I53,",",J53," , ",K53,", '",L53,"', '",M53,"' ,'",N53,"' , '",O53,"' , '",P53,"' , '",Q53,"' , '",R53,"','",S53,"','",T53,"','",U53,"','",V53,"','",W53,"','",X53,"','",Y53,"','",Z53,"'") -> EXECUTE [dbo].[PG_CI_ARCUSFIL_SQL] 0, 0, 0, 52, '(NO-Customer)', '( N/C )' , 'XXXX00' , 0,0 , 0, '(NO-Customer)', '(NO-Customer)' ,'(NO-Customer)' , '0' , '36526' , '52' , '1','','2','MCUEX','','USD','','','N'
B54: 0 | C54: 0 | D54: 0 | E54: 53 | F54: YANFENG AUTOMOTIVE INTERIOR | G54: YANFENG AUTOMOTIVE INTERIOR | H54: YANG02 | I54: 200 | J54: 221 | K54: 54 | L54: ROAD NOV | M54: 1935 WEST 12 MILE ROAD NOVI, MI 48377 | O54: 48152 | P54: 2019-11-19 | Q54: =E54 -> 53 | R54: 1 | T54: 2 | U54: MCUEX | W54: USD | Z54: N | AB54: =CONCATENATE(CI_!$AE$1,E54,", '",F54,"', '",G54,"' , '",H54,"' , ",I54,",",J54," , ",K54,", '",L54,"', '",M54,"' ,'",N54,"' , '",O54,"' , '",P54,"' , '",Q54,"' , '",R54,"','",S54,"','",T54,"','",U54,"','",V54,"','",W54,"','",X54,"','",Y54,"','",Z54,"'") -> EXECUTE [dbo].[PG_CI_ARCUSFIL_SQL] 0, 0, 0, 53, 'YANFENG AUTOMOTIVE INTERIOR', 'YANFENG AUTOMOTIVE INTERIOR' , 'YANG02' , 200,221 , 54, 'ROAD NOV', '1935 WEST 12 MILE ROAD NOVI, MI 48377' ,'' , '48152' , '2019-11-19' , '53' , '1','','2','MCUEX','','USD','','','N'
B55: 0 | C55: 0 | D55: 0 | E55: 54 | F55: GRAMMER INDUSTRIES, INC | H55: GRAM04 | I55: 200 | J55: 221 | K55: 54 | L55: TROY | M55: 1975 TECHNOLOGY DR | O55: 48083 | P55: 2019-11-19 | Q55: =E55 -> 54 | R55: 1 | T55: 2 | U55: MCUEX | W55: USD | Z55: N | AB55: =CONCATENATE(CI_!$AE$1,E55,", '",F55,"', '",G55,"' , '",H55,"' , ",I55,",",J55," , ",K55,", '",L55,"', '",M55,"' ,'",N55,"' , '",O55,"' , '",P55,"' , '",Q55,"' , '",R55,"','",S55,"','",T55,"','",U55,"','",V55,"','",W55,"','",X55,"','",Y55,"','",Z55,"'") -> EXECUTE [dbo].[PG_CI_ARCUSFIL_SQL] 0, 0, 0, 54, 'GRAMMER INDUSTRIES, INC', '' , 'GRAM04' , 200,221 , 54, 'TROY', '1975 TECHNOLOGY DR' ,'' , '48083' , '2019-11-19' , '54' , '1','','2','MCUEX','','USD','','','N'
B56: 0 | C56: 0 | D56: 0 | E56: 55 | F56: WPI | H56: WPI003 | I56: 200 | J56: 221 | K56: 54 | L56: WILLIAMSTON | M56: WILLIAMSTON PRODUCTS,INC | N56: 845 PROGRESS CT | O56: 48895 | P56: 2019-12-04 | Q56: =E56 -> 55 | R56: 1 | T56: 2 | U56: MCUEX | W56: USD | Z56: N | AB56: =CONCATENATE(CI_!$AE$1,E56,", '",F56,"', '",G56,"' , '",H56,"' , ",I56,",",J56," , ",K56,", '",L56,"', '",M56,"' ,'",N56,"' , '",O56,"' , '",P56,"' , '",Q56,"' , '",R56,"','",S56,"','",T56,"','",U56,"','",V56,"','",W56,"','",X56,"','",Y56,"','",Z56,"'") -> EXECUTE [dbo].[PG_CI_ARCUSFIL_SQL] 0, 0, 0, 55, 'WPI', '' , 'WPI003' , 200,221 , 54, 'WILLIAMSTON', 'WILLIAMSTON PRODUCTS,INC' ,'845 PROGRESS CT' , '48895' , '2019-12-04' , '55' , '1','','2','MCUEX','','USD','','','N'
B57: 0 | C57: 0 | D57: 0 | E57: 56 | F57: DAIMAY AUTOMOTIVE INTERIOR, S. DE R.L. D | G57: DAIMAY AUTOMOTIVE INTE | H57: DAIM05 | I57: 200 | J57: 260 | K57: 5 | L57: RAMOS ARZIPE | M57: AVE. CENZONTLE ESQ. HALCON | N57: CARRETERA MONCLOVA #7 | O57: 0 | P57: 2020-02-05 | Q57: =E57 -> 56 | R57: 1 | S57: OFFICE@DAIMAYUS.COM | T57: 2 | U57: MCUEX | W57: USD | Z57: N | AB57: =CONCATENATE(CI_!$AE$1,E57,", '",F57,"', '",G57,"' , '",H57,"' , ",I57,",",J57," , ",K57,", '",L57,"', '",M57,"' ,'",N57,"' , '",O57,"' , '",P57,"' , '",Q57,"' , '",R57,"','",S57,"','",T57,"','",U57,"','",V57,"','",W57,"','",X57,"','",Y57,"','",Z57,"'") -> EXECUTE [dbo].[PG_CI_ARCUSFIL_SQL] 0, 0, 0, 56, 'DAIMAY AUTOMOTIVE INTERIOR, S. DE R.L. D', 'DAIMAY AUTOMOTIVE INTE' , 'DAIM05' , 200,260 , 5, 'RAMOS ARZIPE', 'AVE. CENZONTLE ESQ. HALCON' ,'CARRETERA MONCLOVA #7' , '0' , '2020-02-05' , '56' , '1','OFFICE@DAIMAYUS.COM','2','MCUEX','','USD','','','N'
B58: 0 | C58: 0 | D58: 0 | E58: 57 | F58: Eissmann Automotive de Mexico | G58: EISSMANN AUTOMOTIVE DE MEXICO | H58: EISS01 | I58: 200 | J58: 260 | K58: 29 | L58: PANZACOLA | M58: Reforma Sur No. 27 | N58: Nave 1 | O58: 90796 | P58: 2020-09-01 | Q58: =E58 -> 57 | R58: 1 | T58: 2 | U58: MCUEX | W58: USD | Z58: N | AB58: =CONCATENATE(CI_!$AE$1,E58,", '",F58,"', '",G58,"' , '",H58,"' , ",I58,",",J58," , ",K58,", '",L58,"', '",M58,"' ,'",N58,"' , '",O58,"' , '",P58,"' , '",Q58,"' , '",R58,"','",S58,"','",T58,"','",U58,"','",V58,"','",W58,"','",X58,"','",Y58,"','",Z58,"'") -> EXECUTE [dbo].[PG_CI_ARCUSFIL_SQL] 0, 0, 0, 57, 'Eissmann Automotive de Mexico', 'EISSMANN AUTOMOTIVE DE MEXICO' , 'EISS01' , 200,260 , 29, 'PANZACOLA', 'Reforma Sur No. 27' ,'Nave 1' , '90796' , '2020-09-01' , '57' , '1','','2','MCUEX','','USD','','','N'
B59: 0 | C59: 0 | D59: 0 | E59: 58 | F59: YANGFENG AUTOMOTIVE INTERIOR SYSTEMS(THAILAND) CO.,LTD | G59: YANGFENG AUTOMOTIVE INTERIOR SYSTEMS(THAILAND) CO.,LTD | H59: YANG03 | I59: 300 | J59: 349 | K59: 123 | L59: CHONBURI | M59: 700/20 WHA EASTERN SEABOARD INDUSTRIAL | N59: 1 MOO 7 TAMBOL KAOKANSONG, AMPHUR SRIRACH | O59: 700/20 | P59: 2020-11-19 | Q59: =E59 -> 58 | R59: 1 | T59: 11 | U59: MCUEX | W59: USD | Z59: N | AB59: =CONCATENATE(CI_!$AE$1,E59,", '",F59,"', '",G59,"' , '",H59,"' , ",I59,",",J59," , ",K59,", '",L59,"', '",M59,"' ,'",N59,"' , '",O59,"' , '",P59,"' , '",Q59,"' , '",R59,"','",S59,"','",T59,"','",U59,"','",V59,"','",W59,"','",X59,"','",Y59,"','",Z59,"'") -> EXECUTE [dbo].[PG_CI_ARCUSFIL_SQL] 0, 0, 0, 58, 'YANGFENG AUTOMOTIVE INTERIOR SYSTEMS(THAILAND) CO.,LTD', 'YANGFENG AUTOMOTIVE INTERIOR SYSTEMS(THAILAND) CO.,LTD' , 'YANG03' , 300,349 , 123, 'CHONBURI', '700/20 WHA EASTERN SEABOARD INDUSTRIAL' ,'1 MOO 7 TAMBOL KAOKANSONG, AMPHUR SRIRACH' , '700/20' , '2020-11-19' , '58' , '1','','11','MCUEX','','USD','','','N'
B60: 0 | C60: 0 | D60: 0 | E60: 59 | F60: ADIENT US LLC | H60: ADIE01 | I60: 200 | J60: 221 | K60: 54 | L60: PLYMOUTH | M60: 49200 HALYARD DRIVE.PLYMOUTH, | O60: 49200 | P60: 2020-12-16 | Q60: =E60 -> 59 | R60: 1 | T60: 2 | U60: MCUEX | W60: USD | Z60: N | AB60: =CONCATENATE(CI_!$AE$1,E60,", '",F60,"', '",G60,"' , '",H60,"' , ",I60,",",J60," , ",K60,", '",L60,"', '",M60,"' ,'",N60,"' , '",O60,"' , '",P60,"' , '",Q60,"' , '",R60,"','",S60,"','",T60,"','",U60,"','",V60,"','",W60,"','",X60,"','",Y60,"','",Z60,"'") -> EXECUTE [dbo].[PG_CI_ARCUSFIL_SQL] 0, 0, 0, 59, 'ADIENT US LLC', '' , 'ADIE01' , 200,221 , 54, 'PLYMOUTH', '49200 HALYARD DRIVE.PLYMOUTH,' ,'' , '49200' , '2020-12-16' , '59' , '1','','2','MCUEX','','USD','','','N'
B61: 0 | C61: 0 | D61: 0 | E61: 60 | F61: YANFENG AUTOMOTIVE INTER S. (THAILAND) | G61: YANFENG AUTOMOTIVE INTER S. (THAILAND) | H61: YANG04 | I61: 300 | J61: 349 | K61: 123 | L61: CHONBURI | M61: 700/20 WHA EASTERN SEABOARD INDUSTRIAL | N61: 1 MOO 7 TAMBOL KAOKANSONG,AMPHUR SRIRACH | O61: 700/20 | P61: 2021-01-11 | Q61: =E61 -> 60 | R61: 1 | T61: 5 | U61: MFUEX | W61: USD | Z61: N | AB61: =CONCATENATE(CI_!$AE$1,E61,", '",F61,"', '",G61,"' , '",H61,"' , ",I61,",",J61," , ",K61,", '",L61,"', '",M61,"' ,'",N61,"' , '",O61,"' , '",P61,"' , '",Q61,"' , '",R61,"','",S61,"','",T61,"','",U61,"','",V61,"','",W61,"','",X61,"','",Y61,"','",Z61,"'") -> EXECUTE [dbo].[PG_CI_ARCUSFIL_SQL] 0, 0, 0, 60, 'YANFENG AUTOMOTIVE INTER S. (THAILAND)', 'YANFENG AUTOMOTIVE INTER S. (THAILAND)' , 'YANG04' , 300,349 , 123, 'CHONBURI', '700/20 WHA EASTERN SEABOARD INDUSTRIAL' ,'1 MOO 7 TAMBOL KAOKANSONG,AMPHUR SRIRACH' , '700/20' , '2021-01-11' , '60' , '1','','5','MFUEX','','USD','','','N'
B62: - | C62: - | D62: - | E62: - | F62: - | G62: - | H62: - | I62: - | J62: - | K62: - | L62: - | AB62: =CONCATENATE(CI_!$AE$1,E62,", '",F62,"', '",G62,"' , '",H62,"' , ",I62,",",J62," , ",K62,", '",L62,"', '",M62,"' ,'",N62,"' , '",O62,"' , '",P62,"' , '",Q62,"' , '",R62,"','",S62,"','",T62,"','",U62,"','",V62,"','",W62,"','",X62,"','",Y62,"','",Z62,"'") -> EXECUTE [dbo].[PG_CI_ARCUSFIL_SQL] 0, 0, 0, -, '-', '-' , '-' , -,- , -, '-', '' ,'' , '' , '' , '' , '','','','','','','','',''

Sheet ADDRESS
A1: ??? | B1: L_DEBUG | C1: K_SISTEMA_EXE | D1: K_USUARIO_ACCION | E1: [K_CUSTOMER] | F1: [K_ADDRESS_TYPE] | G1: [D_CUSTOMER_ADDRESS_NAME] | H1: [D_CUSTOMER_ADDRESS_01] | I1: [D_CUSTOMER_ADDRESS_02] | J1: [D_CUSTOMER_ADDRESS_03] | K1: [D_CUSTOMER_ADDRESS_04] | L1: [L_CUSTOMER_ADDRESS_MAIN] | N1: EXECUTE [dbo].[ | O1: =TABLE!A1 -> PG_CI_CUSTOMER | P1: ] | Q1: =CONCATENATE($N$1,$O$1,$P$1,B3, ", ", C3, ", ", D3, ", ", ) -> EXECUTE [dbo].[PG_CI_CUSTOMER] 0, 0, 0,
B2: - | C2: - | D2: - | E2: - | F2: - | G2: - | H2: - | I2: - | J2: - | K2: - | N2: ="-- ==========================================================" -> -- ==========================================================
B3: 0 | C3: 0 | D3: 0 | E3: 56 | F3: 1 | G3: DAIMAY AUTOMOTIVE INTERIOR, S DE R.L. DE | H3: AVE. CENZONTLE ESQ. HALCON | I3: CARRETERA MONCLOVA #7 | J3: PARQUE INDUSTRIAL FINSA | K3: RAMOS ARZIPE COAH | L3: 1 | N3: =CONCATENATE(ADDRESS!$Q$1,E3,", '",F3,"', '",G3,"' , '",H3,"' , '",I3,"' , '",J3,"', '",K3,"', '",L3,"'") -> EXECUTE [dbo].[PG_CI_CUSTOMER] 0, 0, 0, 56, '1', 'DAIMAY AUTOMOTIVE INTERIOR, S DE R.L. DE' , 'AVE. CENZONTLE ESQ. HALCON' , 'CARRETERA MONCLOVA #7' , 'PARQUE INDUSTRIAL FINSA', 'RAMOS ARZIPE COAH', '1'
B4: 0 | C4: 0 | D4: 0 | E4: 56 | F4: 2 | G4: DAIMAY AUTOMOTIVE INTERIOR, S DE R.L. DE | H4: AVE. CENZONTLE ESQ. HALCON | I4: CARRETERA MONCLOVA #7 | J4: PARQUE INDUSTRIAL FINSA | K4: RAMOS ARZIPE COAH | L4: 1 | N4: =CONCATENATE(ADDRESS!$Q$1,E4,", '",F4,"', '",G4,"' , '",H4,"' , '",I4,"' , '",J4,"', '",K4,"', '",L4,"'") -> EXECUTE [dbo].[PG_CI_CUSTOMER] 0, 0, 0, 56, '2', 'DAIMAY AUTOMOTIVE INTERIOR, S DE R.L. DE' , 'AVE. CENZONTLE ESQ. HALCON' , 'CARRETERA MONCLOVA #7' , 'PARQUE INDUSTRIAL FINSA', 'RAMOS ARZIPE COAH', '1'
B5: 0 | C5: 0 | D5: 0 | E5: 57 | F5: 1 | G5: Eissmann Automotive de Mexico | H5: Reforma Sur No. 27 | I5: Nave 1 | J5: Panzacola, 90796 | K5: MEXICO | L5: 1 | N5: =CONCATENATE(ADDRESS!$Q$1,E5,", '",F5,"', '",G5,"' , '",H5,"' , '",I5,"' , '",J5,"', '",K5,"', '",L5,"'") -> EXECUTE [dbo].[PG_CI_CUSTOMER] 0, 0, 0, 57, '1', 'Eissmann Automotive de Mexico' , 'Reforma Sur No. 27' , 'Nave 1' , 'Panzacola, 90796', 'MEXICO', '1'
B6: 0 | C6: 0 | D6: 0 | E6: 57 | F6: 2 | G6: Eissmann Automotive de Mexico | H6: Reforma Sur No. 27 | I6: Nave 1 | J6: Panzacola, 90796 | K6: MEXICO | L6: 1 | N6: =CONCATENATE(ADDRESS!$Q$1,E6,", '",F6,"', '",G6,"' , '",H6,"' , '",I6,"' , '",J6,"', '",K6,"', '",L6,"'") -> EXECUTE [dbo].[PG_CI_CUSTOMER] 0, 0, 0, 57, '2', 'Eissmann Automotive de Mexico' , 'Reforma Sur No. 27' , 'Nave 1' , 'Panzacola, 90796', 'MEXICO', '1'
B7: 0 | C7: 0 | D7: 0 | E7: 34 | F7: 1 | G7: Irvin Automotive Products, LLC | H7: 2A Fawcett Dr. | I7: Del Rio, TX 78840 | J7: United States | L7: 1 | N7: =CONCATENATE(ADDRESS!$Q$1,E7,", '",F7,"', '",G7,"' , '",H7,"' , '",I7,"' , '",J7,"', '",K7,"', '",L7,"'") -> EXECUTE [dbo].[PG_CI_CUSTOMER] 0, 0, 0, 34, '1', 'Irvin Automotive Products, LLC' , '2A Fawcett Dr.' , 'Del Rio, TX 78840' , 'United States', '', '1'
B8: 0 | C8: 0 | D8: 0 | E8: 34 | F8: 2 | G8: Irvin Automotive Products, LLC | H8: 2A Fawcett Dr. | I8: Del Rio, TX 78840 | J8: United States | L8: 1 | N8: =CONCATENATE(ADDRESS!$Q$1,E8,", '",F8,"', '",G8,"' , '",H8,"' , '",I8,"' , '",J8,"', '",K8,"', '",L8,"'") -> EXECUTE [dbo].[PG_CI_CUSTOMER] 0, 0, 0, 34, '2', 'Irvin Automotive Products, LLC' , '2A Fawcett Dr.' , 'Del Rio, TX 78840' , 'United States', '', '1'
B9: 0 | C9: 0 | D9: 0 | E9: 18 | F9: 1 | G9: MAGNA SEATING OF AMERICA INC | H9: 2199 SPUR 239 | I9: MAILING TO: P.O. BOX 420699 | J9: DEL RIO TX 78840 | K9: USA | L9: 1 | N9: =CONCATENATE(ADDRESS!$Q$1,E9,", '",F9,"', '",G9,"' , '",H9,"' , '",I9,"' , '",J9,"', '",K9,"', '",L9,"'") -> EXECUTE [dbo].[PG_CI_CUSTOMER] 0, 0, 0, 18, '1', 'MAGNA SEATING OF AMERICA INC' , '2199 SPUR 239' , 'MAILING TO: P.O. BOX 420699' , 'DEL RIO TX 78840', 'USA', '1'
B10: 0 | C10: 0 | D10: 0 | E10: 18 | F10: 2 | G10: MAGNA SEATING OF AMERICA INC | H10: 2199 SPUR 239 | I10: MAILING TO: P.O. BOX 420699 | J10: DEL RIO TX 78840 | K10: USA | L10: 1 | N10: =CONCATENATE(ADDRESS!$Q$1,E10,", '",F10,"', '",G10,"' , '",H10,"' , '",I10,"' , '",J10,"', '",K10,"', '",L10,"'") -> EXECUTE [dbo].[PG_CI_CUSTOMER] 0, 0, 0, 18, '2', 'MAGNA SEATING OF AMERICA INC' , '2199 SPUR 239' , 'MAILING TO: P.O. BOX 420699' , 'DEL RIO TX 78840', 'USA', '1'
B11: 0 | C11: 0 | D11: 0 | E11: 19 | F11: 1 | G11: SEATING SYS.OF ACUNA DIV INTIER AUTO | H11: 2199 SPUR 239 | I11: P.O. BOX 420699 | J11: DEL RIO, TX 78840 | K11: USA | L11: 1 | N11: =CONCATENATE(ADDRESS!$Q$1,E11,", '",F11,"', '",G11,"' , '",H11,"' , '",I11,"' , '",J11,"', '",K11,"', '",L11,"'") -> EXECUTE [dbo].[PG_CI_CUSTOMER] 0, 0, 0, 19, '1', 'SEATING SYS.OF ACUNA DIV INTIER AUTO' , '2199 SPUR 239' , 'P.O. BOX 420699' , 'DEL RIO, TX 78840', 'USA', '1'
B12: 0 | C12: 0 | D12: 0 | E12: 19 | F12: 2 | G12: SEATING SYS.OF ACUNA DIV INTIER AUTO | H12: 2199 SPUR 239 | I12: P.O. BOX 420699 | J12: DEL RIO, TX 78840 | K12: USA | L12: 1 | N12: =CONCATENATE(ADDRESS!$Q$1,E12,", '",F12,"', '",G12,"' , '",H12,"' , '",I12,"' , '",J12,"', '",K12,"', '",L12,"'") -> EXECUTE [dbo].[PG_CI_CUSTOMER] 0, 0, 0, 19, '2', 'SEATING SYS.OF ACUNA DIV INTIER AUTO' , '2199 SPUR 239' , 'P.O. BOX 420699' , 'DEL RIO, TX 78840', 'USA', '1'
B13: 0 | C13: 0 | D13: 0 | E13: 36 | F13: 1 | G13: SALTILLO INTERIOR TRIM SA DE CV | H13: AUTOPISTA SALTILLO-MONTERREY KM 11.50 | I13: PARQUE INDUSTRIAL RAMOS ARIZPE | J13: COAHUILA, CP 25900 | L13: 1 | N13: =CONCATENATE(ADDRESS!$Q$1,E13,", '",F13,"', '",G13,"' , '",H13,"' , '",I13,"' , '",J13,"', '",K13,"', '",L13,"'") -> EXECUTE [dbo].[PG_CI_CUSTOMER] 0, 0, 0, 36, '1', 'SALTILLO INTERIOR TRIM SA DE CV' , 'AUTOPISTA SALTILLO-MONTERREY KM 11.50' , 'PARQUE INDUSTRIAL RAMOS ARIZPE' , 'COAHUILA, CP 25900', '', '1'
B14: 0 | C14: 0 | D14: 0 | E14: 36 | F14: 2 | G14: SALTILLO INTERIOR TRIM SA DE CV | H14: AUTOPISTA SALTILLO-MONTERREY KM 11.50 | I14: PARQUE INDUSTRIAL RAMOS ARIZPE | J14: COAHUILA, CP 25900 | L14: 1 | N14: =CONCATENATE(ADDRESS!$Q$1,E14,", '",F14,"', '",G14,"' , '",H14,"' , '",I14,"' , '",J14,"', '",K14,"', '",L14,"'") -> EXECUTE [dbo].[PG_CI_CUSTOMER] 0, 0, 0, 36, '2', 'SALTILLO INTERIOR TRIM SA DE CV' , 'AUTOPISTA SALTILLO-MONTERREY KM 11.50' , 'PARQUE INDUSTRIAL RAMOS ARIZPE' , 'COAHUILA, CP 25900', '', '1'
B15: 0 | C15: 0 | D15: 0 | E15: 55 | F15: 1 | G15: WPI | H15: 845 PROGRESS CT. WILLIAMSTON, MI 48895 | I15: WILLIAMSTON, MI | L15: 1 | N15: =CONCATENATE(ADDRESS!$Q$1,E15,", '",F15,"', '",G15,"' , '",H15,"' , '",I15,"' , '",J15,"', '",K15,"', '",L15,"'") -> EXECUTE [dbo].[PG_CI_CUSTOMER] 0, 0, 0, 55, '1', 'WPI' , '845 PROGRESS CT. WILLIAMSTON, MI 48895' , 'WILLIAMSTON, MI' , '', '', '1'
B16: 0 | C16: 0 | D16: 0 | E16: 55 | F16: 2 | G16: WPI | H16: 845 PROGRESS CT. WILLIAMSTON, MI 48895 | I16: WILLIAMSTON, MI | L16: 1 | N16: =CONCATENATE(ADDRESS!$Q$1,E16,", '",F16,"', '",G16,"' , '",H16,"' , '",I16,"' , '",J16,"', '",K16,"', '",L16,"'") -> EXECUTE [dbo].[PG_CI_CUSTOMER] 0, 0, 0, 55, '2', 'WPI' , '845 PROGRESS CT. WILLIAMSTON, MI 48895' , 'WILLIAMSTON, MI' , '', '', '1'
B17: 0 | C17: 0 | D17: 0 | E17: 53 | F17: 1 | G17: Yanfeng Mexico | H17: PO BOX 7148 | I17: 48376 Novi MI | J17: UNITED STATES | L17: 1 | N17: =CONCATENATE(ADDRESS!$Q$1,E17,", '",F17,"', '",G17,"' , '",H17,"' , '",I17,"' , '",J17,"', '",K17,"', '",L17,"'") -> EXECUTE [dbo].[PG_CI_CUSTOMER] 0, 0, 0, 53, '1', 'Yanfeng Mexico' , 'PO BOX 7148' , '48376 Novi MI' , 'UNITED STATES', '', '1'
B18: 0 | C18: 0 | D18: 0 | E18: 53 | F18: 2 | G18: Yanfeng Mexico | H18: PO BOX 7148 | I18: 48376 Novi MI | J18: UNITED STATES | L18: 1 | N18: =CONCATENATE(ADDRESS!$Q$1,E18,", '",F18,"', '",G18,"' , '",H18,"' , '",I18,"' , '",J18,"', '",K18,"', '",L18,"'") -> EXECUTE [dbo].[PG_CI_CUSTOMER] 0, 0, 0, 53, '2', 'Yanfeng Mexico' , 'PO BOX 7148' , '48376 Novi MI' , 'UNITED STATES', '', '1'
B19: 0 | C19: 0 | D19: 0 | E19: 58 | F19: 1 | G19: YANGFENG AUTOMOTIVE INTERIOR SYSTEMS(THAILAND) CO.,LTD | H19: 700/20 WHA EASTERN SEABOARD INDUSTRIAL | I19: 1 M00 7 Tambol Khao Khan Song, Amphur Sriracha | J19: CHONBURI, 700/20 | K19: THAILAND TAX ID:0205562018045 | L19: 1 | N19: =CONCATENATE(ADDRESS!$Q$1,E19,", '",F19,"', '",G19,"' , '",H19,"' , '",I19,"' , '",J19,"', '",K19,"', '",L19,"'") -> EXECUTE [dbo].[PG_CI_CUSTOMER] 0, 0, 0, 58, '1', 'YANGFENG AUTOMOTIVE INTERIOR SYSTEMS(THAILAND) CO.,LTD' , '700/20 WHA EASTERN SEABOARD INDUSTRIAL' , '1 M00 7 Tambol Khao Khan Song, Amphur Sriracha' , 'CHONBURI, 700/20', 'THAILAND TAX ID:0205562018045', '1'
B20: 0 | C20: 0 | D20: 0 | E20: 58 | F20: 2 | G20: YANGFENG AUTOMOTIVE INTERIOR SYSTEMS(THAILAND) CO.,LTD | H20: 700/20 WHA EASTERN SEABOARD INDUSTRIAL | I20: 1 M00 7 Tambol Khao Khan Song, Amphur Sriracha | J20: CHONBURI, 700/20 | K20: THAILAND TAX ID:0205562018045 | L20: 1 | N20: =CONCATENATE(ADDRESS!$Q$1,E20,", '",F20,"', '",G20,"' , '",H20,"' , '",I20,"' , '",J20,"', '",K20,"', '",L20,"'") -> EXECUTE [dbo].[PG_CI_CUSTOMER] 0, 0, 0, 58, '2', 'YANGFENG AUTOMOTIVE INTERIOR SYSTEMS(THAILAND) CO.,LTD' , '700/20 WHA EASTERN SEABOARD INDUSTRIAL' , '1 M00 7 Tambol Khao Khan Song, Amphur Sriracha' , 'CHONBURI, 700/20', 'THAILAND TAX ID:0205562018045', '1'

Sheet CONTACT
A1: ??? | B1: L_DEBUG | C1: K_SISTEMA_EXE | D1: K_USUARIO_ACCION | E1: [K_CUSTOMER] | F1: [D_CUSTOMER_CONTACT_NAME] | G1: [CUSTOMER_CONTACT_PHONE_01] | H1: [CUSTOMER_CONTACT_PHONE_01_EXT] | I1: [CUSTOMER_CONTACT_EMAIL_01] | J1: [CUSTOMER_CONTACT_FAX_01] | K1: [C_CUSTOMER_CONTACT] | M1: EXECUTE [dbo].[ | N1: =TABLE!A1 -> PG_CI_CUSTOMER | O1: ] | P1: =CONCATENATE($M$1,$N$1,$O$1,B3, ", ", C3, ", ", D3, ", ", ) -> EXECUTE [dbo].[PG_CI_CUSTOMER] 0, 0, 0,
B2: - | C2: - | D2: - | E2: - | F2: - | G2: - | H2: - | I2: - | J2: - | K2: - | M2: ="-- ==========================================================" -> -- ==========================================================
B3: 0 | C3: 0 | D3: 0 | E3: 59 | F3: MAURICIO ESPINOSA | G3: 18773348706 | M3: =CONCATENATE(CONTACT!$P$1,E3,", '",F3,"', '",G3,"' , '",H3,"' , '",I3,"' , '",J3,"', '",K3,"'") -> EXECUTE [dbo].[PG_CI_CUSTOMER] 0, 0, 0, 59, 'MAURICIO ESPINOSA', '18773348706' , '' , '' , '', ''
B4: 0 | C4: 0 | D4: 0 | E4: 46 | I4: bkamali@kamaligroup.com | M4: =CONCATENATE(CONTACT!$P$1,E4,", '",F4,"', '",G4,"' , '",H4,"' , '",I4,"' , '",J4,"', '",K4,"'") -> EXECUTE [dbo].[PG_CI_CUSTOMER] 0, 0, 0, 46, '', '' , '' , 'bkamali@kamaligroup.com' , '', ''
B5: 0 | C5: 0 | D5: 0 | E5: 49 | F5: RUTH KAMALI | G5: 5166274000 | M5: =CONCATENATE(CONTACT!$P$1,E5,", '",F5,"', '",G5,"' , '",H5,"' , '",I5,"' , '",J5,"', '",K5,"'") -> EXECUTE [dbo].[PG_CI_CUSTOMER] 0, 0, 0, 49, 'RUTH KAMALI', '5166274000' , '' , '' , '', ''
B6: 0 | C6: 0 | D6: 0 | E6: 29 | G6: 5197333713 | J6: 5197335887 | M6: =CONCATENATE(CONTACT!$P$1,E6,", '",F6,"', '",G6,"' , '",H6,"' , '",I6,"' , '",J6,"', '",K6,"'") -> EXECUTE [dbo].[PG_CI_CUSTOMER] 0, 0, 0, 29, '', '5197333713' , '' , '' , '5197335887', ''
B7: 0 | C7: 0 | D7: 0 | E7: 33 | M7: =CONCATENATE(CONTACT!$P$1,E7,", '",F7,"', '",G7,"' , '",H7,"' , '",I7,"' , '",J7,"', '",K7,"'") -> EXECUTE [dbo].[PG_CI_CUSTOMER] 0, 0, 0, 33, '', '' , '' , '' , '', ''
B8: 0 | C8: 0 | D8: 0 | E8: 42 | F8: ROGELIO CORRAL | G8: 6563827522 | M8: =CONCATENATE(CONTACT!$P$1,E8,", '",F8,"', '",G8,"' , '",H8,"' , '",I8,"' , '",J8,"', '",K8,"'") -> EXECUTE [dbo].[PG_CI_CUSTOMER] 0, 0, 0, 42, 'ROGELIO CORRAL', '6563827522' , '' , '' , '', ''
B9: 0 | C9: 0 | D9: 0 | E9: 1 | F9: NIKKI OSTERLAND | G9: 2485857700 | J9: 2485855800 | M9: =CONCATENATE(CONTACT!$P$1,E9,", '",F9,"', '",G9,"' , '",H9,"' , '",I9,"' , '",J9,"', '",K9,"'") -> EXECUTE [dbo].[PG_CI_CUSTOMER] 0, 0, 0, 1, 'NIKKI OSTERLAND', '2485857700' , '' , '' , '2485855800', ''
B10: 0 | C10: 0 | D10: 0 | E10: 56 | I10: Office@daimayus.com | M10: =CONCATENATE(CONTACT!$P$1,E10,", '",F10,"', '",G10,"' , '",H10,"' , '",I10,"' , '",J10,"', '",K10,"'") -> EXECUTE [dbo].[PG_CI_CUSTOMER] 0, 0, 0, 56, '', '' , '' , 'Office@daimayus.com' , '', ''
B11: 0 | C11: 0 | D11: 0 | E11: 2 | G11: 9783565701 | J11: 9783569832 | M11: =CONCATENATE(CONTACT!$P$1,E11,", '",F11,"', '",G11,"' , '",H11,"' , '",I11,"' , '",J11,"', '",K11,"'") -> EXECUTE [dbo].[PG_CI_CUSTOMER] 0, 0, 0, 2, '', '9783565701' , '' , '' , '9783569832', ''
B12: 0 | C12: 0 | D12: 0 | E12: 57 | M12: =CONCATENATE(CONTACT!$P$1,E12,", '",F12,"', '",G12,"' , '",H12,"' , '",I12,"' , '",J12,"', '",K12,"'") -> EXECUTE [dbo].[PG_CI_CUSTOMER] 0, 0, 0, 57, '', '' , '' , '' , '', ''
B13: 0 | C13: 0 | D13: 0 | E13: 3 | F13: LUIS ENRIQUE HERNANDEZ | M13: =CONCATENATE(CONTACT!$P$1,E13,", '",F13,"', '",G13,"' , '",H13,"' , '",I13,"' , '",J13,"', '",K13,"'") -> EXECUTE [dbo].[PG_CI_CUSTOMER] 0, 0, 0, 3, 'LUIS ENRIQUE HERNANDEZ', '' , '' , '' , '', ''
B14: 0 | C14: 0 | D14: 0 | E14: 51 | F14: ACCOUNTS PAYABLE | M14: =CONCATENATE(CONTACT!$P$1,E14,", '",F14,"', '",G14,"' , '",H14,"' , '",I14,"' , '",J14,"', '",K14,"'") -> EXECUTE [dbo].[PG_CI_CUSTOMER] 0, 0, 0, 51, 'ACCOUNTS PAYABLE', '' , '' , '' , '', ''
B15: 0 | C15: 0 | D15: 0 | E15: 4 | G15: 4194245429 | J15: 4194223164 | M15: =CONCATENATE(CONTACT!$P$1,E15,", '",F15,"', '",G15,"' , '",H15,"' , '",I15,"' , '",J15,"', '",K15,"'") -> EXECUTE [dbo].[PG_CI_CUSTOMER] 0, 0, 0, 4, '', '4194245429' , '' , '' , '4194223164', ''
B16: 0 | C16: 0 | D16: 0 | E16: 5 | F16: WILLIS I SIMMONS | G16: 9416766081 | J16: 9416766463 | M16: =CONCATENATE(CONTACT!$P$1,E16,", '",F16,"', '",G16,"' , '",H16,"' , '",I16,"' , '",J16,"', '",K16,"'") -> EXECUTE [dbo].[PG_CI_CUSTOMER] 0, 0, 0, 5, 'WILLIS I SIMMONS', '9416766081' , '' , '' , '9416766463', ''
B17: 0 | C17: 0 | D17: 0 | E17: 6 | F17: ROSA BOURDEAU | M17: =CONCATENATE(CONTACT!$P$1,E17,", '",F17,"', '",G17,"' , '",H17,"' , '",I17,"' , '",J17,"', '",K17,"'") -> EXECUTE [dbo].[PG_CI_CUSTOMER] 0, 0, 0, 6, 'ROSA BOURDEAU', '' , '' , '' , '', ''
B18: 0 | C18: 0 | D18: 0 | E18: 40 | F18: CLEMENCIA VIVEROS | G18: 522414184600 | H18: 3654 | J18: 522414127291 | M18: =CONCATENATE(CONTACT!$P$1,E18,", '",F18,"', '",G18,"' , '",H18,"' , '",I18,"' , '",J18,"', '",K18,"'") -> EXECUTE [dbo].[PG_CI_CUSTOMER] 0, 0, 0, 40, 'CLEMENCIA VIVEROS', '522414184600' , '3654' , '' , '522414127291', ''
B19: 0 | C19: 0 | D19: 0 | E19: 54 | M19: =CONCATENATE(CONTACT!$P$1,E19,", '",F19,"', '",G19,"' , '",H19,"' , '",I19,"' , '",J19,"', '",K19,"'") -> EXECUTE [dbo].[PG_CI_CUSTOMER] 0, 0, 0, 54, '', '' , '' , '' , '', ''
B20: 0 | C20: 0 | D20: 0 | E20: 7 | F20: MARIA CLABORN | G20: 12484514216 | M20: =CONCATENATE(CONTACT!$P$1,E20,", '",F20,"', '",G20,"' , '",H20,"' , '",I20,"' , '",J20,"', '",K20,"'") -> EXECUTE [dbo].[PG_CI_CUSTOMER] 0, 0, 0, 7, 'MARIA CLABORN', '12484514216' , '' , '' , '', ''
B21: 0 | C21: 0 | D21: 0 | E21: 34 | F21: LISA BETH RUMPL | G21: 2484514276 | J21: 2484514230 | M21: =CONCATENATE(CONTACT!$P$1,E21,", '",F21,"', '",G21,"' , '",H21,"' , '",I21,"' , '",J21,"', '",K21,"'") -> EXECUTE [dbo].[PG_CI_CUSTOMER] 0, 0, 0, 34, 'LISA BETH RUMPL', '2484514276' , '' , '' , '2484514230', ''
B22: 0 | C22: 0 | D22: 0 | E22: 8 | G22: 5252847224 | J22: 5252847231 | M22: =CONCATENATE(CONTACT!$P$1,E22,", '",F22,"', '",G22,"' , '",H22,"' , '",I22,"' , '",J22,"', '",K22,"'") -> EXECUTE [dbo].[PG_CI_CUSTOMER] 0, 0, 0, 8, '', '5252847224' , '' , '' , '5252847231', ''
B23: 0 | C23: 0 | D23: 0 | E23: 32 | F23: RICARDO PEREZ | G23: 015552847154 | J23: 015552847210 | M23: =CONCATENATE(CONTACT!$P$1,E23,", '",F23,"', '",G23,"' , '",H23,"' , '",I23,"' , '",J23,"', '",K23,"'") -> EXECUTE [dbo].[PG_CI_CUSTOMER] 0, 0, 0, 32, 'RICARDO PEREZ', '015552847154' , '' , '' , '015552847210', ''
B24: 0 | C24: 0 | D24: 0 | E24: 9 | M24: =CONCATENATE(CONTACT!$P$1,E24,", '",F24,"', '",G24,"' , '",H24,"' , '",I24,"' , '",J24,"', '",K24,"'") -> EXECUTE [dbo].[PG_CI_CUSTOMER] 0, 0, 0, 9, '', '' , '' , '' , '', ''
B25: 0 | C25: 0 | D25: 0 | E25: 37 | F25: BETHANY SCOTT | M25: =CONCATENATE(CONTACT!$P$1,E25,", '",F25,"', '",G25,"' , '",H25,"' , '",I25,"' , '",J25,"', '",K25,"'") -> EXECUTE [dbo].[PG_CI_CUSTOMER] 0, 0, 0, 37, 'BETHANY SCOTT', '' , '' , '' , '', ''
B26: 0 | C26: 0 | D26: 0 | E26: 38 | F26: MIKE CHOPSON | M26: =CONCATENATE(CONTACT!$P$1,E26,", '",F26,"', '",G26,"' , '",H26,"' , '",I26,"' , '",J26,"', '",K26,"'") -> EXECUTE [dbo].[PG_CI_CUSTOMER] 0, 0, 0, 38, 'MIKE CHOPSON', '' , '' , '' , '', ''
B27: 0 | C27: 0 | D27: 0 | E27: 48 | F27: RUTH KAMALI | M27: =CONCATENATE(CONTACT!$P$1,E27,", '",F27,"', '",G27,"' , '",H27,"' , '",I27,"' , '",J27,"', '",K27,"'") -> EXECUTE [dbo].[PG_CI_CUSTOMER] 0, 0, 0, 48, 'RUTH KAMALI', '' , '' , '' , '', ''
B28: 0 | C28: 0 | D28: 0 | E28: 39 | F28: DAVE SCHUTTER | G28: 12486153090 | J28: 12486153098 | M28: =CONCATENATE(CONTACT!$P$1,E28,", '",F28,"', '",G28,"' , '",H28,"' , '",I28,"' , '",J28,"', '",K28,"'") -> EXECUTE [dbo].[PG_CI_CUSTOMER] 0, 0, 0, 39, 'DAVE SCHUTTER', '12486153090' , '' , '' , '12486153098', ''
B29: 0 | C29: 0 | D29: 0 | E29: 10 | F29: STEVE KRAFT | G29: 5175457500 | J29: 5175458199 | M29: =CONCATENATE(CONTACT!$P$1,E29,", '",F29,"', '",G29,"' , '",H29,"' , '",I29,"' , '",J29,"', '",K29,"'") -> EXECUTE [dbo].[PG_CI_CUSTOMER] 0, 0, 0, 10, 'STEVE KRAFT', '5175457500' , '' , '' , '5175458199', ''
B30: 0 | C30: 0 | D30: 0 | E30: 11 | G30: 9154994545 | J30: 9158495610 | M30: =CONCATENATE(CONTACT!$P$1,E30,", '",F30,"', '",G30,"' , '",H30,"' , '",I30,"' , '",J30,"', '",K30,"'") -> EXECUTE [dbo].[PG_CI_CUSTOMER] 0, 0, 0, 11, '', '9154994545' , '' , '' , '9158495610', ''
B31: 0 | C31: 0 | D31: 0 | E31: 30 | F31: DAVID RAMOS | M31: =CONCATENATE(CONTACT!$P$1,E31,", '",F31,"', '",G31,"' , '",H31,"' , '",I31,"' , '",J31,"', '",K31,"'") -> EXECUTE [dbo].[PG_CI_CUSTOMER] 0, 0, 0, 30, 'DAVID RAMOS', '' , '' , '' , '', ''
B32: 0 | C32: 0 | D32: 0 | E32: 12 | F32: CATHY SADLER | M32: =CONCATENATE(CONTACT!$P$1,E32,", '",F32,"', '",G32,"' , '",H32,"' , '",I32,"' , '",J32,"', '",K32,"'") -> EXECUTE [dbo].[PG_CI_CUSTOMER] 0, 0, 0, 12, 'CATHY SADLER', '' , '' , '' , '', ''
B33: 0 | C33: 0 | D33: 0 | E33: 13 | M33: =CONCATENATE(CONTACT!$P$1,E33,", '",F33,"', '",G33,"' , '",H33,"' , '",I33,"' , '",J33,"', '",K33,"'") -> EXECUTE [dbo].[PG_CI_CUSTOMER] 0, 0, 0, 13, '', '' , '' , '' , '', ''
B34: 0 | C34: 0 | D34: 0 | E34: 14 | F34: Ms Daniela Olejnik | G34: 13137554909 | J34: 13137554898 | M34: =CONCATENATE(CONTACT!$P$1,E34,", '",F34,"', '",G34,"' , '",H34,"' , '",I34,"' , '",J34,"', '",K34,"'") -> EXECUTE [dbo].[PG_CI_CUSTOMER] 0, 0, 0, 14, 'Ms Daniela Olejnik', '13137554909' , '' , '' , '13137554898', ''
B35: 0 | C35: 0 | D35: 0 | E35: 15 | G35: 8105780400 | M35: =CONCATENATE(CONTACT!$P$1,E35,", '",F35,"', '",G35,"' , '",H35,"' , '",I35,"' , '",J35,"', '",K35,"'") -> EXECUTE [dbo].[PG_CI_CUSTOMER] 0, 0, 0, 15, '', '8105780400' , '' , '' , '', ''
B36: 0 | C36: 0 | D36: 0 | E36: 16 | F36: LILA MACKEY | G36: 3135939000 | J36: 3132535041 | M36: =CONCATENATE(CONTACT!$P$1,E36,", '",F36,"', '",G36,"' , '",H36,"' , '",I36,"' , '",J36,"', '",K36,"'") -> EXECUTE [dbo].[PG_CI_CUSTOMER] 0, 0, 0, 16, 'LILA MACKEY', '3135939000' , '' , '' , '3132535041', ''
B37: 0 | C37: 0 | D37: 0 | E37: 17 | F37: DOUG DEATON | G37: 0115286130319 | M37: =CONCATENATE(CONTACT!$P$1,E37,", '",F37,"', '",G37,"' , '",H37,"' , '",I37,"' , '",J37,"', '",K37,"'") -> EXECUTE [dbo].[PG_CI_CUSTOMER] 0, 0, 0, 17, 'DOUG DEATON', '0115286130319' , '' , '' , '', ''
B38: 0 | C38: 0 | D38: 0 | E38: 18 | M38: =CONCATENATE(CONTACT!$P$1,E38,", '",F38,"', '",G38,"' , '",H38,"' , '",I38,"' , '",J38,"', '",K38,"'") -> EXECUTE [dbo].[PG_CI_CUSTOMER] 0, 0, 0, 18, '', '' , '' , '' , '', ''
B39: 0 | C39: 0 | D39: 0 | E39: 19 | F39: MARILY BURKE | M39: =CONCATENATE(CONTACT!$P$1,E39,", '",F39,"', '",G39,"' , '",H39,"' , '",I39,"' , '",J39,"', '",K39,"'") -> EXECUTE [dbo].[PG_CI_CUSTOMER] 0, 0, 0, 19, 'MARILY BURKE', '' , '' , '' , '', ''
B40: 0 | C40: 0 | D40: 0 | E40: 47 | M40: =CONCATENATE(CONTACT!$P$1,E40,", '",F40,"', '",G40,"' , '",H40,"' , '",I40,"' , '",J40,"', '",K40,"'") -> EXECUTE [dbo].[PG_CI_CUSTOMER] 0, 0, 0, 47, '', '' , '' , '' , '', ''
B41: 0 | C41: 0 | D41: 0 | E41: 41 | F41: LISA FIRTH | G41: 5172236734 | J41: 5172231331 | M41: =CONCATENATE(CONTACT!$P$1,E41,", '",F41,"', '",G41,"' , '",H41,"' , '",I41,"' , '",J41,"', '",K41,"'") -> EXECUTE [dbo].[PG_CI_CUSTOMER] 0, 0, 0, 41, 'LISA FIRTH', '5172236734' , '' , '' , '5172231331', ''
B42: 0 | C42: 0 | D42: 0 | E42: 20 | F42: VITO PALADINO | M42: =CONCATENATE(CONTACT!$P$1,E42,", '",F42,"', '",G42,"' , '",H42,"' , '",I42,"' , '",J42,"', '",K42,"'") -> EXECUTE [dbo].[PG_CI_CUSTOMER] 0, 0, 0, 20, 'VITO PALADINO', '' , '' , '' , '', ''
B43: 0 | C43: 0 | D43: 0 | E43: 21 | F43: MIHO NAKATANI | M43: =CONCATENATE(CONTACT!$P$1,E43,", '",F43,"', '",G43,"' , '",H43,"' , '",I43,"' , '",J43,"', '",K43,"'") -> EXECUTE [dbo].[PG_CI_CUSTOMER] 0, 0, 0, 21, 'MIHO NAKATANI', '' , '' , '' , '', ''
B44: 0 | C44: 0 | D44: 0 | E44: 22 | G44: 0755914911 | J44: 0755914983 | M44: =CONCATENATE(CONTACT!$P$1,E44,", '",F44,"', '",G44,"' , '",H44,"' , '",I44,"' , '",J44,"', '",K44,"'") -> EXECUTE [dbo].[PG_CI_CUSTOMER] 0, 0, 0, 22, '', '0755914911' , '' , '' , '0755914983', ''
B45: 0 | C45: 0 | D45: 0 | E45: 23 | G45: 0755914911 | J45: 0755914983 | M45: =CONCATENATE(CONTACT!$P$1,E45,", '",F45,"', '",G45,"' , '",H45,"' , '",I45,"' , '",J45,"', '",K45,"'") -> EXECUTE [dbo].[PG_CI_CUSTOMER] 0, 0, 0, 23, '', '0755914911' , '' , '' , '0755914983', ''
B46: 0 | C46: 0 | D46: 0 | E46: 24 | F46: PATTY O'DELL | G46: 3139636114 | M46: =CONCATENATE(CONTACT!$P$1,E46,", '",F46,"', '",G46,"' , '",H46,"' , '",I46,"' , '",J46,"', '",K46,"'") -> EXECUTE [dbo].[PG_CI_CUSTOMER] 0, 0, 0, 24, 'PATTY O'DELL', '3139636114' , '' , '' , '', ''
B47: 0 | C47: 0 | D47: 0 | E47: 25 | F47: Mr. Kurt Greaser | G47: 001113174845555 | J47: 001513174845565 | M47: =CONCATENATE(CONTACT!$P$1,E47,", '",F47,"', '",G47,"' , '",H47,"' , '",I47,"' , '",J47,"', '",K47,"'") -> EXECUTE [dbo].[PG_CI_CUSTOMER] 0, 0, 0, 25, 'Mr. Kurt Greaser', '001113174845555' , '' , '' , '001513174845565', ''
B48: 0 | C48: 0 | D48: 0 | E48: 26 | M48: =CONCATENATE(CONTACT!$P$1,E48,", '",F48,"', '",G48,"' , '",H48,"' , '",I48,"' , '",J48,"', '",K48,"'") -> EXECUTE [dbo].[PG_CI_CUSTOMER] 0, 0, 0, 26, '', '' , '' , '' , '', ''
B49: 0 | C49: 0 | D49: 0 | E49: 43 | F49: SELENA LAU | G49: 5166274000 | M49: =CONCATENATE(CONTACT!$P$1,E49,", '",F49,"', '",G49,"' , '",H49,"' , '",I49,"' , '",J49,"', '",K49,"'") -> EXECUTE [dbo].[PG_CI_CUSTOMER] 0, 0, 0, 43, 'SELENA LAU', '5166274000' , '' , '' , '', ''
B50: 0 | C50: 0 | D50: 0 | E50: 45 | F50: JOHN RUGGIERO | G50: 5187624543 | I50: jruggiero@pearlleather.com | M50: =CONCATENATE(CONTACT!$P$1,E50,", '",F50,"', '",G50,"' , '",H50,"' , '",I50,"' , '",J50,"', '",K50,"'") -> EXECUTE [dbo].[PG_CI_CUSTOMER] 0, 0, 0, 45, 'JOHN RUGGIERO', '5187624543' , '' , 'jruggiero@pearlleather.com' , '', ''
B51: 0 | C51: 0 | D51: 0 | E51: 44 | F51: BILL REID | G51: 2485057417 | I51: william.a.reid@att.net | M51: =CONCATENATE(CONTACT!$P$1,E51,", '",F51,"', '",G51,"' , '",H51,"' , '",I51,"' , '",J51,"', '",K51,"'") -> EXECUTE [dbo].[PG_CI_CUSTOMER] 0, 0, 0, 44, 'BILL REID', '2485057417' , '' , 'william.a.reid@att.net' , '', ''
B52: 0 | C52: 0 | D52: 0 | E52: 27 | F52: CECILIA RODRIGUEZ | M52: =CONCATENATE(CONTACT!$P$1,E52,", '",F52,"', '",G52,"' , '",H52,"' , '",I52,"' , '",J52,"', '",K52,"'") -> EXECUTE [dbo].[PG_CI_CUSTOMER] 0, 0, 0, 27, 'CECILIA RODRIGUEZ', '' , '' , '' , '', ''
B53: 0 | C53: 0 | D53: 0 | E53: 35 | F53: NORMA GUTIERREZ | G53: 00111528787830150 | M53: =CONCATENATE(CONTACT!$P$1,E53,", '",F53,"', '",G53,"' , '",H53,"' , '",I53,"' , '",J53,"', '",K53,"'") -> EXECUTE [dbo].[PG_CI_CUSTOMER] 0, 0, 0, 35, 'NORMA GUTIERREZ', '00111528787830150' , '' , '' , '', ''
B54: 0 | C54: 0 | D54: 0 | E54: 28 | F54: MARY KEHOE | G54: 2485869118 | J54: 2486425154 | M54: =CONCATENATE(CONTACT!$P$1,E54,", '",F54,"', '",G54,"' , '",H54,"' , '",I54,"' , '",J54,"', '",K54,"'") -> EXECUTE [dbo].[PG_CI_CUSTOMER] 0, 0, 0, 28, 'MARY KEHOE', '2485869118' , '' , '' , '2486425154', ''
B55: 0 | C55: 0 | D55: 0 | E55: 50 | F55: RICARDO VALTIERRA | G55: 6564011973 | M55: =CONCATENATE(CONTACT!$P$1,E55,", '",F55,"', '",G55,"' , '",H55,"' , '",I55,"' , '",J55,"', '",K55,"'") -> EXECUTE [dbo].[PG_CI_CUSTOMER] 0, 0, 0, 50, 'RICARDO VALTIERRA', '6564011973' , '' , '' , '', ''
B56: 0 | C56: 0 | D56: 0 | E56: 31 | M56: =CONCATENATE(CONTACT!$P$1,E56,", '",F56,"', '",G56,"' , '",H56,"' , '",I56,"' , '",J56,"', '",K56,"'") -> EXECUTE [dbo].[PG_CI_CUSTOMER] 0, 0, 0, 31, '', '' , '' , '' , '', ''
B57: 0 | C57: 0 | D57: 0 | E57: 36 | F57: BRIAN TANNER | G57: 5196763626 | J57: 3139829198 | M57: =CONCATENATE(CONTACT!$P$1,E57,", '",F57,"', '",G57,"' , '",H57,"' , '",I57,"' , '",J57,"', '",K57,"'") -> EXECUTE [dbo].[PG_CI_CUSTOMER] 0, 0, 0, 36, 'BRIAN TANNER', '5196763626' , '' , '' , '3139829198', ''
B58: 0 | C58: 0 | D58: 0 | E58: 55 | M58: =CONCATENATE(CONTACT!$P$1,E58,", '",F58,"', '",G58,"' , '",H58,"' , '",I58,"' , '",J58,"', '",K58,"'") -> EXECUTE [dbo].[PG_CI_CUSTOMER] 0, 0, 0, 55, '', '' , '' , '' , '', ''
B59: 0 | C59: 0 | D59: 0 | E59: 53 | M59: =CONCATENATE(CONTACT!$P$1,E59,", '",F59,"', '",G59,"' , '",H59,"' , '",I59,"' , '",J59,"', '",K59,"'") -> EXECUTE [dbo].[PG_CI_CUSTOMER] 0, 0, 0, 53, '', '' , '' , '' , '', ''
B60: 0 | C60: 0 | D60: 0 | E60: 58 | F60: MR. ZHANG WENKANG | G60: 8613061818985 | M60: =CONCATENATE(CONTACT!$P$1,E60,", '",F60,"', '",G60,"' , '",H60,"' , '",I60,"' , '",J60,"', '",K60,"'") -> EXECUTE [dbo].[PG_CI_CUSTOMER] 0, 0, 0, 58, 'MR. ZHANG WENKANG', '8613061818985' , '' , '' , '', ''
B61: 0 | C61: 0 | D61: 0 | E61: 60 | F61: YUENYONG NATTIDA | G61: 886211963 | M61: =CONCATENATE(CONTACT!$P$1,E61,", '",F61,"', '",G61,"' , '",H61,"' , '",I61,"' , '",J61,"', '",K61,"'") -> EXECUTE [dbo].[PG_CI_CUSTOMER] 0, 0, 0, 60, 'YUENYONG NATTIDA', '886211963' , '' , '' , '', ''

Sheet Hoja1
A1: A4GLIdentity | B1: cus_no | D1: cus_name | E1: addr_1 | F1: addr_2 | G1: city | I1: state | J1: zip | K1: country | L1: contact | M1: contact_2 | N1: phone_no | O1: phone_no_2 | P1: phone_ext | Q1: phone_ext_2 | R1: fax_no | S1: start_dt | T1: slspsn_no | U1: cus_type_cd | V1: bal_meth | W1: stm_freq | X1: cr_lmt | Y1: cr_rating | Z1: hold_fg | AA1: collector | AB1: fin_chg_fg | AC1: cus_origin | AD1: filler_0003 | AE1: terr | AF1: curr_cd | AG1: par_cus_no | AH1: par_cus_fg | AI1: ship_via_cd | AJ1: ups_zone | AK1: ar_terms_cd | AL1: dsc_pct | AM1: ytd_dsc_given | AN1: txbl_fg | AO1: tax_cd | AP1: tax_cd_2 | AQ1: tax_cd_3 | AR1: exempt_no | AS1: sls_ptd | AT1: sls_ytd | AU1: sls_last_yr | AV1: cost_ptd | AW1: cost_ytd | AX1: cost_last_yr | AY1: balance | AZ1: high_balance | BA1: last_sale_dt | BB1: last_sale_amt | BC1: inv_ytd | BD1: inv_last_yr | BE1: paid_inv_ytd | BF1: last_pay_dt | BG1: last_pay_amt | BH1: avg_pay_ytd | BI1: avg_pay_last_yr | BJ1: last_stm_age_dt | BK1: amt_age_prd_1 | BL1: amt_age_prd_2 | BM1: amt_age_prd_3 | BN1: amt_age_prd_4 | BO1: allow_sb_item | BP1: allow_bo | BQ1: allow_part_ship | BR1: print_dunn_fg | BS1: cmt_1 | BT1: cmt_2 | BU1: vend_no | BV1: tax_sched | BW1: cr_card_1_desc | BX1: cr_card_1_acct | BY1: cr_card_1_exp_dt | BZ1: cr_card_2_desc | CA1: cr_card_2_acct | CB1: cr_card_2_exp_dt | CC1: user_def_fld_1 | CD1: user_def_fld_2 | CE1: user_def_fld_3 | CF1: user_def_fld_4 | CG1: user_def_fld_5 | CH1: dflt_inv_form | CI1: loc | CJ1: note_1 | CK1: note_2 | CL1: note_3 | CM1: note_4 | CN1: note_5 | CO1: user_dt | CP1: user_amount | CQ1: amt_age_oe_term | CR1: cus_alt_adr_cd | CS1: rfc_no | CT1: email_addr | CU1: filler_0002 | CV1: A4GLIdentity
A2: 59 | B2: ADIE01 | C2: ADIE01 | D2: 49200 | E2: 49200 HALYARD DRIVE.PLYMOUTH, | G2: PLYMOUTH | H2: PLYMOUTH | I2: MI | J2: 49200 | K2: EU | L2: MAURICIO ESPINOSA | N2: 18773348706 | S2: 20201216 | T2: 2 | U2: MCUEX | V2: O | W2: M | X2: 3000000 | Y2: =LEFT(S2,4) -> 2020 | Z2: =RIGHT(S2,4) -> 1216 | AA2: =LEFT(Z2,2) -> 12 | AB2: =RIGHT(Z2,2) -> 16 | AC2: =CONCATENATE(Y2,"-",AA2,"-",AB2) -> 2020-12-16 | AD2: NULL | AE2: US | AF2: USD | AG2: NULL | AH2: N | AI2: EXP | AJ2: NULL | AK2: 60 | AL2: 0 | AM2: 0 | AN2: N | AO2: 0 | AP2: NULL | AQ2: NULL | AR2: NULL | AS2: 0 | AT2: 0 | AU2: 0 | AV2: 0 | AW2: 0 | AX2: 0 | AY2: 0 | AZ2: 0 | BA2: 0 | BB2: 0 | BC2: 0 | BD2: 0 | BE2: 0 | BF2: 0 | BG2: 0 | BH2: NULL | BI2: NULL | BJ2: 0 | BK2: 0 | BL2: 0 | BM2: 0 | BN2: 0 | BO2: N | BP2: Y | BQ2: Y | BR2: N | BS2: NULL | BT2: NULL | BU2: NULL | BV2: NULL | BW2: NULL | BX2: NULL | BY2: 0 | BZ2: NULL | CA2: NULL | CB2: 0 | CC2: NULL | CD2: NULL | CE2: NULL | CF2: NULL | CG2: NULL | CH2: 26 | CI2: MFP | CJ2: NULL | CK2: NULL | CL2: NULL | CM2: NULL | CN2: NULL | CO2: 0 | CP2: 0 | CQ2: 0 | CR2: NULL | CS2: NULL | CU2: NULL | CV2: 59
A3: 46 | B3: ALGRP1 | C3: ALGRP1 | D3: 11021 | E3: 17 BARSTOWN ROAD | F3: NULL | G3: GREAT NECK STATES | H3: GREAT NECK STATES | I3: NY | J3: 11021 | K3: USA | L3: NULL | M3: NULL | O3: NULL | P3: NULL | Q3: NULL | R3: NULL | S3: 20150831 | T3: 2 | U3: MCUEX | V3: O | W3: M | X3: 3000000 | Y3: =LEFT(S3,4) -> 2015 | Z3: =RIGHT(S3,4) -> 0831 | AA3: =LEFT(Z3,2) -> 08 | AB3: =RIGHT(Z3,2) -> 31 | AC3: =CONCATENATE(Y3,"-",AA3,"-",AB3) -> 2015-08-31 | AD3: NULL | AE3: US | AF3: USD | AG3: NULL | AH3: N | AI3: LOC | AJ3: NULL | AK3: 5 | AL3: 0 | AM3: 0 | AN3: N | AO3: 0 | AP3: NULL | AQ3: NULL | AR3: NULL | AS3: 0 | AT3: 0 | AU3: 0 | AV3: 0 | AW3: 0 | AX3: 0 | AY3: 0 | AZ3: 0 | BA3: 20160531 | BB3: 0 | BC3: 0 | BD3: 0 | BE3: 0 | BF3: 0 | BG3: 0 | BH3: NULL | BI3: NULL | BJ3: 0 | BK3: 0 | BL3: 0 | BM3: 0 | BN3: 0 | BO3: N | BP3: Y | BQ3: Y | BR3: N | BS3: NULL | BT3: NULL | BU3: NULL | BV3: NULL | BW3: NULL | BX3: NULL | BY3: 0 | BZ3: NULL | CA3: NULL | CB3: 0 | CC3: NULL | CD3: 69000000 | CE3: NULL | CF3: NULL | CG3: NULL | CH3: 26 | CI3: MFP | CJ3: NULL | CK3: NULL | CL3: NULL | CM3: NULL | CN3: NULL | CO3: 0 | CP3: 0 | CQ3: 0 | CR3: NULL | CS3: NULL | CT3: bkamali@kamaligroup.com | CU3: NULL | CV3: 46
A4: 49 | B4: BILT01 | C4: BILT01 | D4: 11021 | E4: 17 BARSTOW RD. | F4: SUITE 206 | G4: GREAT NECK | H4: GREAT NECK | I4: NY | J4: 11021 | K4: USA | L4: RUTH KAMALI | M4: NULL | N4: 516-627-4000 | O4: NULL | P4: NULL | Q4: NULL | R4: NULL | S4: 20161208 | T4: 2 | U4: MISC | V4: O | W4: M | X4: NULL | Y4: =LEFT(S4,4) -> 2016 | Z4: =RIGHT(S4,4) -> 1208 | AA4: =LEFT(Z4,2) -> 12 | AB4: =RIGHT(Z4,2) -> 08 | AC4: =CONCATENATE(Y4,"-",AA4,"-",AB4) -> 2016-12-08 | AD4: NULL | AE4: NULL | AF4: AUD | AG4: NULL | AH4: N | AI4: LOC | AJ4: NULL | AK4: COD | AL4: 0 | AM4: 0 | AN4: N | AO4: 0 | AP4: NULL | AQ4: NULL | AR4: NULL | AS4: 0 | AT4: 0 | AU4: 0 | AV4: 0 | AW4: 0 | AX4: 0 | AY4: 3440 | AZ4: 3440 | BA4: 20170406 | BB4: 1940 | BC4: 0 | BD4: 0 | BE4: 0 | BF4: 0 | BG4: 0 | BH4: NULL | BI4: NULL | BJ4: 0 | BK4: 0 | BL4: 0 | BM4: 0 | BN4: 0 | BO4: N | BP4: Y | BQ4: Y | BR4: N | BS4: NULL | BT4: NULL | BU4: NULL | BV4: NULL | BW4: NULL | BX4: NULL | BY4: 0 | BZ4: NULL | CA4: NULL | CB4: 0 | CC4: NULL | CD4: 69000000 | CE4: NULL | CF4: NULL | CG4: NULL | CH4: 26 | CI4: NULL | CJ4: NULL | CK4: NULL | CL4: NULL | CM4: NULL | CN4: NULL | CO4: 0 | CP4: 0 | CQ4: 0 | CR4: NULL | CS4: NULL | CT4: NULL | CU4: NULL | CV4: 49
A5: 29 | B5: BMCS01 | C5: BMCS01 | D5: N9Y 2C7 | E5: 163 HERITAGE ROAD | F5: KINGSVILLE | G5: ONTARIO | H5: ONTARIO | I5: NULL | J5: N9Y 2C7 | K5: CANADA | L5: NULL | M5: NULL | N5: 519 733 3713 | O5: NULL | P5: NULL | Q5: NULL | R5: 5197335887 | S5: 20011008 | T5: 2 | U5: MCUEX | V5: O | W5: M | X5: 500000 | Y5: =LEFT(S5,4) -> 2001 | Z5: =RIGHT(S5,4) -> 1008 | AA5: =LEFT(Z5,2) -> 10 | AB5: =RIGHT(Z5,2) -> 08 | AC5: =CONCATENATE(Y5,"-",AA5,"-",AB5) -> 2001-10-08 | AD5: NULL | AE5: MX | AF5: USD | AG5: NULL | AH5: N | AI5: LOC | AJ5: NULL | AK5: 30 | AL5: 0 | AM5: 0 | AN5: N | AO5: 0 | AP5: NULL | AQ5: NULL | AR5: NULL | AS5: 0 | AT5: 0 | AU5: 0 | AV5: 0 | AW5: 0 | AX5: 0 | AY5: 0 | AZ5: 24196.8 | BA5: 20040916 | BB5: 319 | BC5: 0 | BD5: 0 | BE5: 0 | BF5: 20040210 | BG5: 960 | BH5: NULL | BI5: NULL | BJ5: 20110131 | BK5: 0 | BL5: 0 | BM5: 0 | BN5: 0 | BO5: N | BP5: Y | BQ5: Y | BR5: N | BS5: NULL | BT5: n/a | BU5: NULL | BV5: NULL | BW5: NULL | BX5: NULL | BY5: 0 | BZ5: NULL | CA5: NULL | CB5: 0 | CC5: NULL | CD5: 69000000 | CE5: NULL | CF5: NULL | CG5: NULL | CH5: 26 | CI5: MFP | CJ5: NULL | CK5: NULL | CL5: NULL | CM5: NULL | CN5: NULL | CO5: 0 | CP5: 0 | CQ5: 0 | CR5: 2 | CS5: NULL | CT5: NULL | CU5: NULL | CV5: 29
A6: 33 | B6: CASH01 | C6: CASH01 | E6: NULL | F6: NULL | G6: NULL | H6: NULL | I6: NULL | K6: NULL | L6: NULL | M6: NULL | O6: NULL | P6: NULL | Q6: NULL | R6: NULL | S6: 20020128 | T6: 2 | U6: MISC | V6: O | W6: M | X6: 5000 | Y6: =LEFT(S6,4) -> 2002 | Z6: =RIGHT(S6,4) -> 0128 | AA6: =LEFT(Z6,2) -> 01 | AB6: =RIGHT(Z6,2) -> 28 | AC6: =CONCATENATE(Y6,"-",AA6,"-",AB6) -> 2002-01-28 | AD6: NULL | AE6: NULL | AF6: USD | AG6: NULL | AH6: N | AI6: LOC | AJ6: NULL | AK6: COD | AL6: 0 | AM6: 0 | AN6: N | AO6: NULL | AP6: NULL | AQ6: NULL | AR6: NULL | AS6: 0 | AT6: 0 | AU6: 0 | AV6: 0 | AW6: 0 | AX6: 0 | AY6: 540171.25 | AZ6: 540171.25 | BA6: 20180830 | BB6: 23015 | BC6: 0 | BD6: 0 | BE6: 0 | BF6: 20110111 | BG6: 14169 | BH6: NULL | BI6: NULL | BJ6: 20110131 | BK6: 0 | BL6: 0 | BM6: 0 | BN6: 0 | BO6: N | BP6: Y | BQ6: Y | BR6: N | BS6: NULL | BT6: NULL | BU6: NULL | BV6: EXP | BW6: NULL | BX6: NULL | BY6: 0 | BZ6: NULL | CA6: NULL | CB6: 0 | CC6: NULL | CD6: 69000000 | CE6: NULL | CF6: NULL | CG6: NULL | CH6: 26 | CI6: MFP | CJ6: NULL | CK6: NULL | CL6: NULL | CM6: NULL | CN6: NULL | CO6: 0 | CP6: 0 | CQ6: 0 | CR6: NULL | CS6: NULL | CT6: NULL | CU6: NULL | CV6: 33
A7: 42 | B7: CASH02 | C7: CASH02 | D7: CP 32676 | E7: CALLE PASCUAL OROZCO 591 | F7: COL. SANTA MARIA | G7: CD. JUAREZ | H7: CD. JUAREZ | I7: CHIH | J7: CP 32676 | K7: RFC: RED090407DF4 | L7: ROGELIO CORRAL | M7: NULL | N7: 6563827522 | O7: NULL | P7: NULL | Q7: NULL | R7: NULL | S7: 20130115 | T7: 2 | U7: MISC | V7: O | W7: M | X7: NULL | Y7: =LEFT(S7,4) -> 2013 | Z7: =RIGHT(S7,4) -> 0115 | AA7: =LEFT(Z7,2) -> 01 | AB7: =RIGHT(Z7,2) -> 15 | AC7: =CONCATENATE(Y7,"-",AA7,"-",AB7) -> 2013-01-15 | AD7: NULL | AE7: NULL | AF7: USD | AG7: NULL | AH7: N | AI7: LOC | AJ7: NULL | AK7: COD | AL7: 0 | AM7: 0 | AN7: N | AO7: 0 | AP7: NULL | AQ7: NULL | AR7: NULL | AS7: 0 | AT7: 0 | AU7: 0 | AV7: 0 | AW7: 0 | AX7: 0 | AY7: 4779.16 | AZ7: 4779.16 | BA7: 20130530 | BB7: 1741.5 | BC7: 0 | BD7: 0 | BE7: 0 | BF7: 0 | BG7: 0 | BH7: NULL | BI7: NULL | BJ7: 0 | BK7: 0 | BL7: 0 | BM7: 0 | BN7: 0 | BO7: N | BP7: Y | BQ7: Y | BR7: N | BS7: NULL | BT7: NULL | BU7: NULL | BV7: NULL | BW7: NULL | BX7: NULL | BY7: 0 | BZ7: NULL | CA7: NULL | CB7: 0 | CC7: NULL | CD7: 69000000 | CE7: NULL | CF7: NULL | CG7: NULL | CH7: 26 | CI7: NULL | CJ7: NULL | CK7: NULL | CL7: NULL | CM7: NULL | CN7: NULL | CO7: 0 | CP7: 0 | CQ7: 0 | CR7: NULL | CS7: NULL | CT7: NULL | CU7: NULL | CV7: 42
A8: 1 | B8: CNII01 | C8: CNII01 | D8: 48083 | E8: 1148 ROCHESTER ROAD | F8: NULL | G8: TROY | H8: TROY | I8: MI | J8: 48083 | K8: USA | L8: NIKKI OSTERLAND | M8: NULL | N8: 248 5857700 | O8: NULL | P8: NULL | Q8: NULL | R8: 248 5855800 | S8: 19980522 | T8: 2 | U8: MCUEX | V8: O | W8: M | X8: 50000 | Y8: =LEFT(S8,4) -> 1998 | Z8: =RIGHT(S8,4) -> 0522 | AA8: =LEFT(Z8,2) -> 05 | AB8: =RIGHT(Z8,2) -> 22 | AC8: =CONCATENATE(Y8,"-",AA8,"-",AB8) -> 1998-05-22 | AD8: NULL | AE8: MX | AF8: USD | AG8: NULL | AH8: N | AI8: LOC | AJ8: NULL | AK8: 45 | AL8: 0 | AM8: 0 | AN8: N | AO8: NULL | AP8: NULL | AQ8: NULL | AR8: NULL | AS8: 0 | AT8: 0 | AU8: 0 | AV8: 0 | AW8: 0 | AX8: 0 | AY8: 1700 | AZ8: 1414574.8 | BA8: 20161118 | BB8: 1700 | BC8: 0 | BD8: 0 | BE8: 0 | BF8: 20091016 | BG8: 148.8 | BH8: NULL | BI8: NULL | BJ8: 20110131 | BK8: 0 | BL8: 0 | BM8: 0 | BN8: 0 | BO8: N | BP8: Y | BQ8: Y | BR8: N | BS8: FOB ACUNA | BT8: N/A | BU8: NULL | BV8: EXP | BW8: NULL | BX8: NULL | BY8: 0 | BZ8: NULL | CA8: NULL | CB8: 0 | CC8: NULL | CD8: 65000000 | CE8: NULL | CF8: NULL | CG8: 12169199 | CH8: 20 | CI8: MFP | CJ8: NULL | CK8: NULL | CL8: NULL | CM8: NULL | CN8: NULL | CO8: 0 | CP8: 0 | CQ8: 0 | CR8: 1 | CS8: NULL | CT8: NULL | CU8: NULL | CV8: 1
A9: 56 | B9: DAIM05 | C9: DAIM05 | E9: AVE. CENZONTLE ESQ. HALCON | F9: CARRETERA MONCLOVA #7 | G9: RAMOS ARZIPE | H9: RAMOS ARZIPE | I9: COA | K9: MEX | S9: 20200205 | T9: 2 | U9: MCUEX | V9: O | W9: M | X9: 3000000 | Y9: =LEFT(S9,4) -> 2020 | Z9: =RIGHT(S9,4) -> 0205 | AA9: =LEFT(Z9,2) -> 02 | AB9: =RIGHT(Z9,2) -> 05 | AC9: =CONCATENATE(Y9,"-",AA9,"-",AB9) -> 2020-02-05 | AD9: NULL | AE9: US | AF9: USD | AG9: NULL | AH9: N | AI9: LOC | AJ9: NULL | AK9: 5 | AL9: 0 | AM9: 0 | AN9: N | AO9: 0 | AP9: NULL | AQ9: NULL | AR9: NULL | AS9: 0 | AT9: 0 | AU9: 0 | AV9: 0 | AW9: 0 | AX9: 0 | AY9: 0 | AZ9: 0 | BA9: 0 | BB9: 0 | BC9: 0 | BD9: 0 | BE9: 0 | BF9: 0 | BG9: 0 | BH9: NULL | BI9: NULL | BJ9: 0 | BK9: 0 | BL9: 0 | BM9: 0 | BN9: 0 | BO9: N | BP9: Y | BQ9: Y | BR9: N | BS9: NULL | BT9: NULL | BU9: NULL | BV9: NULL | BW9: NULL | BX9: NULL | BY9: 0 | BZ9: NULL | CA9: NULL | CB9: 0 | CC9: NULL | CD9: 69000000 | CE9: NULL | CF9: NULL | CG9: NULL | CH9: 26 | CI9: MFP | CJ9: NULL | CK9: NULL | CL9: NULL | CM9: NULL | CN9: NULL | CO9: 0 | CP9: 0 | CQ9: 0 | CR9: NULL | CS9: NULL | CT9: Office@daimayus.com | CU9: NULL | CV9: 56
A10: 2 | B10: EBIN01 | C10: EBIN01 | D10: 1938 | E10: 44 MITCHELL ROAD | F10: IPSWICH | G10: MASSACHUSETTS | H10: MASSACHUSETTS | I10: NULL | J10: 1938 | K10: USA | L10: NULL | M10: NULL | N10: 978-356-5701 | O10: NULL | P10: NULL | Q10: NULL | R10: 978-356-9832 | S10: 20010212 | T10: 2 | U10: MSUEX | V10: O | W10: M | X10: 1000 | Y10: =LEFT(S10,4) -> 2001 | Z10: =RIGHT(S10,4) -> 0212 | AA10: =LEFT(Z10,2) -> 02 | AB10: =RIGHT(Z10,2) -> 12 | AC10: =CONCATENATE(Y10,"-",AA10,"-",AB10) -> 2001-02-12 | AD10: NULL | AE10: US | AF10: USD | AG10: NULL | AH10: N | AI10: AF | AJ10: NULL | AK10: 7 | AL10: 0 | AM10: 0 | AN10: N | AO10: 0 | AP10: NULL | AQ10: NULL | AR10: NULL | AS10: 0 | AT10: 0 | AU10: 0 | AV10: 0 | AW10: 0 | AX10: 0 | AY10: 0 | AZ10: 16744.98 | BA10: 20010525 | BB10: 225.5 | BC10: 0 | BD10: 0 | BE10: 0 | BF10: 20010607 | BG10: 225.5 | BH10: NULL | BI10: NULL | BJ10: 20110131 | BK10: 0 | BL10: 0 | BM10: 0 | BN10: 0 | BO10: N | BP10: Y | BQ10: Y | BR10: N | BS10: NULL | BT10: n/a | BU10: NULL | BV10: NULL | BW10: NULL | BX10: NULL | BY10: 0 | BZ10: NULL | CA10: NULL | CB10: 0 | CC10: NULL | CD10: 0 | CE10: NULL | CF10: NULL | CG10: NULL | CH10: 20 | CI10: MFP | CJ10: NULL | CK10: NULL | CL10: NULL | CM10: NULL | CN10: NULL | CO10: 0 | CP10: 0 | CQ10: 0 | CR10: EFFO01 | CS10: NULL | CT10: NULL | CU10: NULL | CV10: 2
A11: 57 | B11: EISS01 | C11: EISS01 | D11: 90796 | E11: Reforma Sur No. 27 | F11: Nave 1 | G11: Panzacola | H11: Panzacola | I11: NULL | J11: 90796 | K11: MEXICO | L11: NULL | M11: NULL | O11: NULL | P11: NULL | Q11: NULL | R11: NULL | S11: 20200901 | T11: 2 | U11: MCUEX | V11: O | W11: M | X11: NULL | Y11: =LEFT(S11,4) -> 2020 | Z11: =RIGHT(S11,4) -> 0901 | AA11: =LEFT(Z11,2) -> 09 | AB11: =RIGHT(Z11,2) -> 01 | AC11: =CONCATENATE(Y11,"-",AA11,"-",AB11) -> 2020-09-01 | AD11: NULL | AE11: US | AF11: USD | AG11: NULL | AH11: N | AI11: LOC | AJ11: NULL | AK11: 30 | AL11: 0 | AM11: 0 | AN11: N | AO11: 0 | AP11: NULL | AQ11: NULL | AR11: NULL | AS11: 0 | AT11: 0 | AU11: 0 | AV11: 0 | AW11: 0 | AX11: 0 | AY11: 0 | AZ11: 0 | BA11: 0 | BB11: 0 | BC11: 0 | BD11: 0 | BE11: 0 | BF11: 0 | BG11: 0 | BH11: NULL | BI11: NULL | BJ11: 0 | BK11: 0 | BL11: 0 | BM11: 0 | BN11: 0 | BO11: N | BP11: Y | BQ11: Y | BR11: N | BS11: NULL | BT11: NULL | BU11: NULL | BV11: NULL | BW11: NULL | BX11: NULL | BY11: 0 | BZ11: NULL | CA11: NULL | CB11: 0 | CC11: NULL | CD11: 69000000 | CE11: NULL | CF11: NULL | CG11: NULL | CH11: 26 | CI11: MFP | CJ11: NULL | CK11: NULL | CL11: NULL | CM11: NULL | CN11: NULL | CO11: 0 | CP11: 0 | CQ11: 0 | CR11: NULL | CS11: NULL | CT11: NULL | CU11: NULL | CV11: 57
A12: 3 | B12: ENSA01 | C12: ENSA01 | D12: 32650 | E12: BLVD. OSCAR FLORES 4250 | F12: NULL | G12: CD JUAREZ, CHIH. | H12: CD JUAREZ, CHIH. | I12: NULL | J12: 32650 | K12: MEXICO | L12: LUIS ENRIQUE HERNANDEZ | M12: NULL | O12: NULL | P12: NULL | Q12: NULL | R12: NULL | S12: 20010607 | T12: 2 | U12: MISC | V12: O | W12: M | X12: 50000 | Y12: =LEFT(S12,4) -> 2001 | Z12: =RIGHT(S12,4) -> 0607 | AA12: =LEFT(Z12,2) -> 06 | AB12: =RIGHT(Z12,2) -> 07 | AC12: =CONCATENATE(Y12,"-",AA12,"-",AB12) -> 2001-06-07 | AD12: NULL | AE12: US | AF12: USD | AG12: NULL | AH12: N | AI12: LOC | AJ12: NULL | AK12: 30 | AL12: 0 | AM12: 0 | AN12: N | AO12: 0 | AP12: NULL | AQ12: NULL | AR12: NULL | AS12: 0 | AT12: 0 | AU12: 0 | AV12: 0 | AW12: 0 | AX12: 0 | AY12: 1861.84 | AZ12: 47634.54 | BA12: 20131107 | BB12: 1861.84 | BC12: 0 | BD12: 0 | BE12: 0 | BF12: 20100226 | BG12: 137 | BH12: NULL | BI12: NULL | BJ12: 20110131 | BK12: 0 | BL12: 0 | BM12: 0 | BN12: 0 | BO12: N | BP12: Y | BQ12: Y | BR12: N | BS12: NULL | BT12: N/A | BU12: NULL | BV12: NULL | BW12: NULL | BX12: NULL | BY12: 0 | BZ12: NULL | CA12: NULL | CB12: 0 | CC12: NULL | CD12: 0 | CE12: NULL | CF12: NULL | CG12: NULL | CH12: 26 | CI12: MIS | CJ12: NULL | CK12: NULL | CL12: NULL | CM12: NULL | CN12: NULL | CO12: 0 | CP12: 0 | CQ12: 0 | CR12: ENSA01 | CS12: NULL | CT12: NULL | CU12: NULL | CV12: 3
A13: 51 | B13: FAUR01 | C13: FAUR01 | D13: 48321 | E13: TROY_1402 | G13: AUBURN HILLS | H13: AUBURN HILLS | I13: MI | J13: 48321 | K13: USA | L13: ACCOUNTS PAYABLE | R13: NULL | S13: 20191111 | T13: 2 | U13: MCUEX | V13: O | W13: M | X13: NULL | Y13: =LEFT(S13,4) -> 2019 | Z13: =RIGHT(S13,4) -> 1111 | AA13: =LEFT(Z13,2) -> 11 | AB13: =RIGHT(Z13,2) -> 11 | AC13: =CONCATENATE(Y13,"-",AA13,"-",AB13) -> 2019-11-11 | AD13: NULL | AE13: US | AF13: USD | AG13: NULL | AH13: N | AI13: LOC | AJ13: NULL | AK13: 5 | AL13: 0 | AM13: 0 | AN13: N | AO13: 0 | AP13: NULL | AQ13: NULL | AR13: NULL | AS13: 0 | AT13: 0 | AU13: 0 | AV13: 0 | AW13: 0 | AX13: 0 | AY13: 0 | AZ13: 0 | BA13: 0 | BB13: 0 | BC13: 0 | BD13: 0 | BE13: 0 | BF13: 0 | BG13: 0 | BH13: NULL | BI13: NULL | BJ13: 0 | BK13: 0 | BL13: 0 | BM13: 0 | BN13: 0 | BO13: N | BP13: Y | BQ13: Y | BR13: N | BS13: NULL | BT13: NULL | BU13: NULL | BV13: NULL | BW13: NULL | BX13: NULL | BY13: 0 | BZ13: NULL | CA13: NULL | CB13: 0 | CC13: NULL | CD13: 69000000 | CE13: NULL | CF13: NULL | CG13: NULL | CH13: 26 | CI13: MFP | CJ13: NULL | CK13: NULL | CL13: NULL | CM13: NULL | CN13: NULL | CO13: 0 | CP13: 0 | CQ13: 0 | CR13: NULL | CS13: NULL | CU13: NULL | CV13: 51
A14: 4 | B14: FIND01 | C14: FIND01 | D14: 45840 | E14: 4000 FOSTORIA ROAD | F14: FINDLAY 0410 45840 | G14: OHIO | H14: OHIO | I14: NULL | J14: 45840 | K14: USA | L14: NULL | M14: NULL | N14: 419 4245429 | O14: NULL | P14: NULL | Q14: NULL | R14: 419 4223164 | S14: 19980522 | T14: 2 | U14: MCUEX | V14: O | W14: M | X14: NULL | Y14: =LEFT(S14,4) -> 1998 | Z14: =RIGHT(S14,4) -> 0522 | AA14: =LEFT(Z14,2) -> 05 | AB14: =RIGHT(Z14,2) -> 22 | AC14: =CONCATENATE(Y14,"-",AA14,"-",AB14) -> 1998-05-22 | AD14: NULL | AE14: US | AF14: USD | AG14: NULL | AH14: N | AI14: AF | AJ14: NULL | AK14: 30 | AL14: 0 | AM14: 0 | AN14: N | AO14: NULL | AP14: NULL | AQ14: NULL | AR14: NULL | AS14: 0 | AT14: 0 | AU14: 0 | AV14: 0 | AW14: 0 | AX14: 0 | AY14: 0 | AZ14: 3954.39 | BA14: 20091125 | BB14: -288.09 | BC14: 0 | BD14: 0 | BE14: 0 | BF14: 20091110 | BG14: 355.21 | BH14: NULL | BI14: NULL | BJ14: 20110131 | BK14: 0 | BL14: 0 | BM14: 0 | BN14: 0 | BO14: N | BP14: Y | BQ14: Y | BR14: N | BS14: NETT CIF | BT14: N/A | BU14: NULL | BV14: EXP | BW14: NULL | BX14: NULL | BY14: 0 | BZ14: NULL | CA14: NULL | CB14: 0 | CC14: NULL | CD14: 0 | CE14: NULL | CF14: NULL | CG14: 3-30322 | CH14: 20 | CI14: MFP | CJ14: balance of $674.39 written off | CK14: 13/10/00 | CL14: NULL | CM14: NULL | CN14: NULL | CO14: 0 | CP14: 0 | CQ14: 0 | CR14: NULL | CS14: NULL | CT14: NULL | CU14: NULL | CV14: 4
A15: 5 | B15: FIND02 | C15: FIND02 | D15: 33853 | E15: PO BOX 1350 | F15: LAKE WALES | G15: FLORIDA | H15: FLORIDA | I15: FL | J15: 33853 | K15: USA | L15: WILLIS I SIMMONS | M15: NULL | N15: 941 676 6081 | O15: NULL | P15: NULL | Q15: NULL | R15: 941 676 6463 | S15: 19990902 | T15: 2 | U15: MCUEX | V15: O | W15: M | X15: NULL | Y15: =LEFT(S15,4) -> 1999 | Z15: =RIGHT(S15,4) -> 0902 | AA15: =LEFT(Z15,2) -> 09 | AB15: =RIGHT(Z15,2) -> 02 | AC15: =CONCATENATE(Y15,"-",AA15,"-",AB15) -> 1999-09-02 | AD15: NULL | AE15: US | AF15: USD | AG15: NULL | AH15: N | AI15: AF | AJ15: NULL | AK15: 30 | AL15: 0 | AM15: 0 | AN15: N | AO15: NO | AP15: NULL | AQ15: NULL | AR15: NULL | AS15: 0 | AT15: 0 | AU15: 0 | AV15: 0 | AW15: 0 | AX15: 0 | AY15: 0 | AZ15: 123034.87 | BA15: 20080527 | BB15: 243.8 | BC15: 0 | BD15: 0 | BE15: 0 | BF15: 20091110 | BG15: 243.8 | BH15: NULL | BI15: NULL | BJ15: 20110131 | BK15: 0 | BL15: 0 | BM15: 0 | BN15: 0 | BO15: N | BP15: Y | BQ15: Y | BR15: N | BS15: NETT CIF | BT15: N/A | BU15: NULL | BV15: NULL | BW15: NULL | BX15: NULL | BY15: 0 | BZ15: NULL | CA15: NULL | CB15: 0 | CC15: NULL | CD15: 50000000 | CE15: NULL | CF15: NULL | CG15: 3-30322 | CH15: 18 | CI15: MFP | CJ15: $674.39 written off on account | CK15: FIND01 13/10/00 | CL15: NULL | CM15: NULL | CN15: NULL | CO15: 0 | CP15: 0 | CQ15: 0 | CR15: NULL | CS15: NULL | CT15: NULL | CU15: NULL | CV15: 5
A16: 6 | B16: GLOB01 | C16: GLOB01 | D16: N9C2Z2 | E16: UNIT C/735 PRINCE ROAD | F16: WINDSOR | G16: NULL | H16: NULL | I16: NULL | J16: N9C2Z2 | K16: CANADA | L16: ROSA BOURDEAU | M16: NULL | O16: NULL | P16: NULL | Q16: NULL | R16: NULL | S16: 20000323 | T16: 2 | U16: MCUEX | V16: O | W16: M | X16: 200000 | Y16: =LEFT(S16,4) -> 2000 | Z16: =RIGHT(S16,4) -> 0323 | AA16: =LEFT(Z16,2) -> 03 | AB16: =RIGHT(Z16,2) -> 23 | AC16: =CONCATENATE(Y16,"-",AA16,"-",AB16) -> 2000-03-23 | AD16: NULL | AE16: MX | AF16: USD | AG16: NULL | AH16: N | AI16: AF | AJ16: NULL | AK16: 30 | AL16: 0 | AM16: 0 | AN16: N | AO16: NO | AP16: NULL | AQ16: NULL | AR16: NULL | AS16: 0 | AT16: 0 | AU16: 0 | AV16: 0 | AW16: 0 | AX16: 0 | AY16: 0 | AZ16: 221793.42 | BA16: 20040907 | BB16: 3631.2 | BC16: 0 | BD16: 0 | BE16: 0 | BF16: 20041112 | BG16: 3631.2 | BH16: NULL | BI16: NULL | BJ16: 20110131 | BK16: 0 | BL16: 0 | BM16: 0 | BN16: 0 | BO16: N | BP16: Y | BQ16: Y | BR16: N | BS16: NULL | BT16: N/A | BU16: NULL | BV16: NULL | BW16: NULL | BX16: NULL | BY16: 0 | BZ16: NULL | CA16: NULL | CB16: 0 | CC16: NULL | CD16: 69000000 | CE16: NULL | CF16: NULL | CG16: 11514281 | CH16: 20 | CI16: MFP | CJ16: NULL | CK16: NULL | CL16: NULL | CM16: NULL | CN16: NULL | CO16: 0 | CP16: 0 | CQ16: 0 | CR16: NULL | CS16: NULL | CT16: NULL | CU16: NULL | CV16: 6
A17: 40 | B17: GRAM01 | C17: GRAM01 | D17: 90434 | E17: BOULEVARD TETLA NO 107 | F17: Cd. Industrial Xicohtencatl | G17: Tetla, Tiaxcala | H17: Tetla, Tiaxcala | I17: NULL | J17: 90434 | K17: MEXICO | L17: CLEMENCIA VIVEROS | M17: NULL | N17: 52 241 418 46 00 | O17: NULL | P17: 3654 | Q17: NULL | R17: 52 241 412 7291 | S17: 20080206 | T17: 2 | U17: MCUEX | V17: O | W17: M | X17: NULL | Y17: =LEFT(S17,4) -> 2008 | Z17: =RIGHT(S17,4) -> 0206 | AA17: =LEFT(Z17,2) -> 02 | AB17: =RIGHT(Z17,2) -> 06 | AC17: =CONCATENATE(Y17,"-",AA17,"-",AB17) -> 2008-02-06 | AD17: NULL | AE17: NULL | AF17: USD | AG17: NULL | AH17: N | AI17: LOC | AJ17: NULL | AK17: 60 | AL17: 0 | AM17: 0 | AN17: N | AO17: NULL | AP17: NULL | AQ17: NULL | AR17: NULL | AS17: 0 | AT17: 0 | AU17: 0 | AV17: 0 | AW17: 0 | AX17: 0 | AY17: 165335.07 | AZ17: 165335.07 | BA17: 20141208 | BB17: 551.7 | BC17: 0 | BD17: 0 | BE17: 0 | BF17: 20111101 | BG17: 17871.3 | BH17: NULL | BI17: NULL | BJ17: 20110131 | BK17: 981 | BL17: 0 | BM17: 990.54 | BN17: -11.45 | BO17: N | BP17: Y | BQ17: Y | BR17: N | BS17: FOB Juarez | BT17: na | BU17: NULL | BV17: EXP | BW17: NULL | BX17: NULL | BY17: 0 | BZ17: NULL | CA17: NULL | CB17: 0 | CC17: NULL | CD17: 65000000 | CE17: NULL | CF17: NULL | CG17: NULL | CH17: 26 | CI17: MFP | CJ17: NULL | CK17: NULL | CL17: NULL | CM17: NULL | CN17: NULL | CO17: 0 | CP17: 0 | CQ17: 1960.09 | CR17: NULL | CS17: NULL | CT17: NULL | CU17: NULL | CV17: 40
A18: 54 | B18: GRAM04 | C18: GRAM04 | D18: 48083 | E18: 1975 TECHNOLOGY DR | G18: TROY | H18: TROY | I18: MI | J18: 48083 | S18: 20191119 | T18: 2 | U18: MCUEX | V18: O | W18: M | X18: 3000000 | Y18: =LEFT(S18,4) -> 2019 | Z18: =RIGHT(S18,4) -> 1119 | AA18: =LEFT(Z18,2) -> 11 | AB18: =RIGHT(Z18,2) -> 19 | AC18: =CONCATENATE(Y18,"-",AA18,"-",AB18) -> 2019-11-19 | AD18: NULL | AE18: US | AF18: USD | AG18: NULL | AH18: N | AI18: LOC | AJ18: NULL | AK18: 5 | AL18: 0 | AM18: 0 | AN18: N | AO18: 0 | AP18: NULL | AQ18: NULL | AR18: NULL | AS18: 0 | AT18: 0 | AU18: 0 | AV18: 0 | AW18: 0 | AX18: 0 | AY18: 0 | AZ18: 0 | BA18: 0 | BB18: 0 | BC18: 0 | BD18: 0 | BE18: 0 | BF18: 0 | BG18: 0 | BH18: NULL | BI18: NULL | BJ18: 0 | BK18: 0 | BL18: 0 | BM18: 0 | BN18: 0 | BO18: N | BP18: Y | BQ18: Y | BR18: N | BS18: NULL | BT18: NULL | BU18: NULL | BV18: NULL | BW18: NULL | BX18: NULL | BY18: 0 | BZ18: NULL | CA18: NULL | CB18: 0 | CC18: NULL | CD18: 69000000 | CE18: NULL | CF18: NULL | CG18: NULL | CH18: 26 | CI18: MFP | CJ18: NULL | CK18: NULL | CL18: NULL | CM18: NULL | CN18: NULL | CO18: 0 | CP18: 0 | CQ18: 0 | CR18: NULL | CS18: NULL | CT18: NULL | CU18: NULL | CV18: 54
A19: 7 | B19: IRVI02 | C19: IRVI02 | D19: 48341 | E19: 2600 CENTER POINT PARKWAY | F19: NULL | G19: PONTIAC | H19: PONTIAC | I19: MI | J19: 48341 | K19: USA | L19: MARIA CLABORN | M19: JANET HAULER | N19: 1 248 451 4216 | O19: 1 248 253 7521 | P19: NULL | Q19: NULL | R19: NULL | S19: 20010725 | T19: 2 | U19: MFUEX | V19: O | W19: M | X19: 500000 | Y19: =LEFT(S19,4) -> 2001 | Z19: =RIGHT(S19,4) -> 0725 | AA19: =LEFT(Z19,2) -> 07 | AB19: =RIGHT(Z19,2) -> 25 | AC19: =CONCATENATE(Y19,"-",AA19,"-",AB19) -> 2001-07-25 | AD19: NULL | AE19: NULL | AF19: USD | AG19: NULL | AH19: N | AI19: AF | AJ19: NULL | AK19: 45 | AL19: 0 | AM19: 0 | AN19: N | AO19: 0 | AP19: NULL | AQ19: NULL | AR19: NULL | AS19: 0 | AT19: 0 | AU19: 0 | AV19: 0 | AW19: 0 | AX19: 0 | AY19: 646931.83 | AZ19: 3575144 | BA19: 20190221 | BB19: 1553.7 | BC19: 0 | BD19: 0 | BE19: 0 | BF19: 20100825 | BG19: 116.1 | BH19: NULL | BI19: NULL | BJ19: 20110131 | BK19: 0 | BL19: 0 | BM19: 0 | BN19: 11.32 | BO19: N | BP19: Y | BQ19: Y | BR19: N | BS19: NULL | BT19: n/a | BU19: NULL | BV19: NULL | BW19: NULL | BX19: NULL | BY19: 0 | BZ19: NULL | CA19: NULL | CB19: 0 | CC19: NULL | CD19: 70000000 | CE19: NULL | CF19: NULL | CG19: 1127566 | CH19: 26 | CI19: MFP | CJ19: NULL | CK19: NULL | CL19: NULL | CM19: NULL | CN19: NULL | CO19: 0 | CP19: 0 | CQ19: 11.32 | CR19: IRVI02 | CS19: NULL | CT19: NULL | CU19: NULL | CV19: 7
A20: 34 | B20: IRVI03 | C20: IRVI03 | D20: 78840 | E20: 2A FAWCETT DRIVE | F20: NULL | G20: DEL RIO | H20: DEL RIO | I20: TX | J20: 78840 | K20: USA | L20: LISA BETH RUMPL | M20: NULL | N20: 248 451 4276 | O20: NULL | P20: NULL | Q20: NULL | R20: 248 451 4230 | S20: 20031106 | T20: 2 | U20: MFUEX | V20: O | W20: M | X20: 500000 | Y20: =LEFT(S20,4) -> 2003 | Z20: =RIGHT(S20,4) -> 1106 | AA20: =LEFT(Z20,2) -> 11 | AB20: =RIGHT(Z20,2) -> 06 | AC20: =CONCATENATE(Y20,"-",AA20,"-",AB20) -> 2003-11-06 | AD20: NULL | AE20: NULL | AF20: USD | AG20: NULL | AH20: N | AI20: AF | AJ20: NULL | AK20: 30 | AL20: 0 | AM20: 0 | AN20: N | AO20: NULL | AP20: NULL | AQ20: NULL | AR20: NULL | AS20: 0 | AT20: 0 | AU20: 0 | AV20: 0 | AW20: 0 | AX20: 0 | AY20: 209485.34 | AZ20: 247285.34 | BA20: 20180125 | BB20: -15120 | BC20: 0 | BD20: 0 | BE20: 0 | BF20: 20110701 | BG20: 15224.93 | BH20: NULL | BI20: NULL | BJ20: 20110131 | BK20: 2763.4 | BL20: 0 | BM20: 877.9 | BN20: 636.35 | BO20: N | BP20: Y | BQ20: Y | BR20: N | BS20: FOB SHIP POINT | BT20: NA | BU20: NULL | BV20: EXP | BW20: NULL | BX20: NULL | BY20: 0 | BZ20: NULL | CA20: NULL | CB20: 0 | CC20: NULL | CD20: 70000000 | CE20: NULL | CF20: NULL | CG20: NULL | CH20: 26 | CI20: MHI | CJ20: NULL | CK20: NULL | CL20: NULL | CM20: NULL | CN20: NULL | CO20: 0 | CP20: 0 | CQ20: 1514.25 | CR20: NULL | CS20: NULL | CT20: NULL | CU20: NULL | CV20: 34
A21: 8 | B21: JITC01 | C21: JITC01 | D21: 53370 | E21: PLANT#18232 | F21: CALLE NEGRA MODELO #6A FRACC ALCE BLANCO | G21: NAUCALPA | H21: NAUCALPA | I21: NULL | J21: 53370 | K21: MEXICO | L21: NULL | M21: NULL | N21: 525 284 7224 | O21: 525 284 7221 | P21: NULL | Q21: NULL | R21: 525 2847231 | S21: 19991111 | T21: 2 | U21: MCUEX | V21: O | W21: M | X21: NULL | Y21: =LEFT(S21,4) -> 1999 | Z21: =RIGHT(S21,4) -> 1111 | AA21: =LEFT(Z21,2) -> 11 | AB21: =RIGHT(Z21,2) -> 11 | AC21: =CONCATENATE(Y21,"-",AA21,"-",AB21) -> 1999-11-11 | AD21: NULL | AE21: MX | AF21: USD | AG21: NULL | AH21: N | AI21: AF | AJ21: NULL | AK21: 30 | AL21: 0 | AM21: 0 | AN21: N | AO21: NO | AP21: NULL | AQ21: NULL | AR21: NULL | AS21: 0 | AT21: 0 | AU21: 0 | AV21: 0 | AW21: 0 | AX21: 0 | AY21: 13214 | AZ21: 984539.42 | BA21: 20111029 | BB21: 11234 | BC21: 0 | BD21: 0 | BE21: 0 | BF21: 20020120 | BG21: 0 | BH21: NULL | BI21: NULL | BJ21: 20110131 | BK21: 0 | BL21: 0 | BM21: 0 | BN21: 0 | BO21: N | BP21: Y | BQ21: Y | BR21: N | BS21: NULL | BT21: n/a | BU21: NULL | BV21: NULL | BW21: NULL | BX21: NULL | BY21: 0 | BZ21: NULL | CA21: NULL | CB21: 0 | CC21: NULL | CD21: 69000000 | CE21: NULL | CF21: NULL | CG21: NULL | CH21: 20 | CI21: MFP | CJ21: 2.59 | CK21: 2.64 | CL21: NULL | CM21: NULL | CN21: NULL | CO21: 0 | CP21: 0 | CQ21: 0 | CR21: JITC01 | CS21: NULL | CT21: NULL | CU21: NULL | CV21: 8
A22: 32 | B22: JOHN01 | C22: JOHN01 | D22: 32320 | E22: EPSILON 6525 | F22: PARQUE INDUSTRIAL OMEGA | G22: JUAREZ | H22: JUAREZ | I22: NULL | J22: 32320 | K22: MEXICO | L22: RICARDO PEREZ | M22: NULL | N22: 01-55-5284-7154 | O22: NULL | P22: NULL | Q22: NULL | R22: 01-55-5284-7210 | S22: 20020122 | T22: 2 | U22: MFUEX | V22: O | W22: M | X22: 50000 | Y22: =LEFT(S22,4) -> 2002 | Z22: =RIGHT(S22,4) -> 0122 | AA22: =LEFT(Z22,2) -> 01 | AB22: =RIGHT(Z22,2) -> 22 | AC22: =CONCATENATE(Y22,"-",AA22,"-",AB22) -> 2002-01-22 | AD22: NULL | AE22: MX | AF22: USD | AG22: NULL | AH22: N | AI22: AF | AJ22: NULL | AK22: 30 | AL22: 0 | AM22: 0 | AN22: N | AO22: NULL | AP22: NULL | AQ22: NULL | AR22: NULL | AS22: 0 | AT22: 0 | AU22: 0 | AV22: 0 | AW22: 0 | AX22: 0 | AY22: 1283982.1 | AZ22: 1283982.1 | BA22: 20181211 | BB22: 1531.6 | BC22: 0 | BD22: 0 | BE22: 0 | BF22: 20111101 | BG22: 29305.8 | BH22: NULL | BI22: NULL | BJ22: 20110131 | BK22: 0 | BL22: 0 | BM22: 0 | BN22: 0 | BO22: N | BP22: Y | BQ22: Y | BR22: N | BS22: RICARDO.PEREZ@JCI.COM | BT22: N/A | BU22: NULL | BV22: EXP | BW22: NULL | BX22: NULL | BY22: 0 | BZ22: NULL | CA22: NULL | CB22: 0 | CC22: NULL | CD22: 69000000 | CE22: NULL | CF22: NULL | CG22: 3-30318 | CH22: 26 | CI22: MFP | CJ22: NULL | CK22: NULL | CL22: NULL | CM22: NULL | CN22: NULL | CO22: 0 | CP22: 0 | CQ22: 0 | CR22: NULL | CS22: NULL | CT22: NULL | CU22: NULL | CV22: 32
A23: 9 | B23: JOHN02 | C23: JOHN02 | D23: 79936 | E23: 1320 Goodyear Dr | F23: NULL | G23: El Paso | H23: El Paso | I23: TX | J23: 79936 | K23: U.S.A | L23: NULL | M23: NULL | O23: NULL | P23: NULL | Q23: NULL | R23: NULL | S23: 20010304 | T23: 2 | U23: MCUEX | V23: O | W23: M | X23: 250000 | Y23: =LEFT(S23,4) -> 2001 | Z23: =RIGHT(S23,4) -> 0304 | AA23: =LEFT(Z23,2) -> 03 | AB23: =RIGHT(Z23,2) -> 04 | AC23: =CONCATENATE(Y23,"-",AA23,"-",AB23) -> 2001-03-04 | AD23: NULL | AE23: US | AF23: USD | AG23: NULL | AH23: N | AI23: LOC | AJ23: NULL | AK23: 30 | AL23: 0 | AM23: 0 | AN23: N | AO23: 0 | AP23: NULL | AQ23: NULL | AR23: NULL | AS23: 0 | AT23: 0 | AU23: 0 | AV23: 0 | AW23: 0 | AX23: 0 | AY23: 543.6 | AZ23: 60962.08 | BA23: 20141204 | BB23: 500 | BC23: 0 | BD23: 0 | BE23: 0 | BF23: 20071023 | BG23: 107.38 | BH23: NULL | BI23: NULL | BJ23: 20110131 | BK23: 0 | BL23: 0 | BM23: 0 | BN23: 0 | BO23: N | BP23: Y | BQ23: Y | BR23: N | BS23: NULL | BT23: N/A | BU23: NULL | BV23: NULL | BW23: NULL | BX23: NULL | BY23: 0 | BZ23: NULL | CA23: NULL | CB23: 0 | CC23: NULL | CD23: 65000000 | CE23: NULL | CF23: NULL | CG23: 1708048 | CH23: 20 | CI23: MFP | CJ23: 3.08 | CK23: NULL | CL23: NULL | CM23: NULL | CN23: NULL | CO23: 0 | CP23: 0 | CQ23: 0 | CR23: NULL | CS23: NULL | CT23: NULL | CU23: NULL | CV23: 9
A24: 37 | B24: JOHN03 | C24: JOHN03 | D24: 981700 | E24: JOHNSON CONTROLS INC | F24: SSC ACCOUNTS PAYABLE | G24: EL PASO | H24: EL PASO | I24: TX | J24: 981700 | K24: USA | L24: BETHANY SCOTT | M24: NULL | O24: NULL | P24: NULL | Q24: NULL | R24: NULL | S24: 20061220 | T24: 2 | U24: MCUEX | V24: O | W24: M | X24: NULL | Y24: =LEFT(S24,4) -> 2006 | Z24: =RIGHT(S24,4) -> 1220 | AA24: =LEFT(Z24,2) -> 12 | AB24: =RIGHT(Z24,2) -> 20 | AC24: =CONCATENATE(Y24,"-",AA24,"-",AB24) -> 2006-12-20 | AD24: NULL | AE24: NULL | AF24: USD | AG24: NULL | AH24: N | AI24: LOC | AJ24: NULL | AK24: 30 | AL24: 0 | AM24: 0 | AN24: N | AO24: NULL | AP24: NULL | AQ24: NULL | AR24: NULL | AS24: 0 | AT24: 0 | AU24: 0 | AV24: 0 | AW24: 0 | AX24: 0 | AY24: 12287.77 | AZ24: 245762.2 | BA24: 20171123 | BB24: 133.4 | BC24: 0 | BD24: 0 | BE24: 0 | BF24: 20100602 | BG24: 3405.78 | BH24: NULL | BI24: NULL | BJ24: 20110131 | BK24: 0 | BL24: 0 | BM24: 0 | BN24: -630.6 | BO24: N | BP24: Y | BQ24: Y | BR24: N | BS24: NULL | BT24: NA | BU24: NULL | BV24: EXP | BW24: NULL | BX24: NULL | BY24: 0 | BZ24: NULL | CA24: NULL | CB24: 0 | CC24: NULL | CD24: 70000000 | CE24: NULL | CF24: NULL | CG24: NULL | CH24: 26 | CI24: MFP | CJ24: NULL | CK24: NULL | CL24: NULL | CM24: NULL | CN24: NULL | CO24: 0 | CP24: 0 | CQ24: -630.6 | CR24: NULL | CS24: NULL | CT24: NULL | CU24: NULL | CV24: 37
A25: 38 | B25: JOHN04 | C25: JOHN04 | D25: 79998 | E25: SSC ACCOUNTS PAYABLE -18438 | F25: PO BOX 981700 | G25: EL PASO | H25: EL PASO | I25: NULL | J25: 79998 | K25: USA | L25: MIKE CHOPSON | M25: NULL | O25: NULL | P25: NULL | Q25: NULL | R25: NULL | S25: 20070118 | T25: 11 | U25: MCUEX | V25: O | W25: M | X25: NULL | Y25: =LEFT(S25,4) -> 2007 | Z25: =RIGHT(S25,4) -> 0118 | AA25: =LEFT(Z25,2) -> 01 | AB25: =RIGHT(Z25,2) -> 18 | AC25: =CONCATENATE(Y25,"-",AA25,"-",AB25) -> 2007-01-18 | AD25: NULL | AE25: NULL | AF25: USD | AG25: NULL | AH25: N | AI25: LOC | AJ25: NULL | AK25: 30 | AL25: 0 | AM25: 0 | AN25: N | AO25: NULL | AP25: NULL | AQ25: NULL | AR25: NULL | AS25: 0 | AT25: 0 | AU25: 0 | AV25: 0 | AW25: 0 | AX25: 0 | AY25: 0 | AZ25: 1306851.6 | BA25: 20070427 | BB25: 62678.4 | BC25: 0 | BD25: 0 | BE25: 0 | BF25: 20070720 | BG25: 599345.2 | BH25: NULL | BI25: NULL | BJ25: 20110131 | BK25: 0 | BL25: 0 | BM25: 0 | BN25: 0 | BO25: N | BP25: Y | BQ25: Y | BR25: N | BS25: NULL | BT25: NULL | BU25: NULL | BV25: EXP | BW25: NULL | BX25: NULL | BY25: 0 | BZ25: NULL | CA25: NULL | CB25: 0 | CC25: NULL | CD25: 69000000 | CE25: NULL | CF25: NULL | CG25: NULL | CH25: 26 | CI25: MFP | CJ25: NULL | CK25: NULL | CL25: NULL | CM25: NULL | CN25: NULL | CO25: 0 | CP25: 0 | CQ25: 0 | CR25: NULL | CS25: NULL | CT25: NULL | CU25: NULL | CV25: 38
A26: 48 | B26: KAMA01 | C26: KAMA01 | D26: 11021 | E26: 17 BARSTOW ROAD | F26: NULL | G26: GREAT NECK | H26: GREAT NECK | I26: NY | J26: 11021 | K26: USA | L26: RUTH KAMALI | M26: NULL | O26: NULL | P26: NULL | Q26: NULL | R26: NULL | S26: 20151207 | T26: 2 | U26: MISC | V26: O | W26: M | X26: NULL | Y26: =LEFT(S26,4) -> 2015 | Z26: =RIGHT(S26,4) -> 1207 | AA26: =LEFT(Z26,2) -> 12 | AB26: =RIGHT(Z26,2) -> 07 | AC26: =CONCATENATE(Y26,"-",AA26,"-",AB26) -> 2015-12-07 | AD26: NULL | AE26: NULL | AF26: USD | AG26: NULL | AH26: N | AI26: AF | AJ26: NULL | AK26: COD | AL26: 0 | AM26: 0 | AN26: N | AO26: 0 | AP26: NULL | AQ26: NULL | AR26: NULL | AS26: 0 | AT26: 0 | AU26: 0 | AV26: 0 | AW26: 0 | AX26: 0 | AY26: 964169.79 | AZ26: 964169.79 | BA26: 20181002 | BB26: 0 | BC26: 0 | BD26: 0 | BE26: 0 | BF26: 0 | BG26: 0 | BH26: NULL | BI26: NULL | BJ26: 0 | BK26: 0 | BL26: 0 | BM26: 0 | BN26: 0 | BO26: N | BP26: Y | BQ26: Y | BR26: N | BS26: NULL | BT26: NULL | BU26: NULL | BV26: NULL | BW26: NULL | BX26: NULL | BY26: 0 | BZ26: NULL | CA26: NULL | CB26: 0 | CC26: NULL | CD26: 69000000 | CE26: NULL | CF26: NULL | CG26: NULL | CH26: 26 | CI26: NULL | CJ26: NULL | CK26: NULL | CL26: NULL | CM26: NULL | CN26: NULL | CO26: 0 | CP26: 0 | CQ26: 0 | CR26: NULL | CS26: NULL | CT26: NULL | CU26: NULL | CV26: 48
A27: 39 | B27: KONG01 | C27: KONG01 | D27: 78577 | E27: LAREDO FREIGHT - KONGSBERG AUTOMOTIVE | F27: 9208 SOUTH CAGE BLVD | G27: PHARR | H27: PHARR | I27: TX | J27: 78577 | K27: USA | L27: DAVE SCHUTTER | M27: NULL | N27: 12486153090 | O27: NULL | P27: NULL | Q27: NULL | R27: 12486153098 | S27: 20080129 | T27: 2 | U27: MCUEX | V27: O | W27: M | X27: NULL | Y27: =LEFT(S27,4) -> 2008 | Z27: =RIGHT(S27,4) -> 0129 | AA27: =LEFT(Z27,2) -> 01 | AB27: =RIGHT(Z27,2) -> 29 | AC27: =CONCATENATE(Y27,"-",AA27,"-",AB27) -> 2008-01-29 | AD27: NULL | AE27: NULL | AF27: USD | AG27: NULL | AH27: N | AI27: LOC | AJ27: NULL | AK27: 45 | AL27: 0 | AM27: 0 | AN27: N | AO27: NULL | AP27: NULL | AQ27: NULL | AR27: NULL | AS27: 0 | AT27: 0 | AU27: 0 | AV27: 0 | AW27: 0 | AX27: 0 | AY27: 2243.09 | AZ27: 26874.1 | BA27: 20160511 | BB27: 63 | BC27: 0 | BD27: 0 | BE27: 0 | BF27: 20111101 | BG27: 24694.01 | BH27: NULL | BI27: NULL | BJ27: 20110131 | BK27: 0 | BL27: 0 | BM27: 0 | BN27: 3.82 | BO27: N | BP27: Y | BQ27: Y | BR27: N | BS27: EXW | BT27: NA | BU27: NULL | BV27: EXP | BW27: NULL | BX27: NULL | BY27: 0 | BZ27: NULL | CA27: NULL | CB27: 0 | CC27: NULL | CD27: 65000000 | CE27: NULL | CF27: NULL | CG27: NULL | CH27: 26 | CI27: MFP | CJ27: NULL | CK27: NULL | CL27: NULL | CM27: NULL | CN27: NULL | CO27: 0 | CP27: 0 | CQ27: 3.82 | CR27: NULL | CS27: NULL | CT27: NULL | CU27: NULL | CV27: 39
A28: 10 | B28: KRAF01 | C28: KRAF01 | D28: 48843 | E28: 955 GRAND OAKS DRIVE | F28: NULL | G28: HOWELL | H28: HOWELL | I28: MI | J28: 48843 | K28: USA | L28: STEVE KRAFT | M28: NULL | N28: 517 545 7500 | O28: NULL | P28: NULL | Q28: NULL | R28: 517 545 8199 | S28: 20010426 | T28: 8 | U28: MFUEX | V28: O | W28: M | X28: 5000 | Y28: =LEFT(S28,4) -> 2001 | Z28: =RIGHT(S28,4) -> 0426 | AA28: =LEFT(Z28,2) -> 04 | AB28: =RIGHT(Z28,2) -> 26 | AC28: =CONCATENATE(Y28,"-",AA28,"-",AB28) -> 2001-04-26 | AD28: NULL | AE28: NULL | AF28: USD | AG28: NULL | AH28: N | AI28: AF | AJ28: NULL | AK28: 30 | AL28: 0 | AM28: 0 | AN28: N | AO28: 0 | AP28: NULL | AQ28: NULL | AR28: NULL | AS28: 0 | AT28: 0 | AU28: 0 | AV28: 0 | AW28: 0 | AX28: 0 | AY28: 0 | AZ28: 2657.13 | BA28: 20050719 | BB28: 1600.07 | BC28: 0 | BD28: 0 | BE28: 0 | BF28: 20051114 | BG28: 1600.07 | BH28: NULL | BI28: NULL | BJ28: 20110131 | BK28: 0 | BL28: 0 | BM28: 0 | BN28: 0 | BO28: N | BP28: Y | BQ28: Y | BR28: N | BS28: NULL | BT28: N/A | BU28: NULL | BV28: NULL | BW28: NULL | BX28: NULL | BY28: 0 | BZ28: NULL | CA28: NULL | CB28: 0 | CC28: NULL | CD28: 0 | CE28: NULL | CF28: NULL | CG28: NULL | CH28: 26 | CI28: NULL | CJ28: NULL | CK28: NULL | CL28: NULL | CM28: NULL | CN28: NULL | CO28: 0 | CP28: 0 | CQ28: 0 | CR28: KRAF01 | CS28: NULL | CT28: NULL | CU28: NULL | CV28: 10
A29: 11 | B29: LEAR05 | C29: LEAR05 | D29: 79936 | E29: 1440 DON HASKINS | F29: NULL | G29: EL PASO | H29: EL PASO | I29: TX | J29: 79936 | K29: USA | L29: NULL | M29: NULL | N29: 915 499 4545 | O29: NULL | P29: NULL | Q29: NULL | R29: 915 849 5610 | S29: 19980525 | T29: 2 | U29: MCUEX | V29: O | W29: M | X29: 8000000 | Y29: =LEFT(S29,4) -> 1998 | Z29: =RIGHT(S29,4) -> 0525 | AA29: =LEFT(Z29,2) -> 05 | AB29: =RIGHT(Z29,2) -> 25 | AC29: =CONCATENATE(Y29,"-",AA29,"-",AB29) -> 1998-05-25 | AD29: NULL | AE29: MX | AF29: USD | AG29: NULL | AH29: N | AI29: AF | AJ29: HLD | AK29: 30 | AL29: 0 | AM29: 0 | AN29: N | AO29: 0 | AP29: NULL | AQ29: NULL | AR29: NULL | AS29: 0 | AT29: 0 | AU29: 0 | AV29: 0 | AW29: 0 | AX29: 0 | AY29: -10838.62 | AZ29: 5532033.5 | BA29: 20131107 | BB29: 0 | BC29: 0 | BD29: 0 | BE29: 0 | BF29: 20040622 | BG29: 23010.4 | BH29: NULL | BI29: NULL | BJ29: 20110131 | BK29: 0 | BL29: 0 | BM29: 0 | BN29: 0 | BO29: N | BP29: Y | BQ29: Y | BR29: N | BS29: NULL | BT29: n/a | BU29: NULL | BV29: NULL | BW29: NULL | BX29: NULL | BY29: 0 | BZ29: NULL | CA29: NULL | CB29: 0 | CC29: NULL | CD29: 72000000 | CE29: NULL | CF29: NULL | CG29: 1703011 | CH29: 26 | CI29: MFP | CJ29: 2.78 | CK29: NULL | CL29: NULL | CM29: NULL | CN29: NULL | CO29: 0 | CP29: 0 | CQ29: 0 | CR29: LEAR05 | CS29: NULL | CT29: NULL | CU29: NULL | CV29: 11
A30: 30 | B30: LEAR07 | C30: LEAR07 | D30: 85621 | E30: LEAR CORPORATION MEXICO SA DE CV | F30: PO BOX 6323 | G30: NOGALES | H30: NOGALES | I30: AZ | J30: 85621 | K30: USA | L30: DAVID RAMOS | M30: NULL | O30: NULL | P30: NULL | Q30: NULL | R30: NULL | S30: 20011018 | T30: 2 | U30: MCUEX | V30: O | W30: M | X30: 8000000 | Y30: =LEFT(S30,4) -> 2001 | Z30: =RIGHT(S30,4) -> 1018 | AA30: =LEFT(Z30,2) -> 10 | AB30: =RIGHT(Z30,2) -> 18 | AC30: =CONCATENATE(Y30,"-",AA30,"-",AB30) -> 2001-10-18 | AD30: NULL | AE30: MX | AF30: USD | AG30: NULL | AH30: N | AI30: LOC | AJ30: NULL | AK30: 30 | AL30: 0 | AM30: 0 | AN30: N | AO30: 0 | AP30: NULL | AQ30: NULL | AR30: NULL | AS30: 0 | AT30: 0 | AU30: 0 | AV30: 0 | AW30: 0 | AX30: 0 | AY30: 0 | AZ30: 436963.86 | BA30: 20050520 | BB30: 425.94 | BC30: 0 | BD30: 0 | BE30: 0 | BF30: 20050607 | BG30: 293.4 | BH30: NULL | BI30: NULL | BJ30: 20110131 | BK30: 0 | BL30: 0 | BM30: 0 | BN30: 0 | BO30: N | BP30: Y | BQ30: Y | BR30: N | BS30: NULL | BT30: abn | BU30: NULL | BV30: NULL | BW30: NULL | BX30: NULL | BY30: 0 | BZ30: NULL | CA30: NULL | CB30: 0 | CC30: NULL | CD30: 70000000 | CE30: NULL | CF30: NULL | CG30: 1703011 | CH30: 28 | CI30: MFP | CJ30: NULL | CK30: NULL | CL30: NULL | CM30: NULL | CN30: NULL | CO30: 0 | CP30: 0 | CQ30: 0 | CR30: 2 | CS30: NULL | CT30: NULL | CU30: NULL | CV30: 30
A31: 12 | B31: LEAT01 | C31: LEAT01 | D31: 48086-4178 | E31: PO BOX 4178 | F31: SOUTHFIELD | G31: NULL | H31: NULL | I31: WA | J31: 48086-4178 | K31: USA | L31: CATHY SADLER | M31: NULL | O31: NULL | P31: NULL | Q31: NULL | R31: NULL | S31: 20000309 | T31: 2 | U31: MFUEX | V31: O | W31: M | X31: 1000 | Y31: =LEFT(S31,4) -> 2000 | Z31: =RIGHT(S31,4) -> 0309 | AA31: =LEFT(Z31,2) -> 03 | AB31: =RIGHT(Z31,2) -> 09 | AC31: =CONCATENATE(Y31,"-",AA31,"-",AB31) -> 2000-03-09 | AD31: NULL | AE31: MX | AF31: USD | AG31: NULL | AH31: N | AI31: LOC | AJ31: NULL | AK31: 30 | AL31: 0 | AM31: 0 | AN31: N | AO31: NO | AP31: NULL | AQ31: NULL | AR31: NULL | AS31: 0 | AT31: 0 | AU31: 0 | AV31: 0 | AW31: 0 | AX31: 0 | AY31: 0 | AZ31: 0 | BA31: 20000310 | BB31: 592.74 | BC31: 0 | BD31: 0 | BE31: 0 | BF31: 20000621 | BG31: 592.74 | BH31: NULL | BI31: NULL | BJ31: 20110131 | BK31: 0 | BL31: 0 | BM31: 0 | BN31: 0 | BO31: N | BP31: Y | BQ31: Y | BR31: N | BS31: NULL | BT31: n/a | BU31: NULL | BV31: NULL | BW31: NULL | BX31: NULL | BY31: 0 | BZ31: NULL | CA31: NULL | CB31: 0 | CC31: NULL | CD31: 0 | CE31: NULL | CF31: NULL | CG31: 1703011 | CH31: 20 | CI31: MFP | CJ31: NULL | CK31: NULL | CL31: NULL | CM31: NULL | CN31: NULL | CO31: 0 | CP31: 0 | CQ31: 0 | CR31: NULL | CS31: NULL | CT31: NULL | CU31: NULL | CV31: 12
A32: 13 | B32: LEAV01 | C32: LEAV01 | D32: 79917-7709 | E32: 9500 PLAZA CIRCLE | F32: P.O. BOX 17709 | G32: EL PASO | H32: EL PASO | I32: TX | J32: 79917-7709 | K32: USA | L32: NULL | M32: NULL | O32: NULL | P32: NULL | Q32: NULL | R32: NULL | S32: 19990225 | T32: 2 | U32: MFUEX | V32: O | W32: M | X32: 8000000 | Y32: =LEFT(S32,4) -> 1999 | Z32: =RIGHT(S32,4) -> 0225 | AA32: =LEFT(Z32,2) -> 02 | AB32: =RIGHT(Z32,2) -> 25 | AC32: =CONCATENATE(Y32,"-",AA32,"-",AB32) -> 1999-02-25 | AD32: NULL | AE32: MX | AF32: USD | AG32: NULL | AH32: N | AI32: LOC | AJ32: NULL | AK32: 30 | AL32: 0 | AM32: 0 | AN32: N | AO32: NULL | AP32: NULL | AQ32: NULL | AR32: NULL | AS32: 0 | AT32: 0 | AU32: 0 | AV32: 0 | AW32: 0 | AX32: 0 | AY32: 25733520 | AZ32: 25733520 | BA32: 20190124 | BB32: 280.8 | BC32: 0 | BD32: 0 | BE32: 0 | BF32: 20110701 | BG32: 318.38 | BH32: NULL | BI32: NULL | BJ32: 20110131 | BK32: 0 | BL32: 318.38 | BM32: 0 | BN32: 62.3 | BO32: N | BP32: Y | BQ32: Y | BR32: N | BS32: NULL | BT32: n/a | BU32: NULL | BV32: EXP | BW32: NULL | BX32: NULL | BY32: 0 | BZ32: NULL | CA32: NULL | CB32: 0 | CC32: NULL | CD32: 70000000 | CE32: NULL | CF32: NULL | CG32: 1703011 | CH32: 26 | CI32: MFP | CJ32: NULL | CK32: NULL | CL32: NULL | CM32: NULL | CN32: NULL | CO32: 0 | CP32: 0 | CQ32: 380.68 | CR32: NULL | CS32: NULL | CT32: NULL | CU32: NULL | CV32: 13
A33: 14 | B33: LEAW01 | C33: LEAW01 | D33: 48101 | E33: ATTN Accounts Payable | F33: 16630 Southfield Road, Suite 3100 | G33: Allen Park | H33: Allen Park | I33: MI | J33: 48101 | K33: USA | L33: Ms Daniela Olejnik | M33: NULL | N33: 1313 755 4909 | O33: NULL | P33: NULL | Q33: NULL | R33: 1313 755 4898 | S33: 20010822 | T33: 2 | U33: MFUEX | V33: O | W33: M | X33: NULL | Y33: =LEFT(S33,4) -> 2001 | Z33: =RIGHT(S33,4) -> 0822 | AA33: =LEFT(Z33,2) -> 08 | AB33: =RIGHT(Z33,2) -> 22 | AC33: =CONCATENATE(Y33,"-",AA33,"-",AB33) -> 2001-08-22 | AD33: NULL | AE33: NULL | AF33: USD | AG33: NULL | AH33: N | AI33: AF | AJ33: NULL | AK33: 30 | AL33: 0 | AM33: 0 | AN33: N | AO33: 0 | AP33: NULL | AQ33: NULL | AR33: NULL | AS33: 0 | AT33: 0 | AU33: 0 | AV33: 0 | AW33: 0 | AX33: 0 | AY33: 0 | AZ33: 76800.99 | BA33: 20020410 | BB33: 0 | BC33: 0 | BD33: 0 | BE33: 0 | BF33: 20011221 | BG33: 66855.4 | BH33: NULL | BI33: NULL | BJ33: 20110131 | BK33: 0 | BL33: 0 | BM33: 0 | BN33: 0 | BO33: N | BP33: Y | BQ33: Y | BR33: N | BS33: NULL | BT33: Duty Paid | BU33: NULL | BV33: NULL | BW33: NULL | BX33: NULL | BY33: 0 | BZ33: NULL | CA33: NULL | CB33: 0 | CC33: NULL | CD33: 0 | CE33: NULL | CF33: NULL | CG33: NULL | CH33: 28 | CI33: NULL | CJ33: NULL | CK33: NULL | CL33: NULL | CM33: NULL | CN33: NULL | CO33: 0 | CP33: 0 | CQ33: 0 | CR33: LEAW01 | CS33: NULL | CT33: NULL | CU33: NULL | CV33: 14
A34: 15 | B34: LEGM01 | C34: LEGM01 | D34: 48092 | E34: 5800 ENTERPRISE DRIVE | F34: NULL | G34: WARREN | H34: WARREN | I34: MI | J34: 48092 | K34: USA | L34: NULL | M34: NULL | N34: 810 5780400 | O34: 810 5780414 | P34: NULL | Q34: NULL | R34: NULL | S34: 19991119 | T34: 2 | U34: MFUEX | V34: O | W34: M | X34: 1000 | Y34: =LEFT(S34,4) -> 1999 | Z34: =RIGHT(S34,4) -> 1119 | AA34: =LEFT(Z34,2) -> 11 | AB34: =RIGHT(Z34,2) -> 19 | AC34: =CONCATENATE(Y34,"-",AA34,"-",AB34) -> 1999-11-19 | AD34: NULL | AE34: US | AF34: USD | AG34: NULL | AH34: N | AI34: AF | AJ34: NULL | AK34: 30 | AL34: 0 | AM34: 0 | AN34: N | AO34: NO | AP34: NULL | AQ34: NULL | AR34: NULL | AS34: 0 | AT34: 0 | AU34: 0 | AV34: 0 | AW34: 0 | AX34: 0 | AY34: 521.7 | AZ34: 6600 | BA34: 20180207 | BB34: 521.7 | BC34: 0 | BD34: 0 | BE34: 0 | BF34: 20021025 | BG34: 6600 | BH34: NULL | BI34: NULL | BJ34: 20110131 | BK34: 0 | BL34: 0 | BM34: 0 | BN34: 0 | BO34: N | BP34: Y | BQ34: Y | BR34: N | BS34: NULL | BT34: n/a | BU34: NULL | BV34: NULL | BW34: NULL | BX34: NULL | BY34: 0 | BZ34: NULL | CA34: NULL | CB34: 0 | CC34: NULL | CD34: 0 | CE34: NULL | CF34: NULL | CG34: 1703011 | CH34: 20 | CI34: MFP | CJ34: NULL | CK34: NULL | CL34: NULL | CM34: NULL | CN34: NULL | CO34: 0 | CP34: 0 | CQ34: 0 | CR34: NULL | CS34: NULL | CT34: NULL | CU34: NULL | CV34: 15
A35: 16 | B35: LFOR01 | C35: LFOR01 | D35: 48126 | E35: 5250 AUTO CLUB DRIVE ANNEX | F35: NULL | G35: DEARBORN | H35: DEARBORN | I35: MI | J35: 48126 | K35: USA | L35: LILA MACKEY | M35: NULL | N35: 313 5939000 | O35: NULL | P35: NULL | Q35: NULL | R35: 313 2535041 | S35: 19990430 | T35: 2 | U35: MFUEX | V35: O | W35: M | X35: 100000 | Y35: =LEFT(S35,4) -> 1999 | Z35: =RIGHT(S35,4) -> 0430 | AA35: =LEFT(Z35,2) -> 04 | AB35: =RIGHT(Z35,2) -> 30 | AC35: =CONCATENATE(Y35,"-",AA35,"-",AB35) -> 1999-04-30 | AD35: NULL | AE35: US | AF35: USD | AG35: NULL | AH35: N | AI35: AF | AJ35: NULL | AK35: 30 | AL35: 0 | AM35: 0 | AN35: N | AO35: NO | AP35: NULL | AQ35: NULL | AR35: NULL | AS35: 0 | AT35: 0 | AU35: 0 | AV35: 0 | AW35: 0 | AX35: 0 | AY35: 0 | AZ35: 119.93 | BA35: 20001122 | BB35: -602.58 | BC35: 0 | BD35: 0 | BE35: 0 | BF35: 20001219 | BG35: 119.93 | BH35: NULL | BI35: NULL | BJ35: 20110131 | BK35: 0 | BL35: 0 | BM35: 0 | BN35: 0 | BO35: N | BP35: Y | BQ35: Y | BR35: N | BS35: NULL | BT35: N/A | BU35: NULL | BV35: NULL | BW35: NULL | BX35: NULL | BY35: 0 | BZ35: NULL | CA35: NULL | CB35: 0 | CC35: NULL | CD35: 0 | CE35: NULL | CF35: NULL | CG35: 3-43790 | CH35: 20 | CI35: MFP | CJ35: NULL | CK35: NULL | CL35: NULL | CM35: NULL | CN35: NULL | CO35: 0 | CP35: 0 | CQ35: 0 | CR35: NULL | CS35: NULL | CT35: NULL | CU35: NULL | CV35: 16
A36: 17 | B36: MAGN01 | C36: MAGN01 | D36: 78852 | E36: A DIV OF Magna Seating of America, Inc. | F36: 540 SOUTH BIBB PMB #1 | G36: EAGLE PASS | H36: EAGLE PASS | I36: TX | J36: 78852 | K36: USA | L36: DOUG DEATON | M36: NULL | N36: 011 52 86130319 | O36: NULL | P36: NULL | Q36: NULL | R36: NULL | S36: 19991112 | T36: 2 | U36: MCUEX | V36: O | W36: M | X36: 3000000 | Y36: =LEFT(S36,4) -> 1999 | Z36: =RIGHT(S36,4) -> 1112 | AA36: =LEFT(Z36,2) -> 11 | AB36: =RIGHT(Z36,2) -> 12 | AC36: =CONCATENATE(Y36,"-",AA36,"-",AB36) -> 1999-11-12 | AD36: NULL | AE36: MX | AF36: USD | AG36: NULL | AH36: N | AI36: AF | AJ36: NULL | AK36: 5 | AL36: 0 | AM36: 0 | AN36: N | AO36: 0 | AP36: NULL | AQ36: NULL | AR36: NULL | AS36: 0 | AT36: 0 | AU36: 0 | AV36: 0 | AW36: 0 | AX36: 0 | AY36: 2304813.9 | AZ36: 3866467.4 | BA36: 20181129 | BB36: 0 | BC36: 0 | BD36: 0 | BE36: 0 | BF36: 20111101 | BG36: 2222.36 | BH36: NULL | BI36: NULL | BJ36: 20110131 | BK36: 704282.91 | BL36: 509519.25 | BM36: 11585.62 | BN36: -1442.71 | BO36: N | BP36: Y | BQ36: Y | BR36: N | BS36: NULL | BT36: n/a | BU36: NULL | BV36: NULL | BW36: NULL | BX36: NULL | BY36: 0 | BZ36: NULL | CA36: NULL | CB36: 0 | CC36: NULL | CD36: 69000000 | CE36: NULL | CF36: NULL | CG36: 11519661 | CH36: 26 | CI36: MFP | CJ36: NULL | CK36: NULL | CL36: NULL | CM36: NULL | CN36: NULL | CO36: 0 | CP36: 0 | CQ36: 1223945.1 | CR36: 1 | CS36: NULL | CT36: NULL | CU36: NULL | CV36: 17
A37: 18 | B37: MAGN02 | C37: MAGN02 | D37: 78840 | E37: 2199 SPUR 239 | F37: MAILING TO: P.O BOX 420699 | G37: DEL RIO | H37: DEL RIO | I37: TX | J37: 78840 | K37: USA | R37: NULL | S37: 20000201 | T37: 2 | U37: MCUEX | V37: O | W37: M | X37: 3000000 | Y37: =LEFT(S37,4) -> 2000 | Z37: =RIGHT(S37,4) -> 0201 | AA37: =LEFT(Z37,2) -> 02 | AB37: =RIGHT(Z37,2) -> 01 | AC37: =CONCATENATE(Y37,"-",AA37,"-",AB37) -> 2000-02-01 | AD37: NULL | AE37: MX | AF37: USD | AG37: NULL | AH37: N | AI37: LOC | AJ37: NULL | AK37: 60 | AL37: 0 | AM37: 0 | AN37: N | AO37: 0 | AP37: NULL | AQ37: NULL | AR37: NULL | AS37: 0 | AT37: 0 | AU37: 0 | AV37: 0 | AW37: 0 | AX37: 0 | AY37: 4080 | AZ37: 31321.38 | BA37: 20150310 | BB37: 4080 | BC37: 0 | BD37: 0 | BE37: 0 | BF37: 20060428 | BG37: 2640 | BH37: NULL | BI37: NULL | BJ37: 20110131 | BK37: 0 | BL37: 0 | BM37: 0 | BN37: 0 | BO37: N | BP37: Y | BQ37: Y | BR37: N | BS37: NULL | BT37: n/a | BU37: NULL | BV37: NULL | BW37: NULL | BX37: NULL | BY37: 0 | BZ37: NULL | CA37: NULL | CB37: 0 | CC37: NULL | CD37: 0 | CE37: NULL | CF37: NULL | CG37: 11519661 | CH37: 20 | CI37: MFP | CJ37: NULL | CK37: NULL | CL37: NULL | CM37: NULL | CN37: NULL | CO37: 0 | CP37: 0 | CQ37: 0 | CR37: MAGN02 | CS37: NULL | CU37: NULL | CV37: 18
A38: 19 | B38: MAGN03 | C38: MAGN03 | D38: 78840 | E38: 2199 SPUR 239 | F38: P.O. BOX 420699 | G38: DEL RIO | H38: DEL RIO | I38: TX | J38: 78840 | K38: USA | L38: MARILY BURKE | M38: NULL | O38: NULL | P38: NULL | Q38: NULL | R38: NULL | S38: 20000728 | T38: 2 | U38: MCUEX | V38: O | W38: M | X38: 3000000 | Y38: =LEFT(S38,4) -> 2000 | Z38: =RIGHT(S38,4) -> 0728 | AA38: =LEFT(Z38,2) -> 07 | AB38: =RIGHT(Z38,2) -> 28 | AC38: =CONCATENATE(Y38,"-",AA38,"-",AB38) -> 2000-07-28 | AD38: NULL | AE38: US | AF38: USD | AG38: NULL | AH38: N | AI38: LOC | AJ38: NULL | AK38: 5 | AL38: 0 | AM38: 0 | AN38: N | AO38: 0 | AP38: NULL | AQ38: NULL | AR38: NULL | AS38: 0 | AT38: 0 | AU38: 0 | AV38: 0 | AW38: 0 | AX38: 0 | AY38: 33789031 | AZ38: 33789031 | BA38: 20190220 | BB38: 350 | BC38: 0 | BD38: 0 | BE38: 0 | BF38: 20140307 | BG38: 41183.1 | BH38: NULL | BI38: NULL | BJ38: 20110131 | BK38: 2406.5 | BL38: 1368.4 | BM38: 729.9 | BN38: -0.01 | BO38: N | BP38: Y | BQ38: Y | BR38: N | BS38: NULL | BT38: N/A | BU38: NULL | BV38: NULL | BW38: NULL | BX38: NULL | BY38: 0 | BZ38: NULL | CA38: NULL | CB38: 0 | CC38: NULL | CD38: 69000000 | CE38: NULL | CF38: NULL | CG38: 11519661 | CH38: 26 | CI38: MFP | CJ38: NULL | CK38: NULL | CL38: NULL | CM38: NULL | CN38: NULL | CO38: 0 | CP38: 0 | CQ38: 2098.29 | CR38: NULL | CS38: NULL | CT38: NULL | CU38: NULL | CV38: 19
A39: 47 | B39: MAGN04 | C39: MAGN04 | D39: 78840 | E39: 2199 SPUR 239 | F39: MAILING TO: P.O BOX 420699 | G39: DEL RIO | H39: DEL RIO | I39: TX | J39: 78840 | K39: USA | R39: NULL | S39: 20150831 | T39: 2 | U39: MCUEX | V39: O | W39: M | X39: 3000000 | Y39: =LEFT(S39,4) -> 2015 | Z39: =RIGHT(S39,4) -> 0831 | AA39: =LEFT(Z39,2) -> 08 | AB39: =RIGHT(Z39,2) -> 31 | AC39: =CONCATENATE(Y39,"-",AA39,"-",AB39) -> 2015-08-31 | AD39: NULL | AE39: US | AF39: USD | AG39: NULL | AH39: N | AI39: LOC | AJ39: NULL | AK39: 60 | AL39: 0 | AM39: 0 | AN39: N | AO39: 0 | AP39: NULL | AQ39: NULL | AR39: NULL | AS39: 0 | AT39: 0 | AU39: 0 | AV39: 0 | AW39: 0 | AX39: 0 | AY39: 2700 | AZ39: 2700 | BA39: 20160301 | BB39: 2700 | BC39: 0 | BD39: 0 | BE39: 0 | BF39: 0 | BG39: 0 | BH39: NULL | BI39: NULL | BJ39: 0 | BK39: 0 | BL39: 0 | BM39: 0 | BN39: 0 | BO39: N | BP39: Y | BQ39: Y | BR39: N | BS39: NULL | BT39: NULL | BU39: NULL | BV39: NULL | BW39: NULL | BX39: NULL | BY39: 0 | BZ39: NULL | CA39: NULL | CB39: 0 | CC39: NULL | CD39: 69000000 | CE39: NULL | CF39: NULL | CG39: NULL | CH39: 26 | CI39: MFP | CJ39: NULL | CK39: NULL | CL39: NULL | CM39: NULL | CN39: NULL | CO39: 0 | CP39: 0 | CQ39: 0 | CR39: NULL | CS39: NULL | CU39: NULL | CV39: 47
A40: 41 | B40: MAYS01 | C40: MAYS01 | D40: 48836 | E40: 445 E. VAN RIPER | F40: NULL | G40: FOWLERVILLE, MI | H40: FOWLERVILLE, MI | I40: NULL | J40: 48836 | K40: USA | L40: LISA FIRTH | M40: NULL | N40: (517) 223-6734 | O40: NULL | P40: NULL | Q40: NULL | R40: (517)223-1331 | S40: 20080305 | T40: 2 | U40: MCUEX | V40: O | W40: M | X40: NULL | Y40: =LEFT(S40,4) -> 2008 | Z40: =RIGHT(S40,4) -> 0305 | AA40: =LEFT(Z40,2) -> 03 | AB40: =RIGHT(Z40,2) -> 05 | AC40: =CONCATENATE(Y40,"-",AA40,"-",AB40) -> 2008-03-05 | AD40: NULL | AE40: NULL | AF40: USD | AG40: NULL | AH40: N | AI40: LOC | AJ40: NULL | AK40: 30 | AL40: 0 | AM40: 0 | AN40: N | AO40: NULL | AP40: NULL | AQ40: NULL | AR40: NULL | AS40: 0 | AT40: 0 | AU40: 0 | AV40: 0 | AW40: 0 | AX40: 0 | AY40: 0 | AZ40: 0 | BA40: 0 | BB40: 0 | BC40: 0 | BD40: 0 | BE40: 0 | BF40: 0 | BG40: 0 | BH40: NULL | BI40: NULL | BJ40: 20110131 | BK40: 0 | BL40: 0 | BM40: 0 | BN40: 0 | BO40: N | BP40: Y | BQ40: Y | BR40: N | BS40: NULL | BT40: NULL | BU40: NULL | BV40: EXP | BW40: AMEX | BX40: NULL | BY40: 0 | BZ40: NULL | CA40: NULL | CB40: 0 | CC40: NULL | CD40: 65000000 | CE40: NULL | CF40: NULL | CG40: NULL | CH40: 26 | CI40: MFP | CJ40: NULL | CK40: NULL | CL40: NULL | CM40: NULL | CN40: NULL | CO40: 0 | CP40: 0 | CQ40: 0 | CR40: MAYS01 | CS40: NULL | CT40: NULL | CU40: NULL | CV40: 41
A41: 20 | B41: MAZC01 | C41: MAZC01 | D41: MIB 3V4 | E41: 305 MILNER AVENUE, | F41: SUITE 400 | G41: SCARBOROUGH | H41: SCARBOROUGH | I41: ONT | J41: MIB 3V4 | K41: CANADA | L41: VITO PALADINO | M41: NULL | O41: NULL | P41: NULL | Q41: NULL | R41: NULL | S41: 20000322 | T41: 2 | U41: MFUEX | V41: O | W41: M | X41: 1000 | Y41: =LEFT(S41,4) -> 2000 | Z41: =RIGHT(S41,4) -> 0322 | AA41: =LEFT(Z41,2) -> 03 | AB41: =RIGHT(Z41,2) -> 22 | AC41: =CONCATENATE(Y41,"-",AA41,"-",AB41) -> 2000-03-22 | AD41: NULL | AE41: MX | AF41: USD | AG41: NULL | AH41: N | AI41: AF | AJ41: NULL | AK41: 14 | AL41: 0 | AM41: 0 | AN41: N | AO41: NO | AP41: NULL | AQ41: NULL | AR41: NULL | AS41: 0 | AT41: 0 | AU41: 0 | AV41: 0 | AW41: 0 | AX41: 0 | AY41: 0 | AZ41: 990 | BA41: 20040105 | BB41: 990 | BC41: 0 | BD41: 0 | BE41: 0 | BF41: 20040330 | BG41: 990 | BH41: NULL | BI41: NULL | BJ41: 20110131 | BK41: 0 | BL41: 0 | BM41: 0 | BN41: 0 | BO41: N | BP41: Y | BQ41: Y | BR41: N | BS41: NULL | BT41: n/a | BU41: NULL | BV41: NULL | BW41: NULL | BX41: NULL | BY41: 0 | BZ41: NULL | CA41: NULL | CB41: 0 | CC41: NULL | CD41: 0 | CE41: NULL | CF41: NULL | CG41: NULL | CH41: 20 | CI41: MFP | CJ41: NULL | CK41: NULL | CL41: NULL | CM41: NULL | CN41: NULL | CO41: 0 | CP41: 0 | CQ41: 0 | CR41: NULL | CS41: NULL | CT41: NULL | CU41: NULL | CV41: 20
A42: 21 | B42: MAZN01 | C42: MAZN01 | D42: 92618-2922 | E42: 7755 IRVINE CENTRE DRIVE | F42: NULL | G42: IRVINE | H42: IRVINE | I42: CA | J42: 92618-2922 | K42: USA | L42: MIHO NAKATANI | M42: NULL | O42: NULL | P42: NULL | Q42: NULL | R42: NULL | S42: 20000322 | T42: 2 | U42: MFUEX | V42: O | W42: M | X42: 1000 | Y42: =LEFT(S42,4) -> 2000 | Z42: =RIGHT(S42,4) -> 0322 | AA42: =LEFT(Z42,2) -> 03 | AB42: =RIGHT(Z42,2) -> 22 | AC42: =CONCATENATE(Y42,"-",AA42,"-",AB42) -> 2000-03-22 | AD42: NULL | AE42: MX | AF42: USD | AG42: NULL | AH42: N | AI42: AF | AJ42: NULL | AK42: 14 | AL42: 0 | AM42: 0 | AN42: N | AO42: NO | AP42: NULL | AQ42: NULL | AR42: NULL | AS42: 0 | AT42: 0 | AU42: 0 | AV42: 0 | AW42: 0 | AX42: 0 | AY42: 0 | AZ42: 0 | BA42: 20000330 | BB42: 56.66 | BC42: 0 | BD42: 0 | BE42: 0 | BF42: 20000621 | BG42: 56.66 | BH42: NULL | BI42: NULL | BJ42: 20110131 | BK42: 0 | BL42: 0 | BM42: 0 | BN42: 0 | BO42: N | BP42: Y | BQ42: Y | BR42: N | BS42: NULL | BT42: n/a | BU42: NULL | BV42: NULL | BW42: NULL | BX42: NULL | BY42: 0 | BZ42: NULL | CA42: NULL | CB42: 0 | CC42: NULL | CD42: 0 | CE42: NULL | CF42: NULL | CG42: NULL | CH42: 20 | CI42: MFP | CJ42: NULL | CK42: NULL | CL42: NULL | CM42: NULL | CN42: NULL | CO42: 0 | CP42: 0 | CQ42: 0 | CR42: NULL | CS42: NULL | CT42: NULL | CU42: NULL | CV42: 21
A43: 22 | B43: MCDO01 | C43: MCDO01 | D43: 4215 | E43: SUITE 1 SOUTHPORT CHASE | F43: 19 EXPO COURT | G43: SOUTHPORT | H43: SOUTHPORT | I43: QLD | J43: 4215 | K43: AUSTRALIA | L43: NULL | M43: NULL | N43: (07) 5591 4911 | O43: NULL | P43: NULL | Q43: NULL | R43: (07) 5591 4983 | S43: 20010803 | T43: 2 | U43: MISC | V43: O | W43: M | X43: 50000 | Y43: =LEFT(S43,4) -> 2001 | Z43: =RIGHT(S43,4) -> 0803 | AA43: =LEFT(Z43,2) -> 08 | AB43: =RIGHT(Z43,2) -> 03 | AC43: =CONCATENATE(Y43,"-",AA43,"-",AB43) -> 2001-08-03 | AD43: NULL | AE43: NULL | AF43: USD | AG43: NULL | AH43: N | AI43: LOC | AJ43: NULL | AK43: 14 | AL43: 0 | AM43: 0 | AN43: N | AO43: 0 | AP43: NULL | AQ43: NULL | AR43: NULL | AS43: 0 | AT43: 0 | AU43: 0 | AV43: 0 | AW43: 0 | AX43: 0 | AY43: 0 | AZ43: 0 | BA43: 0 | BB43: 0 | BC43: 0 | BD43: 0 | BE43: 0 | BF43: 0 | BG43: 0 | BH43: NULL | BI43: NULL | BJ43: 20110131 | BK43: 0 | BL43: 0 | BM43: 0 | BN43: 0 | BO43: N | BP43: Y | BQ43: Y | BR43: N | BS43: NULL | BT43: ABN | BU43: NULL | BV43: NULL | BW43: NULL | BX43: NULL | BY43: 0 | BZ43: NULL | CA43: NULL | CB43: 0 | CC43: NULL | CD43: 0 | CE43: NULL | CF43: NULL | CG43: NULL | CH43: 26 | CI43: NULL | CJ43: NULL | CK43: NULL | CL43: NULL | CM43: NULL | CN43: NULL | CO43: 0 | CP43: 0 | CQ43: 0 | CR43: NULL | CS43: NULL | CT43: NULL | CU43: NULL | CV43: 22
A44: 23 | B44: MCDO02 | C44: MCDO02 | D44: 4215 | E44: SUITE 1 SOUTHPORT CHASE | F44: 19 EXPO COURT | G44: SOUTHPORT | H44: SOUTHPORT | I44: QLD | J44: 4215 | K44: AUSTRALIA | L44: NULL | M44: NULL | N44: 07 5591 4911 | O44: NULL | P44: NULL | Q44: NULL | R44: 07 5591 4983 | S44: 20010803 | T44: 2 | U44: MISC | V44: O | W44: M | X44: 50000 | Y44: =LEFT(S44,4) -> 2001 | Z44: =RIGHT(S44,4) -> 0803 | AA44: =LEFT(Z44,2) -> 08 | AB44: =RIGHT(Z44,2) -> 03 | AC44: =CONCATENATE(Y44,"-",AA44,"-",AB44) -> 2001-08-03 | AD44: NULL | AE44: US | AF44: USD | AG44: NULL | AH44: N | AI44: LOC | AJ44: NULL | AK44: 14 | AL44: 0 | AM44: 0 | AN44: N | AO44: 0 | AP44: NULL | AQ44: NULL | AR44: NULL | AS44: 0 | AT44: 0 | AU44: 0 | AV44: 0 | AW44: 0 | AX44: 0 | AY44: 0 | AZ44: 80407.96 | BA44: 20030227 | BB44: 7695 | BC44: 0 | BD44: 0 | BE44: 0 | BF44: 20030319 | BG44: 14879.7 | BH44: NULL | BI44: NULL | BJ44: 20110131 | BK44: 0 | BL44: 0 | BM44: 0 | BN44: 0 | BO44: N | BP44: Y | BQ44: Y | BR44: N | BS44: NULL | BT44: ABN | BU44: NULL | BV44: NULL | BW44: NULL | BX44: NULL | BY44: 0 | BZ44: NULL | CA44: NULL | CB44: 0 | CC44: NULL | CD44: 0 | CE44: NULL | CF44: NULL | CG44: NULL | CH44: 26 | CI44: MFP | CJ44: NULL | CK44: NULL | CL44: NULL | CM44: NULL | CN44: NULL | CO44: 0 | CP44: 0 | CQ44: 0 | CR44: NULL | CS44: NULL | CT44: NULL | CU44: NULL | CV44: 23
A45: 24 | B45: MEXI02 | C45: MEXI02 | D45: 48216 | E45: ATT : PATTY ODELL | F45: 1801 HOWARD STREET | G45: DETROIT | H45: DETROIT | I45: MI | J45: 48216 | K45: USA | L45: PATTY O'DELL | M45: NULL | N45: 313 963 6114 | O45: 313 963 6217 | P45: NULL | Q45: NULL | R45: NULL | S45: 19981130 | T45: 2 | U45: MCUEX | V45: O | W45: M | X45: NULL | Y45: =LEFT(S45,4) -> 1998 | Z45: =RIGHT(S45,4) -> 1130 | AA45: =LEFT(Z45,2) -> 11 | AB45: =RIGHT(Z45,2) -> 30 | AC45: =CONCATENATE(Y45,"-",AA45,"-",AB45) -> 1998-11-30 | AD45: NULL | AE45: MX | AF45: USD | AG45: NULL | AH45: N | AI45: AF | AJ45: NULL | AK45: 30 | AL45: 0 | AM45: 0 | AN45: N | AO45: NO | AP45: NULL | AQ45: NULL | AR45: NULL | AS45: 0 | AT45: 0 | AU45: 0 | AV45: 0 | AW45: 0 | AX45: 0 | AY45: 0 | AZ45: 95820.97 | BA45: 20000705 | BB45: -1675.26 | BC45: 0 | BD45: 0 | BE45: 0 | BF45: 20010108 | BG45: 885 | BH45: NULL | BI45: NULL | BJ45: 20110131 | BK45: 0 | BL45: 0 | BM45: 0 | BN45: 0 | BO45: N | BP45: Y | BQ45: Y | BR45: N | BS45: NULL | BT45: n/a | BU45: NULL | BV45: NULL | BW45: NULL | BX45: NULL | BY45: 0 | BZ45: NULL | CA45: NULL | CB45: 0 | CC45: NULL | CD45: 69000000 | CE45: NULL | CF45: NULL | CG45: NULL | CH45: 20 | CI45: MFP | CJ45: NULL | CK45: NULL | CL45: NULL | CM45: NULL | CN45: NULL | CO45: 0 | CP45: 0 | CQ45: 0 | CR45: MEXI02 | CS45: NULL | CT45: NULL | CU45: NULL | CV45: 24
A46: 25 | B46: MORI01 | C46: MORI01 | D46: 46241 | E46: 915 WESTERN DRIVE | F46: NULL | G46: INDIANAPOLIS | H46: INDIANAPOLIS | I46: IN | J46: 46241 | K46: USA | L46: Mr. Kurt Greaser | M46: NULL | N46: 0011 1 317 484 5555 | O46: NULL | P46: NULL | Q46: NULL | R46: 0015 1 317 484 5565 | S46: 19980701 | T46: 2 | U46: MCUEX | V46: O | W46: M | X46: 1500000 | Y46: =LEFT(S46,4) -> 1998 | Z46: =RIGHT(S46,4) -> 0701 | AA46: =LEFT(Z46,2) -> 07 | AB46: =RIGHT(Z46,2) -> 01 | AC46: =CONCATENATE(Y46,"-",AA46,"-",AB46) -> 1998-07-01 | AD46: NULL | AE46: MX | AF46: USD | AG46: NULL | AH46: N | AI46: AF | AJ46: NULL | AK46: 30 | AL46: 0 | AM46: 0 | AN46: N | AO46: 0 | AP46: NULL | AQ46: NULL | AR46: NULL | AS46: 0 | AT46: 0 | AU46: 0 | AV46: 0 | AW46: 0 | AX46: 0 | AY46: -4264.8 | AZ46: 2541959.9 | BA46: 20070509 | BB46: 162.9 | BC46: 0 | BD46: 0 | BE46: 0 | BF46: 20070716 | BG46: 162.9 | BH46: NULL | BI46: NULL | BJ46: 20110131 | BK46: 0 | BL46: 0 | BM46: 0 | BN46: 0 | BO46: N | BP46: Y | BQ46: Y | BR46: N | BS46: NULL | BT46: n/a | BU46: NULL | BV46: NULL | BW46: NULL | BX46: NULL | BY46: 0 | BZ46: NULL | CA46: NULL | CB46: 0 | CC46: NULL | CD46: 72000000 | CE46: NULL | CF46: NULL | CG46: 11519786 | CH46: 18 | CI46: MFP | CJ46: 2.84 | CK46: NULL | CL46: NULL | CM46: NULL | CN46: NULL | CO46: 0 | CP46: 0 | CQ46: 0 | CR46: MORI01 | CS46: NULL | CT46: NULL | CU46: NULL | CV46: 25
A47: 26 | B47: ONTA01 | C47: ONTA01 | D47: 2Y7 | E47: 993 BUCKSKIN WAY | F47: ORLEANS | G47: ONTARIO K1C | H47: ONTARIO K1C | I47: NULL | J47: 2Y7 | K47: CANADA | L47: NULL | M47: NULL | O47: NULL | P47: NULL | Q47: NULL | R47: NULL | S47: 20000622 | T47: 8 | U47: MSUEX | V47: O | W47: M | X47: 1000 | Y47: =LEFT(S47,4) -> 2000 | Z47: =RIGHT(S47,4) -> 0622 | AA47: =LEFT(Z47,2) -> 06 | AB47: =RIGHT(Z47,2) -> 22 | AC47: =CONCATENATE(Y47,"-",AA47,"-",AB47) -> 2000-06-22 | AD47: NULL | AE47: NULL | AF47: USD | AG47: NULL | AH47: N | AI47: SEA | AJ47: NULL | AK47: 30 | AL47: 0 | AM47: 0 | AN47: N | AO47: NO | AP47: NULL | AQ47: NULL | AR47: NULL | AS47: 0 | AT47: 0 | AU47: 0 | AV47: 0 | AW47: 0 | AX47: 0 | AY47: 0 | AZ47: 99263.16 | BA47: 20040315 | BB47: -0.64 | BC47: 0 | BD47: 0 | BE47: 0 | BF47: 20020404 | BG47: 43008.64 | BH47: NULL | BI47: NULL | BJ47: 20110131 | BK47: 0 | BL47: 0 | BM47: 0 | BN47: 0 | BO47: N | BP47: Y | BQ47: Y | BR47: N | BS47: L/C | BT47: n/a | BU47: NULL | BV47: NULL | BW47: NULL | BX47: NULL | BY47: 0 | BZ47: NULL | CA47: NULL | CB47: 0 | CC47: NULL | CD47: 0 | CE47: NULL | CF47: NULL | CG47: NULL | CH47: 20 | CI47: THI | CJ47: NULL | CK47: NULL | CL47: NULL | CM47: NULL | CN47: NULL | CO47: 0 | CP47: 0 | CQ47: 0 | CR47: NULL | CS47: NULL | CT47: NULL | CU47: NULL | CV47: 26
A48: 43 | B48: PEARL01 | C48: PEARL01 | D48: 11030 | E48: 390 PLANDOME ROAD | F48: NULL | G48: MANHASSET | H48: MANHASSET | I48: NY | J48: 11030 | K48: USA | L48: SELENA LAU | M48: RUTH KAMALI | N48: 516-627-4000 | O48: 516-627-4067 | P48: NULL | Q48: NULL | R48: NULL | S48: 20130124 | T48: 2 | U48: MISC | V48: O | W48: M | X48: NULL | Y48: =LEFT(S48,4) -> 2013 | Z48: =RIGHT(S48,4) -> 0124 | AA48: =LEFT(Z48,2) -> 01 | AB48: =RIGHT(Z48,2) -> 24 | AC48: =CONCATENATE(Y48,"-",AA48,"-",AB48) -> 2013-01-24 | AD48: NULL | AE48: NULL | AF48: USD | AG48: NULL | AH48: N | AI48: LOC | AJ48: NULL | AK48: COD | AL48: 0 | AM48: 0 | AN48: N | AO48: 0 | AP48: NULL | AQ48: NULL | AR48: NULL | AS48: 0 | AT48: 0 | AU48: 0 | AV48: 0 | AW48: 0 | AX48: 0 | AY48: 1502789.4 | AZ48: 1502789.4 | BA48: 20180704 | BB48: 27889.74 | BC48: 0 | BD48: 0 | BE48: 0 | BF48: 0 | BG48: 0 | BH48: NULL | BI48: NULL | BJ48: 0 | BK48: 0 | BL48: 0 | BM48: 0 | BN48: 0 | BO48: N | BP48: Y | BQ48: Y | BR48: N | BS48: NULL | BT48: NULL | BU48: NULL | BV48: NULL | BW48: NULL | BX48: NULL | BY48: 0 | BZ48: NULL | CA48: NULL | CB48: 0 | CC48: NULL | CD48: 69000000 | CE48: NULL | CF48: NULL | CG48: NULL | CH48: 26 | CI48: NULL | CJ48: NULL | CK48: NULL | CL48: NULL | CM48: NULL | CN48: NULL | CO48: 0 | CP48: 0 | CQ48: 0 | CR48: NULL | CS48: NULL | CT48: NULL | CU48: NULL | CV48: 43
A49: 45 | B49: PLFNY1 | C49: PLFNY1 | D49: 12095 | E49: 11-21 INDUSTRIAL PARK | F49: NULL | G49: JOHNSTOWN | H49: JOHNSTOWN | I49: NY | J49: 12095 | K49: USA | L49: JOHN RUGGIERO | M49: NULL | N49: 518-762-4543 | O49: NULL | P49: NULL | Q49: NULL | R49: NULL | S49: 20150831 | T49: 2 | U49: MCUEX | V49: O | W49: M | X49: 3000000 | Y49: =LEFT(S49,4) -> 2015 | Z49: =RIGHT(S49,4) -> 0831 | AA49: =LEFT(Z49,2) -> 08 | AB49: =RIGHT(Z49,2) -> 31 | AC49: =CONCATENATE(Y49,"-",AA49,"-",AB49) -> 2015-08-31 | AD49: NULL | AE49: US | AF49: USD | AG49: NULL | AH49: N | AI49: LOC | AJ49: NULL | AK49: 5 | AL49: 0 | AM49: 0 | AN49: N | AO49: 0 | AP49: NULL | AQ49: NULL | AR49: NULL | AS49: 0 | AT49: 0 | AU49: 0 | AV49: 0 | AW49: 0 | AX49: 0 | AY49: 0 | AZ49: 152.01 | BA49: 20160825 | BB49: -152.01 | BC49: 0 | BD49: 0 | BE49: 0 | BF49: 0 | BG49: 0 | BH49: NULL | BI49: NULL | BJ49: 0 | BK49: 0 | BL49: 0 | BM49: 0 | BN49: 0 | BO49: N | BP49: Y | BQ49: Y | BR49: N | BS49: NULL | BT49: NULL | BU49: NULL | BV49: NULL | BW49: NULL | BX49: NULL | BY49: 0 | BZ49: NULL | CA49: NULL | CB49: 0 | CC49: NULL | CD49: 69000000 | CE49: NULL | CF49: NULL | CG49: NULL | CH49: 26 | CI49: MFP | CJ49: NULL | CK49: NULL | CL49: NULL | CM49: NULL | CN49: NULL | CO49: 0 | CP49: 0 | CQ49: 0 | CR49: NULL | CS49: NULL | CT49: jruggiero@pearlleather.com | CU49: NULL | CV49: 45
A50: 44 | B50: PSALES | C50: PSALES | D50: 48009 | E50: 523 ARGYLE | F50: NULL | G50: BIRMINGHAM | H50: BIRMINGHAM | I50: MI | J50: 48009 | K50: USA | L50: BILL REID | M50: NULL | N50: 248-505-7417 | O50: NULL | P50: NULL | Q50: NULL | R50: NULL | S50: 20150831 | T50: 2 | U50: MCUEX | V50: O | W50: M | X50: 3000000 | Y50: =LEFT(S50,4) -> 2015 | Z50: =RIGHT(S50,4) -> 0831 | AA50: =LEFT(Z50,2) -> 08 | AB50: =RIGHT(Z50,2) -> 31 | AC50: =CONCATENATE(Y50,"-",AA50,"-",AB50) -> 2015-08-31 | AD50: NULL | AE50: US | AF50: USD | AG50: NULL | AH50: N | AI50: LOC | AJ50: NULL | AK50: 5 | AL50: 0 | AM50: 0 | AN50: N | AO50: 0 | AP50: NULL | AQ50: NULL | AR50: NULL | AS50: 0 | AT50: 0 | AU50: 0 | AV50: 0 | AW50: 0 | AX50: 0 | AY50: 0 | AZ50: 0 | BA50: 20160813 | BB50: 0 | BC50: 0 | BD50: 0 | BE50: 0 | BF50: 0 | BG50: 0 | BH50: NULL | BI50: NULL | BJ50: 0 | BK50: 0 | BL50: 0 | BM50: 0 | BN50: 0 | BO50: N | BP50: Y | BQ50: Y | BR50: N | BS50: NULL | BT50: NULL | BU50: NULL | BV50: NULL | BW50: NULL | BX50: NULL | BY50: 0 | BZ50: NULL | CA50: NULL | CB50: 0 | CC50: NULL | CD50: 69000000 | CE50: NULL | CF50: NULL | CG50: NULL | CH50: 26 | CI50: MFP | CJ50: NULL | CK50: NULL | CL50: NULL | CM50: NULL | CN50: NULL | CO50: 0 | CP50: 0 | CQ50: 0 | CR50: NULL | CS50: NULL | CT50: william.a.reid@att.net | CU50: NULL | CV50: 44
A51: 27 | B51: TECH01 | C51: TECH01 | D51: 48187-3669 | E51: 42015 FORD ROAD BOX 358 | F51: NULL | G51: CANTON | H51: CANTON | I51: MI | J51: 48187-3669 | K51: USA | L51: CECILIA RODRIGUEZ | M51: NULL | O51: NULL | P51: NULL | Q51: NULL | R51: NULL | S51: 20000131 | T51: 2 | U51: MCUEX | V51: O | W51: M | X51: 600000 | Y51: =LEFT(S51,4) -> 2000 | Z51: =RIGHT(S51,4) -> 0131 | AA51: =LEFT(Z51,2) -> 01 | AB51: =RIGHT(Z51,2) -> 31 | AC51: =CONCATENATE(Y51,"-",AA51,"-",AB51) -> 2000-01-31 | AD51: NULL | AE51: US | AF51: USD | AG51: NULL | AH51: N | AI51: AF | AJ51: NULL | AK51: 30 | AL51: 0 | AM51: 0 | AN51: N | AO51: NO | AP51: NULL | AQ51: NULL | AR51: NULL | AS51: 0 | AT51: 0 | AU51: 0 | AV51: 0 | AW51: 0 | AX51: 0 | AY51: 18397.21 | AZ51: 275307.3 | BA51: 20091026 | BB51: -500 | BC51: 0 | BD51: 0 | BE51: 0 | BF51: 20090825 | BG51: 1938.6 | BH51: NULL | BI51: NULL | BJ51: 20110131 | BK51: 0 | BL51: 0 | BM51: 0 | BN51: -0.01 | BO51: Y | BP51: Y | BQ51: Y | BR51: N | BS51: NULL | BT51: n/a | BU51: NULL | BV51: NULL | BW51: NULL | BX51: NULL | BY51: 0 | BZ51: NULL | CA51: NULL | CB51: 0 | CC51: NULL | CD51: 69000000 | CE51: NULL | CF51: NULL | CG51: 14000774 | CH51: 20 | CI51: MFP | CJ51: 2.74 | CK51: 2.79 | CL51: NULL | CM51: NULL | CN51: NULL | CO51: 0 | CP51: 0 | CQ51: -0.01 | CR51: NULL | CS51: NULL | CT51: NULL | CU51: NULL | CV51: 27
A52: 35 | B52: TENN01 | C52: TENN01 | D52: 78852 | E52: 2262 SAN JUAN DRIVE | F52: EAGLE PASS | G52: NULL | H52: NULL | I52: TX | J52: 78852 | K52: USA | L52: NORMA GUTIERREZ | M52: NULL | N52: 111528787830150 | O52: NULL | P52: NULL | Q52: NULL | R52: NULL | S52: 20050815 | T52: 2 | U52: MCUEX | V52: O | W52: M | X52: NULL | Y52: =LEFT(S52,4) -> 2005 | Z52: =RIGHT(S52,4) -> 0815 | AA52: =LEFT(Z52,2) -> 08 | AB52: =RIGHT(Z52,2) -> 15 | AC52: =CONCATENATE(Y52,"-",AA52,"-",AB52) -> 2005-08-15 | AD52: NULL | AE52: NULL | AF52: USD | AG52: NULL | AH52: N | AI52: LOC | AJ52: NULL | AK52: 30 | AL52: 0 | AM52: 0 | AN52: N | AO52: 0 | AP52: NULL | AQ52: NULL | AR52: NULL | AS52: 0 | AT52: 0 | AU52: 0 | AV52: 0 | AW52: 0 | AX52: 0 | AY52: 0 | AZ52: 76308.22 | BA52: 20081209 | BB52: -17802.02 | BC52: 0 | BD52: 0 | BE52: 0 | BF52: 20080903 | BG52: 1738.52 | BH52: NULL | BI52: NULL | BJ52: 20110131 | BK52: 0 | BL52: 0 | BM52: 0 | BN52: 0 | BO52: N | BP52: Y | BQ52: Y | BR52: N | BS52: NULL | BT52: NA | BU52: NULL | BV52: NULL | BW52: NULL | BX52: NULL | BY52: 0 | BZ52: NULL | CA52: NULL | CB52: 0 | CC52: NULL | CD52: 65000000 | CE52: NULL | CF52: NULL | CG52: NULL | CH52: 26 | CI52: MPF | CJ52: NULL | CK52: NULL | CL52: NULL | CM52: NULL | CN52: NULL | CO52: 0 | CP52: 0 | CQ52: 0 | CR52: NULL | CS52: NULL | CT52: NULL | CU52: NULL | CV52: 35
A53: 28 | B53: UNIV01 | C53: UNIV01 | D53: 48071-0541 | E53: PO BOX 71541 | F53: NULL | G53: MADISON HEIGHTS | H53: MADISON HEIGHTS | I53: MI | J53: 48071-0541 | K53: USA | L53: MARY KEHOE | M53: NULL | N53: 248 5869118 | O53: NULL | P53: NULL | Q53: NULL | R53: 248 6425154 | S53: 20000125 | T53: 2 | U53: MCUEX | V53: O | W53: M | X53: 100000 | Y53: =LEFT(S53,4) -> 2000 | Z53: =RIGHT(S53,4) -> 0125 | AA53: =LEFT(Z53,2) -> 01 | AB53: =RIGHT(Z53,2) -> 25 | AC53: =CONCATENATE(Y53,"-",AA53,"-",AB53) -> 2000-01-25 | AD53: NULL | AE53: MX | AF53: USD | AG53: NULL | AH53: N | AI53: AF | AJ53: NULL | AK53: 30 | AL53: 0 | AM53: 0 | AN53: N | AO53: NO | AP53: NULL | AQ53: NULL | AR53: NULL | AS53: 0 | AT53: 0 | AU53: 0 | AV53: 0 | AW53: 0 | AX53: 0 | AY53: 0 | AZ53: 274765.24 | BA53: 20070130 | BB53: -5456 | BC53: 0 | BD53: 0 | BE53: 0 | BF53: 20040201 | BG53: 3300 | BH53: NULL | BI53: NULL | BJ53: 20110131 | BK53: 0 | BL53: 0 | BM53: 0 | BN53: 0 | BO53: N | BP53: Y | BQ53: Y | BR53: N | BS53: NULL | BT53: n/a | BU53: NULL | BV53: NULL | BW53: NULL | BX53: NULL | BY53: 0 | BZ53: NULL | CA53: NULL | CB53: 0 | CC53: NULL | CD53: 70000000 | CE53: NULL | CF53: NULL | CG53: 10594456 | CH53: 20 | CI53: MFP | CJ53: 3.07 | CK53: NULL | CL53: 3.03 | CM53: NULL | CN53: NULL | CO53: 0 | CP53: 0 | CQ53: 0 | CR53: UNIV01A | CS53: NULL | CT53: NULL | CU53: NULL | CV53: 28
A54: 50 | B54: VALT01 | C54: VALT01 | D54: 32000 | E54: FRAY GARCIA DE SAN FRANCISCO NO. 880 | F54: COL. BELLAVISTA | G54: JUAREZ | H54: JUAREZ | I54: CHIH | J54: 32000 | K54: MEXICO | L54: RICARDO VALTIERRA | M54: NULL | N54: 6564011973 | O54: NULL | P54: NULL | Q54: NULL | R54: NULL | S54: 20190319 | T54: 2 | U54: MFUEX | V54: O | W54: M | X54: NULL | Y54: =LEFT(S54,4) -> 2019 | Z54: =RIGHT(S54,4) -> 0319 | AA54: =LEFT(Z54,2) -> 03 | AB54: =RIGHT(Z54,2) -> 19 | AC54: =CONCATENATE(Y54,"-",AA54,"-",AB54) -> 2019-03-19 | AD54: NULL | AE54: NULL | AF54: USD | AG54: NULL | AH54: N | AI54: LOC | AJ54: NULL | AK54: COD | AL54: 0 | AM54: 0 | AN54: N | AO54: 0 | AP54: NULL | AQ54: NULL | AR54: NULL | AS54: 0 | AT54: 0 | AU54: 0 | AV54: 0 | AW54: 0 | AX54: 0 | AY54: 0 | AZ54: 0 | BA54: 0 | BB54: 0 | BC54: 0 | BD54: 0 | BE54: 0 | BF54: 0 | BG54: 0 | BH54: NULL | BI54: NULL | BJ54: 0 | BK54: 0 | BL54: 0 | BM54: 0 | BN54: 0 | BO54: N | BP54: Y | BQ54: Y | BR54: N | BS54: NULL | BT54: NULL | BU54: NULL | BV54: NULL | BW54: NULL | BX54: NULL | BY54: 0 | BZ54: NULL | CA54: NULL | CB54: 0 | CC54: NULL | CD54: 69000000 | CE54: NULL | CF54: NULL | CG54: NULL | CH54: 26 | CI54: JZ | CJ54: NULL | CK54: NULL | CL54: NULL | CM54: NULL | CN54: NULL | CO54: 0 | CP54: 0 | CQ54: 0 | CR54: NULL | CS54: NULL | CT54: NULL | CU54: NULL | CV54: 50
A55: 31 | B55: VISU01 | C55: VISU01 | D55: 48304-2263 | E55: 41000 WOODWARD AVENUE | F55: NULL | G55: BLOOMFIELD HILLS | H55: BLOOMFIELD HILLS | I55: MI | J55: 48304-2263 | K55: USA | L55: NULL | M55: NULL | O55: NULL | P55: NULL | Q55: NULL | R55: NULL | S55: 20011118 | T55: 2 | U55: MFUEX | V55: O | W55: M | X55: 20000 | Y55: =LEFT(S55,4) -> 2001 | Z55: =RIGHT(S55,4) -> 1118 | AA55: =LEFT(Z55,2) -> 11 | AB55: =RIGHT(Z55,2) -> 18 | AC55: =CONCATENATE(Y55,"-",AA55,"-",AB55) -> 2001-11-18 | AD55: NULL | AE55: NULL | AF55: USD | AG55: NULL | AH55: N | AI55: LOC | AJ55: NULL | AK55: 15 | AL55: 0 | AM55: 0 | AN55: N | AO55: 0 | AP55: NULL | AQ55: NULL | AR55: NULL | AS55: 0 | AT55: 0 | AU55: 0 | AV55: 0 | AW55: 0 | AX55: 0 | AY55: 0 | AZ55: 1485 | BA55: 20021120 | BB55: 660 | BC55: 0 | BD55: 0 | BE55: 0 | BF55: 20030121 | BG55: 660 | BH55: NULL | BI55: NULL | BJ55: 20110131 | BK55: 0 | BL55: 0 | BM55: 0 | BN55: 0 | BO55: N | BP55: Y | BQ55: Y | BR55: N | BS55: NULL | BT55: N/A | BU55: NULL | BV55: NULL | BW55: NULL | BX55: NULL | BY55: 0 | BZ55: NULL | CA55: NULL | CB55: 0 | CC55: NULL | CD55: 0 | CE55: NULL | CF55: NULL | CG55: NULL | CH55: 26 | CI55: MFP | CJ55: NULL | CK55: NULL | CL55: NULL | CM55: NULL | CN55: NULL | CO55: 0 | CP55: 0 | CQ55: 0 | CR55: NULL | CS55: NULL | CT55: NULL | CU55: NULL | CV55: 31
A56: 36 | B56: WOOD01 | C56: WOOD01 | D56: 25900 | E56: SALTILLO MONTERREY KM1150 | F56: PARQUE INDUSTRIAL RAMOS ARIZPE | G56: RAMOS ARIZPE | H56: RAMOS ARIZPE | I56: COAH | J56: 25900 | K56: MEX | L56: BRIAN TANNER | N56: 519 676 3626 | R56: 313 982 9198 | S56: 20060130 | T56: 2 | U56: MFUEX | V56: O | W56: M | X56: 10000 | Y56: =LEFT(S56,4) -> 2006 | Z56: =RIGHT(S56,4) -> 0130 | AA56: =LEFT(Z56,2) -> 01 | AB56: =RIGHT(Z56,2) -> 30 | AC56: =CONCATENATE(Y56,"-",AA56,"-",AB56) -> 2006-01-30 | AD56: NULL | AE56: NULL | AF56: USD | AG56: NULL | AH56: N | AI56: LOC | AJ56: NULL | AK56: 10 | AL56: 0 | AM56: 0 | AN56: N | AO56: 0 | AP56: NULL | AQ56: NULL | AR56: NULL | AS56: 0 | AT56: 0 | AU56: 0 | AV56: 0 | AW56: 0 | AX56: 0 | AY56: 0 | AZ56: 7588.94 | BA56: 20060425 | BB56: 6599.95 | BC56: 0 | BD56: 0 | BE56: 0 | BF56: 20060815 | BG56: 6598.94 | BH56: NULL | BI56: NULL | BJ56: 20110131 | BK56: 0 | BL56: 0 | BM56: 0 | BN56: 0 | BO56: N | BP56: Y | BQ56: Y | BR56: N | BS56: NULL | BT56: NA | BU56: NULL | BV56: NULL | BW56: NULL | BX56: NULL | BY56: 0 | BZ56: NULL | CA56: NULL | CB56: 0 | CC56: NULL | CD56: 0 | CE56: NULL | CF56: NULL | CG56: NULL | CH56: 26 | CI56: MHI | CJ56: NULL | CK56: NULL | CL56: NULL | CM56: NULL | CN56: NULL | CO56: 0 | CP56: 0 | CQ56: 0 | CR56: NULL | CS56: NULL | CU56: NULL | CV56: 36
A57: 55 | B57: WPI003 | C57: WPI003 | D57: 48895 | E57: WILLIAMSTON PRODUCTS,INC | F57: 845 PROGRESS CT | G57: WILLIAMSTON | H57: WILLIAMSTON | I57: MI | J57: 48895 | S57: 20191204 | T57: 2 | U57: MCUEX | V57: O | W57: M | X57: 3000000 | Y57: =LEFT(S57,4) -> 2019 | Z57: =RIGHT(S57,4) -> 1204 | AA57: =LEFT(Z57,2) -> 12 | AB57: =RIGHT(Z57,2) -> 04 | AC57: =CONCATENATE(Y57,"-",AA57,"-",AB57) -> 2019-12-04 | AD57: NULL | AE57: US | AF57: USD | AG57: NULL | AH57: N | AI57: LOC | AJ57: NULL | AK57: 45 | AL57: 0 | AM57: 0 | AN57: N | AO57: 0 | AP57: NULL | AQ57: NULL | AR57: NULL | AS57: 0 | AT57: 0 | AU57: 0 | AV57: 0 | AW57: 0 | AX57: 0 | AY57: 0 | AZ57: 0 | BA57: 0 | BB57: 0 | BC57: 0 | BD57: 0 | BE57: 0 | BF57: 0 | BG57: 0 | BH57: NULL | BI57: NULL | BJ57: 0 | BK57: 0 | BL57: 0 | BM57: 0 | BN57: 0 | BO57: N | BP57: Y | BQ57: Y | BR57: N | BS57: NULL | BT57: NULL | BU57: NULL | BV57: NULL | BW57: NULL | BX57: NULL | BY57: 0 | BZ57: NULL | CA57: NULL | CB57: 0 | CC57: NULL | CD57: 69000000 | CE57: NULL | CF57: NULL | CG57: NULL | CH57: 26 | CI57: MFP | CJ57: NULL | CK57: NULL | CL57: NULL | CM57: NULL | CN57: NULL | CO57: 0 | CP57: 0 | CQ57: 0 | CR57: NULL | CS57: NULL | CU57: NULL | CV57: 55
A58: 53 | B58: YANG02 | C58: YANG02 | D58: 48152 | E58: 1935 WEST 12 MILE ROAD NOVI, MI 48377 | F58: NULL | G58: ROAD NOV | H58: ROAD NOV | I58: MI | J58: 48152 | K58: USA | M58: NULL | O58: NULL | P58: NULL | Q58: NULL | R58: NULL | S58: 20191119 | T58: 2 | U58: MCUEX | V58: O | W58: M | X58: 3000000 | Y58: =LEFT(S58,4) -> 2019 | Z58: =RIGHT(S58,4) -> 1119 | AA58: =LEFT(Z58,2) -> 11 | AB58: =RIGHT(Z58,2) -> 19 | AC58: =CONCATENATE(Y58,"-",AA58,"-",AB58) -> 2019-11-19 | AD58: NULL | AE58: US | AF58: USD | AG58: NULL | AH58: N | AI58: LOC | AJ58: NULL | AK58: 60 | AL58: 0 | AM58: 0 | AN58: N | AO58: 0 | AP58: NULL | AQ58: NULL | AR58: NULL | AS58: 0 | AT58: 0 | AU58: 0 | AV58: 0 | AW58: 0 | AX58: 0 | AY58: 0 | AZ58: 0 | BA58: 0 | BB58: 0 | BC58: 0 | BD58: 0 | BE58: 0 | BF58: 0 | BG58: 0 | BH58: NULL | BI58: NULL | BJ58: 0 | BK58: 0 | BL58: 0 | BM58: 0 | BN58: 0 | BO58: N | BP58: Y | BQ58: Y | BR58: N | BS58: NULL | BT58: NULL | BU58: NULL | BV58: NULL | BW58: NULL | BX58: NULL | BY58: 0 | BZ58: NULL | CA58: NULL | CB58: 0 | CC58: NULL | CD58: 69000000 | CE58: NULL | CF58: NULL | CG58: NULL | CH58: 26 | CI58: MFP | CJ58: NULL | CK58: NULL | CL58: NULL | CM58: NULL | CN58: NULL | CO58: 0 | CP58: 0 | CQ58: 0 | CR58: NULL | CS58: NULL | CT58: NULL | CU58: NULL | CV58: 53
A59: 58 | B59: YANG03 | C59: YANG03 | D59: 700/20 | E59: 700/20 WHA EASTERN SEABOARD INDUSTRIAL | F59: 1 MOO 7 TAMBOL KAOKANSONG, AMPHUR SRIRACH | G59: CHONBURI | H59: CHONBURI | J59: 700/20 | K59: THAILAND TAX ID:0205562018045 | L59: MR. ZHANG WENKANG | N59: 86 1306181 8985 | S59: 20201119 | T59: 11 | U59: MCUEX | V59: O | W59: M | X59: 3000000 | Y59: =LEFT(S59,4) -> 2020 | Z59: =RIGHT(S59,4) -> 1119 | AA59: =LEFT(Z59,2) -> 11 | AB59: =RIGHT(Z59,2) -> 19 | AC59: =CONCATENATE(Y59,"-",AA59,"-",AB59) -> 2020-11-19 | AD59: NULL | AE59: US | AF59: USD | AG59: NULL | AH59: N | AI59: 4 | AJ59: NULL | AK59: 30 | AL59: 0 | AM59: 0 | AN59: N | AO59: 0 | AP59: NULL | AQ59: NULL | AR59: NULL | AS59: 0 | AT59: 0 | AU59: 0 | AV59: 0 | AW59: 0 | AX59: 0 | AY59: 0 | AZ59: 0 | BA59: 0 | BB59: 0 | BC59: 0 | BD59: 0 | BE59: 0 | BF59: 0 | BG59: 0 | BH59: NULL | BI59: NULL | BJ59: 0 | BK59: 0 | BL59: 0 | BM59: 0 | BN59: 0 | BO59: N | BP59: Y | BQ59: Y | BR59: N | BS59: NULL | BT59: NULL | BU59: NULL | BV59: NULL | BW59: NULL | BX59: NULL | BY59: 0 | BZ59: NULL | CA59: NULL | CB59: 0 | CC59: NULL | CD59: 69000000 | CE59: NULL | CF59: NULL | CG59: NULL | CH59: 26 | CI59: MFP | CJ59: NULL | CK59: NULL | CL59: NULL | CM59: NULL | CN59: NULL | CO59: 0 | CP59: 0 | CQ59: 0 | CR59: NULL | CS59: NULL | CU59: NULL | CV59: 58
A60: 60 | B60: YANG04 | C60: YANG04 | D60: 700/20 | E60: 700/20 WHA EASTERN SEABOARD INDUSTRIAL | F60: 1 MOO 7 TAMBOL KAOKANSONG,AMPHUR SRIRACH | G60: CHONBURI | H60: CHONBURI | J60: 700/20 | K60: THAILAND | L60: YUENYONG NATTIDA | N60: 886211963 | S60: 20210111 | T60: 5 | U60: MFUEX | V60: O | W60: M | X60: 3000000 | Y60: =LEFT(S60,4) -> 2021 | Z60: =RIGHT(S60,4) -> 0111 | AA60: =LEFT(Z60,2) -> 01 | AB60: =RIGHT(Z60,2) -> 11 | AC60: =CONCATENATE(Y60,"-",AA60,"-",AB60) -> 2021-01-11 | AD60: NULL | AE60: US | AF60: USD | AG60: NULL | AH60: N | AI60: AF | AJ60: NULL | AK60: 30 | AL60: 0 | AM60: 0 | AN60: N | AO60: 0 | AP60: NULL | AQ60: NULL | AR60: NULL | AS60: 0 | AT60: 0 | AU60: 0 | AV60: 0 | AW60: 0 | AX60: 0 | AY60: 0 | AZ60: 0 | BA60: 0 | BB60: 0 | BC60: 0 | BD60: 0 | BE60: 0 | BF60: 0 | BG60: 0 | BH60: NULL | BI60: NULL | BJ60: 0 | BK60: 0 | BL60: 0 | BM60: 0 | BN60: 0 | BO60: N | BP60: Y | BQ60: Y | BR60: N | BS60: NULL | BT60: NULL | BU60: NULL | BV60: NULL | BW60: NULL | BX60: NULL | BY60: 0 | BZ60: NULL | CA60: NULL | CB60: 0 | CC60: NULL | CD60: NULL | CE60: NULL | CF60: NULL | CG60: NULL | CH60: 26 | CI60: MFP | CJ60: NULL | CK60: NULL | CL60: NULL | CM60: NULL | CN60: NULL | CO60: 0 | CP60: 0 | CQ60: 0 | CR60: NULL | CS60: NULL | CT60: NULL | CU60: NULL | CV60: 60
